Workbook

Sheet RESUMO
E3: RESUMO COMERCIAL
M5: OBRA
M6: ENG
H7: MARGEM REAL | J7: =G134 -> 0.12617233 | K7: VENDAS BRUTAS ULTIMOS 12 MESES | M7: 15000000
B8: ISENÇÃO PIS / COFINS | D8: NÃO | E8: COMISSÃO VENDEDOR EXTERNO | G8: 0 | H8: LUCRO MATERIAIS | J8: 0.1 | K8: PRAZO TOTAL (MESES) | M8: 2
B9: CONSUMIDOR FINAL | D9: SIM | E9: COMISSÃO REPRESENTANTE | G9: 0 | H9: LUCRO SERVIÇOS | J9: 0.1 | K9: ALÍQUOTA SIMPLES NACIONAL | M9: 0.12
B10: CONTRIBUINTE ICMS | D10: CONTRIBUINTE | E10: SERVIÇOS ENGENHARIA | G10: LUCRO REAL | H10: SERVIÇOS CAMPO | J10: LUCRO REAL | K10: MATERIAL | M10: LUCRO REAL
B11: ESTADO DESTINO | D11: SP
B13: SERVIÇOS DE ENGENHARIA | E13: Custo | F13: Venda Liq | G13: ENG | H13: DESPESAS DE ENGENHARIA | K13: Custo | L13: Venda Liq | M13: ENG
E14: =ServInt[[#Totals],[TOTAL]]+ServExt[[#Totals],[TOTAL]] -> 97488 | F14: =ServInt[[#Totals],[TOTAL3]]+ServExt[[#Totals],[TOTAL3]] -> 145539.29 | K14: ='SERVICOS AUTPRO'!L8+'SERVICOS AUTPRO'!L12+'SERVICOS AUTPRO'!L20 -> 44884 | L14: ='SERVICOS AUTPRO'!F8+'SERVICOS AUTPRO'!F12+'SERVICOS AUTPRO'!H20 -> 74620.834
B15: Impostos | C15: (+) Pis | E15: =IF($D$8="SIM",0%,IF($G$10=BASE!$Z$2,BASE!AB3,IF($G$10=BASE!$AC$2,BASE!AE3,IF($G$10=BASE!$AF$2,BASE!AH3,IF($G$10=BASE!$AI$2,BASE!AK3,BASE!AN3))))) -> 0.0165 | F15: =($F$21*E15) -> 2705.8009 | H15: Impostos | I15: (+) Pis | K15: =IF($D$8="SIM",0%,IF($G$10=BASE!$Z$2,BASE!AB3,IF($G$10=BASE!$AC$2,BASE!AE3,IF($G$10=BASE!$AF$2,BASE!AH3,IF($G$10=BASE!$AI$2,BASE!AK3,BASE!AN3))))) -> 0.0165 | L15: =($L$21*K15) -> 1435.8528
C16: (+) Cofins | E16: =IF($D$8="SIM",0%,IF($G$10=BASE!$Z$2,BASE!AB4,IF($G$10=BASE!$AC$2,BASE!AE4,IF($G$10=BASE!$AF$2,BASE!AH4,IF($G$10=BASE!$AI$2,BASE!AK4,BASE!AN4))))) -> 0.076 | F16: =($F$21*E16) -> 12463.083 | I16: (+) Cofins | K16: =IF($D$8="SIM",0%,IF($G$10=BASE!$Z$2,BASE!AB4,IF($G$10=BASE!$AC$2,BASE!AE4,IF($G$10=BASE!$AF$2,BASE!AH4,IF($G$10=BASE!$AI$2,BASE!AK4,BASE!AN4))))) -> 0.076 | L16: =($L$21*K16) -> 6613.625
C17: (+) Simples Nacional | E17: =IF($G$10=BASE!$Z$2,BASE!AB5,IF($G$10=BASE!$AC$2,BASE!AE5,IF($G$10=BASE!$AF$2,BASE!AH5,IF($G$10=BASE!$AI$2,BASE!AK5,BASE!AN5)))) -> 0 | F17: =($F$21*E17) -> 0 | I17: (+) Simples Nacional | K17: =IF($G$10=BASE!$Z$2,BASE!AB5,IF($G$10=BASE!$AC$2,BASE!AE5,IF($G$10=BASE!$AF$2,BASE!AH5,IF($G$10=BASE!$AI$2,BASE!AK5,BASE!AN5)))) -> 0 | L17: =($L$21*K17) -> 0
C18: (+) Iss | E18: 0.02 | F18: =($F$21*E19) -> 0 | I18: (+) Iss | K18: 0.05 | L18: =($L$21*K18) -> 4351.069
F19: =($F$21*E20) -> 0 | L19: =($L$21*K19) -> 0
F20: =($F$21*E21) -> 0 | L20: =($L$21*K20) -> 0
B21: Sub-Total: | F21: =(F14/(100%-SUM(E15:E18))) -> 163987.93 | H21: Sub-Total: | L21: =(L14/(100%-SUM(K15:K18))) -> 87021.381
B22: Sub-Total: | F22: =F20+F21 -> 163987.93 | H22: Sub-Total: | L22: =L20+L21 -> 87021.381
B23: SERVIÇOS DE MONTAGEM | E23: Custo | F23: Venda Liq | G23: OBRA | H23: DESPESAS DE MONTAGEM | K23: Custo | L23: Venda Liq | M23: OBRA
E24: =ServInt10[[#Totals],[TOTAL]]+ServExt8[[#Totals],[TOTAL]] -> 269517.6 | F24: =ServInt10[[#Totals],[TOTAL3]]+ServExt8[[#Totals],[TOTAL3]] -> 338123.27 | K24: ='SERVICOS MONTAGEM'!L7+'SERVICOS MONTAGEM'!L11+'SERVICOS MONTAGEM'!L19 -> 229642 | L24: ='SERVICOS MONTAGEM'!F7+'SERVICOS MONTAGEM'!F11+'SERVICOS MONTAGEM'!H19 -> 288097.34
B25: Impostos | C25: (+) Pis | E25: =IF($D$8="SIM",0%,IF($J$10=BASE!$Z$2,BASE!AB3,IF($J$10=BASE!$AC$2,BASE!AE3,IF($J$10=BASE!$AF$2,BASE!AH3,IF($J$10=BASE!$AI$2,BASE!AK3,BASE!AN3))))) -> 0.0165 | F25: =($F$31*E25) -> 6286.2355 | H25: Impostos | I25: (+) Pis | K25: =IF($D$8="SIM",0%,IF($G$10=BASE!$Z$2,BASE!AB3,IF($G$10=BASE!$AC$2,BASE!AE3,IF($G$10=BASE!$AF$2,BASE!AH3,IF($G$10=BASE!$AI$2,BASE!AK3,BASE!AN3))))) -> 0.0165 | L25: =($L$31*K25) -> 5356.176
C26: (+) Cofins | E26: =IF($D$8="SIM",0%,IF($J$10=BASE!$Z$2,BASE!AB4,IF($J$10=BASE!$AC$2,BASE!AE4,IF($J$10=BASE!$AF$2,BASE!AH4,IF($J$10=BASE!$AI$2,BASE!AK4,BASE!AN4))))) -> 0.076 | F26: =($F$31*E26) -> 28954.782 | I26: (+) Cofins | K26: =IF($D$8="SIM",0%,IF($G$10=BASE!$Z$2,BASE!AB4,IF($G$10=BASE!$AC$2,BASE!AE4,IF($G$10=BASE!$AF$2,BASE!AH4,IF($G$10=BASE!$AI$2,BASE!AK4,BASE!AN4))))) -> 0.076 | L26: =($L$31*K26) -> 24670.871
C27: (+) Simples Nacional | E27: =IF($J$10=BASE!$Z$2,BASE!AB5,IF($J$10=BASE!$AC$2,BASE!AE5,IF($J$10=BASE!$AF$2,BASE!AH5,IF($J$10=BASE!$AI$2,BASE!AK5,BASE!AN5)))) -> 0 | F27: =($F$31*E27) -> 0 | I27: (+) Simples Nacional | K27: =IF($G$10=BASE!$Z$2,BASE!AB5,IF($G$10=BASE!$AC$2,BASE!AE5,IF($G$10=BASE!$AF$2,BASE!AH5,IF($G$10=BASE!$AI$2,BASE!AK5,BASE!AN5)))) -> 0 | L27: =($L$31*K27) -> 0
C28: (+) Iss | E28: 0.02 | F28: =($F$31*E28) -> 7619.6794 | I28: (+) Iss | K28: 0.02 | L28: =($L$31*K28) -> 6492.3345
F29: =($F$31*E29) -> 0 | I29: (+) IR CSLL | L29: =($L$31*K29) -> 0
B31: Sub-Total: | F31: =(F24/(100%-SUM(E25:E29))) -> 380983.97 | H31: Sub-Total: | L31: =(L24/(100%-SUM(K25:K29))) -> 324616.72
B32: Sub-Total: | F32: =F30+F31 -> 380983.97 | H32: Sub-Total: | L32: =L30+L31 -> 324616.72
B33: TERCEIROS E LOCAÇÕES | E33: Custo | F33: Venda Liq | G33: SELECIONAR
E34: =ServTerc[[#Totals],[TOTAL CUSTO]] -> 177860 | F34: =ServTerc[[#Totals],[TOTAL VENDA]] -> 195820.93 | G34: OBRA
B35: Impostos | C35: (+) Pis | E35: =IF($G$34=$G$13,E15,E25) -> 0.0165 | F35: =($F$41*E35) -> 3640.6144 | I35: DESCRIÇÃO | K35: CÓDIGO / NCM | L35: VALOR S/ IPI | M35: VALOR C/ IPI
C36: (+) Cofins | E36: =IF($G$34=$G$13,E16,E26) -> 0.076 | F36: =($F$41*E36) -> 16768.89 | I36: SERVIÇOS DE ENGENHARIA | K36: 07.01 | L36: =IF(G34="ENG",F42+F22+L22,F22+L22) -> 251009.31 | M36: =L36 -> 251009.31
C37: (+) Simples Nacional | E37: =IF($G$34=$G$13,E17,E27) -> 0 | F37: =($F$41*E37) -> 0 | I37: SERVIÇOS DE INSTALAÇÃO OU OBRAS | K37: 14.01 / 14.06 / 07.02 | L37: =IF(G34="ENG",F32+L32,+F32+L32+F42) -> 926243.99 | M37: =L37 -> 926243.99
C38: (+) Iss | E38: =IF($G$34=$G$13,E18,E28) -> 0.02 | F38: =($F$41*E38) -> 4412.8659 | I38: SISTEMA DE ENERGIA | K38: 8537.20.90 | L38: =F55 -> 259656.49 | M38: =F58 -> 259656.49
F39: =($F$41*E39) -> 0 | I39: PAINÉIS/SISTEMA DE AUTOMAÇÃO | K39: 8537.10.90 | L39: =F70 -> 9430.4315 | M39: =F73 -> 9430.4315
I40: SUB TOTAL | L40: =SUM(L36:L39) -> 1446340.2 | M40: =SUM(M36:M39) -> 1446340.2
B41: Sub-Total: | F41: =(F34/(100%-SUM(E35:E39))) -> 220643.3 | I41: FATURAMENTO DIRETO | L41: ='FAT. DIRETO'!K43 -> 397106.92
B42: Sub-Total: | F42: =F40+F41 -> 220643.3 | I42: CONDIÇÃO DE PAGAMENTO | L42: 28 dias
B44: MATERIAIS CAMPO | E44: Custo | F44: Venda Liq | G44: MATERIAL DE CAMPO | I44: SINAL > 20% | L44: SIM
E45: =MateriaisCampo[[#Totals],[TOTAL C/ IPI]] -> 210754.89 | F45: =MateriaisCampo[[#Totals],[VENDA]] -> 204479.49
B46: Impostos | C46: (+) ICMS | E46: =IF(OR($M$10="EXPORTAÇÃO",$M$10="SIMPLES RESENDE",$M$10="SIMPLES YAMA"),0%,IF($D$11="SP",BASE!$AQ$40,BASE!$AQ$40)) -> 0.12 | F46: =IF(D9="SIM",E46*F58,E46*F55) -> 31158.779 | I46: TOTAL GERAL | L46: =L40+L41 -> 1843447.1 | M46: =M40+L41 -> 1843447.1
C47: (+) Pis | E47: =IF($D$8="SIM",0%,IF($M$10=BASE!$Z$2,BASE!AB3,IF($M$10=BASE!$AC$2,BASE!AE3,IF($M$10=BASE!$AF$2,BASE!AH3,IF($M$10=BASE!$AI$2,BASE!AK3,BASE!AN3))))) -> 0.0165 | F47: =($F$53*E47) -> 4284.3321
C48: (+) Cofins | E48: =IF($D$8="SIM",0%,IF($M$10=BASE!$Z$2,BASE!AB4,IF($M$10=BASE!$AC$2,BASE!AE4,IF($M$10=BASE!$AF$2,BASE!AH4,IF($M$10=BASE!$AI$2,BASE!AK4,BASE!AN4))))) -> 0.076 | F48: =($F$53*E48) -> 19733.893
C49: (+) Simples Nacional | E49: =IF($M$10=BASE!$Z$2,BASE!AB5,IF($M$10=BASE!$AC$2,BASE!AE5,IF($M$10=BASE!$AF$2,BASE!AH5,IF($M$10=BASE!$AI$2,BASE!AK5,BASE!AN5)))) -> 0 | F49: =($F$55*E49) -> 0 | L49: DESPESAS | M49: =SUM(L22,L32) -> 411638.11 | N49: 26225
L50: ENGENHARIA | M50: 26225 | N50: 128388.29
L51: SERVIÇOS TÉCNICOS E GESTÃO | M51: =F22-M50 -> 137762.93 | N51: 351175.49
L52: SERVIÇOS DE INSTALAÇÃO E SUPERVISÃO | M52: =F32 -> 380983.97 | N52: 391469.64
C53: Sub para cáculos | F53: =IF($D$9="NÃO",(F45/(100%-SUM(E46:E51))),(F45/(100%-SUM(E46:E51,E54)))) -> 259656.49 | L53: MAQUINÁRIO E LOGISTICAS | M53: =F42 -> 220643.3 | N53: 204535.53
C54: (+) IPI | E54: 0 | F54: =F58-F55 -> 0 | L54: MATERIAIS | M54: =SUM(L41,M39,M38) -> 666193.84 | N54: =SUM(N49:N53) -> 1101793.9
B55: SEM IPI | F55: =IF(E54=I120,F58,IF(E54=I121,K121,IF(E54=I122,K122,K123))) -> 259656.49 | M55: =SUM(M49:M54) -> 1843447.1
B56: UTILIZAR CRÉDITO ICMS: | E56: SIM | F56: =MateriaisCampo[[#Totals],[TOTAL ICMS $]] -> 33503.866
B57: UTILIZAR CRÉDITO IPI: | E57: SIM | F57: =MateriaisCampo[[#Totals],[TOTAL C/ IPI]]-MateriaisCampo[[#Totals],[TOTAL S/ IPI]] -> 4732.1489 | M57: 1102000
B58: TOTAL CAMPO: | F58: =IF($D$9="NÃO",F53+(E54*F53),F53) -> 259656.49 | M58: 238200
B59: MATERIAIS PAINEIS | E59: Custo | F59: Venda Liq | G59: MATERIAL DE PAINÉIS | K59: =M46-M62 -> 116448.27 | M59: 307300
E60: =MateriaisPainel[[#Totals],[TOTAL C/ IPI]] -> 7561.5 | F60: =MateriaisPainel[[#Totals],[VENDA]] -> 7426.4648 | M60: =SUM(M57:M59) -> 1647500
B61: Impostos | C61: (+) ICMS | E61: =IF(OR($M$10="EXPORTAÇÃO",$M$10="SIMPLES RESENDE",$M$10="SIMPLES YAMA"),0%,IF($D$11="SP",BASE!$AQ$40,BASE!$AQ$40)) -> 0.12 | F61: =IF(D9="SIM",E61*F73,E61*F68) -> 1131.6518
C62: (+) Pis | E62: =IF($D$8="SIM",0%,IF($M$10=BASE!$Z$2,BASE!AB3,IF($M$10=BASE!$AC$2,BASE!AE3,IF($M$10=BASE!$AF$2,BASE!AH3,IF($M$10=BASE!$AI$2,BASE!AK3,BASE!AN3))))) -> 0.0165 | F62: =($F$68*E62) -> 155.60212 | M62: 1726998.9
C63: (+) Cofins | E63: =IF($D$8="SIM",0%,IF($M$10=BASE!$Z$2,BASE!AB4,IF($M$10=BASE!$AC$2,BASE!AE4,IF($M$10=BASE!$AF$2,BASE!AH4,IF($M$10=BASE!$AI$2,BASE!AK4,BASE!AN4))))) -> 0.076 | F63: =($F$68*E63) -> 716.71279
C64: (+) Simples Nacional | E64: =IF($M$10=BASE!$Z$2,BASE!AB5,IF($M$10=BASE!$AC$2,BASE!AE5,IF($M$10=BASE!$AF$2,BASE!AH5,IF($M$10=BASE!$AI$2,BASE!AK5,BASE!AN5)))) -> 0 | F64: =($F$73*E64) -> 0
C68: Sub para cáculos | F68: =IF($D$9="NÃO",(F60/(100%-SUM(E61:E66))),(F60/(100%-SUM(E61:E66,E69)))) -> 9430.4315 | K68: =M62/M46 -> 0.93683124
C69: (+) IPI | E69: 0 | F69: =(F70*(1+E69))-F70 -> 0
B70: SEM IPI | F70: =IF(E69=I120,F73,IF(E69=I121,L121,IF(E69=I122,L122,L123))) -> 9430.4315
B71: UTILIZAR CRÉDITO ICMS: | E71: SIM | F71: =MateriaisPainel[[#Totals],[TOTAL ICMS $]] -> 852
B72: UTILIZAR CRÉDITO IPI: | E72: SIM | F72: =MateriaisPainel[[#Totals],[TOTAL C/ IPI]]-MateriaisPainel[[#Totals],[TOTAL S/ IPI]] -> 461.5
B73: TOTAL PAINÉIS: | F73: =IF($D$9="NÃO",F68+(E69*F68),F68) -> 9430.4315
B75: REVISÃO | C75: 45260
E96: RESUMO ADMINISTRATIVO
B104: DESCRIÇÃO | E104: CUSTO | F104: VENDA LIQUIDA | J104: RESUMO COMPARATIVO | K104: VALORES CUSTO | L104: VALORES LIQUIDO
B105: Serviços Internos AUTPRO | E105: =ServInt[[#Totals],[TOTAL]] -> 14688 | F105: =ServInt[[#Totals],[TOTAL3]] -> 21927.633 | J105: TOTAL SERVIÇOS | K105: =SUM(E105:E111) -> 819391.6 | L105: =SUM(F105:F111) -> 1042201.7
B106: Serviços Externos AUTPRO | E106: =ServExt[[#Totals],[TOTAL]] -> 82800 | F106: =ServExt[[#Totals],[TOTAL3]] -> 123611.66 | J106: MARGEM TOTAL SERVIÇOS | K106: =L105-K105 -> 222810.06 | L106: =K106/L105 -> 0.21378786
B107: Despesas Externas AUTPRO | E107: =K14 -> 44884 | F107: =L14 -> 74620.834 | J107: LUCRO SERVIÇOS | K107: =L107*L105 -> 133075.08 | L107: =K106/L105-BASE!$Q$31-BASE!$Q$34 -> 0.1276865
B108: Serviços Internos MONTAGEM | E108: =ServInt10[[#Totals],[TOTAL]] -> 0 | F108: =ServInt10[[#Totals],[TOTAL3]] -> 0
B109: Serviços Externos MONTAGEM | E109: =ServExt8[[#Totals],[TOTAL]] -> 269517.6 | F109: =ServExt8[[#Totals],[TOTAL3]] -> 338123.27
B110: Despesas Externas MONTAGEM | E110: =K24 -> 229642 | F110: =L24 -> 288097.34
B111: Terceiros e Locações | E111: =ServTerc[[#Totals],[TOTAL CUSTO]] -> 177860 | F111: =ServTerc[[#Totals],[TOTAL VENDA]] -> 195820.93 | J111: TOTAL PRODUTOS | K111: =SUM(E112:E113) -> 168909.95 | L111: =SUM(F112:F113) -> 211905.95
B112: Materiais de Campo | E112: =MateriaisCampo[[#Totals],[TOT CUSTO]] -> 162990.32 | F112: =MateriaisCampo[[#Totals],[VENDA]] -> 204479.49 | J112: MARGEM TOTAL PRODUTOS | K112: =L111-K111 -> 42996.006 | L112: =K112/L111-BASE!Q37 -> 0.19290136
B113: Materiais de Painel | E113: =MateriaisPainel[[#Totals],[TOT CUSTO]] -> 5919.625 | F113: =MateriaisPainel[[#Totals],[VENDA]] -> 7426.4648 | J113: LUCRO PRODUTOS | K113: =L111*L113 -> 22631.556 | L113: =K112/L111-BASE!Q31-BASE!Q37 -> 0.1068
B114: Bonificação | E114: =F118*1% -> 12541.076 | F114: 0
B115: Comissão Vendedor Externo | E115: =$F$118*G8 -> 0 | F115: 0
B116: Comissão Representante | E116: =$F$118*G9 -> 0 | F116: 0
B117: Custo Financeiro | E117: =SUM(E105:E116)*BASE!V28 -> 23952.724 | F117: 0
B118: TOTAL: | E118: =SUM(E105:E117) -> 1024795.3 | F118: =SUM(F105:F113) -> 1254107.6
I119: IPI | J119: Constante | K119: CAMPO | L119: PAINEL
B120: IMPOSTOS À PAGAR | F120: VALOR | I120: 0 | J120: 0 | K120: =IF($D$9="NÃO",$F$53,IF($E$54=0%,0,0)) -> 0 | L120: =IF($D$9="NÃO",$F$68,IF($E$69=0%,0,0)) -> 0
B121: ICMS | F121: =F61+F46 -> 32290.431 | I121: 0.15 | J121: 0.13043478 | K121: =IF($D$9="NÃO",$F$53,IF($E$54=15%,($F$58-($F$58*J121)),0)) -> 0 | L121: =IF($D$9="NÃO",$F$68,IF($E$69=15%,($F$73-($F$73*J121)),0)) -> 0
B122: IPI | F122: =F69+F54 -> 0 | I122: 0.1125 | J122: 0.1011236 | K122: =IF($D$9="NÃO",$F$53,IF($E$54=11.25%,($F$58-($F$58*J122)),0)) -> 0 | L122: =IF($D$9="NÃO",$F$68,IF($E$69=11.25%,($F$73-($F$73*J122)),0)) -> 0
B123: PIS | F123: =F62+F47+F35+F25+L15+F15+L25 -> 23864.614 | I123: 0.0975 | J123: 0.088838269 | K123: =IF($D$9="NÃO",$F$53,IF($E$54=9.75%,($F$58-($F$58*J123)),0)) -> 0 | L123: =IF($D$9="NÃO",$F$68,IF($E$69=9.75%,($F$73-($F$73*J123)),0)) -> 0
B124: COFINS | F124: =F63+F48+F36+F26+L16+F16+L26 -> 109921.86
B125: ISS | F125: =F18+L18+F28+F38+F50+F65 -> 16383.614
B126: IR | F126: =F19+L19+F29+F39+F51+F66 -> 0
B127: Adic. IR | F127: =F20+L20+F30+F40+F52+F67 -> 0
B128: Simples | F128: =F37+F27+L17+F17+L28 -> 6492.3345
B129: TOTAL: | F129: =SUM(F121:F128) -> 188952.85
B134: Líquido em Caixa: | F134: =M40-E118-F129 -> 232592.03 | G134: =F134/M46 -> 0.12617233

Sheet SERVICOS AUTPRO
F2: ORÇAMENTO DETALHADO
D6: HOSPEDAGEM | H6: CUSTO | L6: CUSTO
D7: DESCRIÇÃO | E7: QUANTIDADE | F7: TOTAL | H7: VALOR HOTEL | O7: MARK-UP
D8: HOSPEDAGEM | E8: =ServExt[[#Totals],[TOTAL4]]/2 -> 140 | F8: =(E8*H8)/O8 -> 37620.939 | H8: 180 | L8: =(E8*H8) -> 25200 | O8: =BASE!$W$60 -> 0.66983974
D10: ALIMENTAÇÃO | H10: CUSTO | L10: CUSTO
D11: DESCRIÇÃO | E11: QUANTIDADE | F11: TOTAL | H11: VALOR REFEIÇÃO | O11: MARK-UP
D12: REFEIÇÕES | E12: =ServExt[[#Totals],[TOTAL4]] -> 280 | F12: =(E12*H12)/O12 -> 16720.417 | H12: 40 | L12: =(E12*H12) -> 11200 | O12: =BASE!$W$60 -> 0.66983974
D14: TRANSPORTE | J14: MESES | L14: CUSTO
D15: DESCRIÇÃO | E15: VIAGENS | F15: PEDÁGIOS | G15: KM | H15: TOTAL | O15: MARK-UP
D16: MOBILIZAÇÃO (POR TRANSLADO) | E16: 6 | F16: 75 | G16: 234 | H16: =(((G16*E16*BASE!M3)+(F16*E16))/O16) -> 2767.8262 | J16: 2 | L16: =((G16*E16*BASE!M3)+(F16*E16)) -> 1854 | O16: =BASE!$W$60 -> 0.66983974
D17: HOTEL PARA OBRA | E17: 120 | G17: 15 | H17: =(((G17*E17*BASE!M4)+(F17*E17))/O17) -> 2284.1284 | L17: =((G17*E17*BASE!M4)+(F17*E17)) -> 1530 | O17: =BASE!$W$60 -> 0.66983974
D18: ALUGUEL CARRO MENSAL | E18: Carros: | G18: =ROUNDUP(ServExt[[#Totals],[Coluna1]]/4,0) -> 2 | H18: =(L18/O18)*G18 -> 15227.523 | L18: =IF(ServExt[[#Totals],[DIAS]]>=30,BASE!W3*(J16),ServExt[[#Totals],[DIAS]]*BASE!W4*1.3) -> 5100 | O18: =BASE!$W$60 -> 0.66983974
D19: PASSAGEM AEREA | H19: =L19/O19 -> 0 | L19: =F19*E19 -> 0 | O19: =BASE!$W$60 -> 0.66983974
D20: TOTAL: | H20: =SUM(H16:I19) -> 20279.478 | L20: =SUM(L16:L19) -> 8484
B22: SERVIÇOS INTERNOS | W22: SERVIÇOS EXTERNOS | AR22: LEGENDA
B23: DESCRIÇÃO | E23: PROFISSIONAL | F23: Profissional | G23: REGIME DE TRABALHO | K23: CUSTO | T23: VENDA | W23: DESCRIÇÃO | Z23: PROFISSIONAL | AA23: Profissional | AB23: REGIME DE TRABALHO | AF23: CUSTO | AP23: VENDA | AR23: 1 | AS23: Especialista Eletricista I
B24: ITEM | C24: CENTRO DE CUSTO | D24: SERVIÇO | E24: CÓDIGO | F24: DESCRIÇÃO FUNÇÃO | G24: DIAS | H24: PESSOAS | I24: HORAS DIA | J24: TIPO H | K24: HE CALC | L24: TOTAL HORAS | M24: R$ / HORA | N24: TOTAL | O24: MARK-UP | P24: HORA | Q24: TOTAL3 | R24: TOTAL4 | S24: MULTA | T24: VENDA COM IMPOSTOS | W24: ITEM | X24: CENTRO DE CUSTO | Y24: SERVIÇO | Z24: CÓDIGO | AA24: DESCRIÇÃO FUNÇÃO | AB24: DIAS | AC24: PESSOAS | AD24: HORAS DIA | AE24: TIPO H | AF24: HE CALC | AG24: TOTAL HORAS | AH24: R$ / HORA | AI24: TOTAL | AJ24: MARK-UP | AK24: HORA | AL24: TOTAL3 | AM24: TOTAL4 | AN24: MULTA | AO24: Coluna1 | AP24: VENDA COM IMPOSTOS | AR24: 2 | AS24: Especialista Eletricista II
B25: 1 | C25: Projetos | D25: AS-BUILT DE PROJETOS E DOCUMENTAÇÕES | E25: 30 | F25: =LOOKUP('SERVICOS AUTPRO'!$E$25:$E$64,BASE!A$4:A$125,BASE!B$4:B$125) -> Projetista Elétrico V | G25: 40 | H25: 1 | I25: 9 | J25: NORMAL | K25: =_xlfn.IFS('SERVICOS AUTPRO'!$J$25:$J$64="EXTRA 150%",((1)*2.5),'SERVICOS AUTPRO'!$J$25:$J$64="EXTRA 100%",((1)*2),'SERVICOS AUTPRO'!$J$25:$J$64="EXTRA 75%",((1)*1.75),'SERVICOS AUTPRO'!$J$25:$J$64="EXTRA 50%",((1)*1.5),'SERVICOS AUTPRO'!$J$25:$J$64="NORMAL",((1))) -> 1 | L25: =ServInt[[#This Row],[DIAS]]*ServInt[[#This Row],[PESSOAS]]*ServInt[[#This Row],[HORAS DIA]] -> 360 | M25: =(IF(ServInt[[#This Row],[CÓDIGO]]="","",LOOKUP(E25,BASE!A$4:A$125,BASE!G$4:G$125)))*ServInt[[#This Row],[HE CALC]] -> 40.8 | N25: =ServInt[[#This Row],[TOTAL HORAS]]*ServInt[[#This Row],[R$ / HORA]] -> 14688 | O25: =BASE!$W$60 -> 0.66983974 | P25: =M25/O25 -> 60.910092 | Q25: =N25/O25 -> 21927.633 | S25: =(IF(E25="","",LOOKUP(E25,BASE!A$4:A$19,BASE!E$4:E$19)))*ServInt[[#This Row],[TOTAL HORAS]] -> 1100.8979 | T25: =IFERROR(ServInt[[#This Row],[TOTAL3]]*(RESUMO!$F$22/RESUMO!$F$14),0) -> 24707.192 | W25: 1 | X25: Sistemas | Y25: Serviço | Z25: 50 | AA25: =LOOKUP(Z25,BASE!A$4:A$125,BASE!B$4:B$125) -> Eletricista Força e Comando V | AB25: 20 | AC25: 1 | AD25: 10 | AE25: NORMAL | AF25: =_xlfn.IFS(ServExt[[#This Row],[TIPO H]]="EXTRA 150%",((1)*2.5),ServExt[[#This Row],[TIPO H]]="EXTRA 100%",((1)*2),ServExt[[#This Row],[TIPO H]]="EXTRA 75%",((1)*1.75),ServExt[[#This Row],[TIPO H]]="EXTRA 50%",((1)*1.5),ServExt[[#This Row],[TIPO H]]="NORMAL",((1))) -> 1 | AG25: =ServExt[[#This Row],[DIAS]]*ServExt[[#This Row],[PESSOAS]]*ServExt[[#This Row],[HORAS DIA]] -> 200 | AH25: =(IF(Z25="","",LOOKUP(Z25,BASE!A$4:A$125,BASE!H$4:H$125)))*ServExt[[#This Row],[HE CALC]] -> 39 | AI25: =ServExt[[#This Row],[TOTAL HORAS]]*ServExt[[#This Row],[R$ / HORA]] -> 7800 | AJ25: =BASE!$W$60 -> 0.66983974 | AK25: =AH25/AJ25 -> 58.222882 | AL25: =AI25/AJ25 -> 11644.576 | AM25: =IF(OR(ServExt[[#This Row],[TIPO H]]="NORMAL",ServExt[[#This Row],[HORAS DIA]]>=8),ServExt[[#This Row],[PESSOAS]]*ServExt[[#This Row],[DIAS]]*2,0) -> 40 | AN25: =(IF(Z25="","",LOOKUP(Z25,BASE!A$4:A$19,BASE!E$4:E$19)))*ServExt[[#This Row],[TOTAL HORAS]] -> 611.60995 | AO25: =IF(ServExt[[#This Row],[TIPO H]]="NORMAL",ServExt[[#This Row],[PESSOAS]],0) -> 1 | AP25: =IFERROR(ServExt[[#This Row],[TOTAL3]]*(RESUMO!$F$22/RESUMO!$F$14),0) -> 13120.649 | AR25: 3 | AS25: Especialista Eletricista III
B26: 2 | C26: Projetos | D26: Serviço | E26: 0 | F26: =LOOKUP('SERVICOS AUTPRO'!$E$25:$E$64,BASE!A$4:A$125,BASE!B$4:B$125) -> 0 | I26: 80 | J26: NORMAL | K26: =_xlfn.IFS('SERVICOS AUTPRO'!$J$25:$J$44="EXTRA 150%",((1)*2.5),'SERVICOS AUTPRO'!$J$25:$J$44="EXTRA 100%",((1)*2),'SERVICOS AUTPRO'!$J$25:$J$44="EXTRA 75%",((1)*1.75),'SERVICOS AUTPRO'!$J$25:$J$44="EXTRA 50%",((1)*1.5),'SERVICOS AUTPRO'!$J$25:$J$44="NORMAL",((1))) -> 1 | L26: =ServInt[[#This Row],[DIAS]]*ServInt[[#This Row],[PESSOAS]]*ServInt[[#This Row],[HORAS DIA]] -> 0 | M26: =(IF(ServInt[[#This Row],[CÓDIGO]]="","",LOOKUP(E26,BASE!A$4:A$125,BASE!G$4:G$125)))*ServInt[[#This Row],[HE CALC]] -> 0 | N26: =ServInt[[#This Row],[TOTAL HORAS]]*ServInt[[#This Row],[R$ / HORA]] -> 0 | O26: =BASE!$W$60 -> 0.66983974 | P26: =M26/O26 -> 0 | Q26: =N26/O26 -> 0 | S26: =(IF(E26="","",LOOKUP(E26,BASE!A$4:A$19,BASE!E$4:E$19)))*ServInt[[#This Row],[TOTAL HORAS]] -> 0 | T26: =IFERROR(ServInt[[#This Row],[TOTAL3]]*(RESUMO!$F$22/RESUMO!$F$14),0) -> 0 | W26: 2 | X26: Sistemas | Y26: Serviço | Z26: 5 | AA26: =LOOKUP(Z26,BASE!A$4:A$125,BASE!B$4:B$125) -> Especialista Eletricista V | AB26: 45 | AC26: 1 | AD26: 10 | AE26: NORMAL | AF26: =_xlfn.IFS(ServExt[[#This Row],[TIPO H]]="EXTRA 150%",((1)*2.5),ServExt[[#This Row],[TIPO H]]="EXTRA 100%",((1)*2),ServExt[[#This Row],[TIPO H]]="EXTRA 75%",((1)*1.75),ServExt[[#This Row],[TIPO H]]="EXTRA 50%",((1)*1.5),ServExt[[#This Row],[TIPO H]]="NORMAL",((1))) -> 1 | AG26: =ServExt[[#This Row],[DIAS]]*ServExt[[#This Row],[PESSOAS]]*ServExt[[#This Row],[HORAS DIA]] -> 450 | AH26: =(IF(Z26="","",LOOKUP(Z26,BASE!A$4:A$125,BASE!H$4:H$125)))*ServExt[[#This Row],[HE CALC]] -> 84 | AI26: =ServExt[[#This Row],[TOTAL HORAS]]*ServExt[[#This Row],[R$ / HORA]] -> 37800 | AJ26: =BASE!$W$60 -> 0.66983974 | AK26: =AH26/AJ26 -> 125.40313 | AL26: =AI26/AJ26 -> 56431.409 | AM26: =IF(OR(ServExt[[#This Row],[TIPO H]]="NORMAL",ServExt[[#This Row],[HORAS DIA]]>=8),ServExt[[#This Row],[PESSOAS]]*ServExt[[#This Row],[DIAS]]*2,0) -> 90 | AN26: =(IF(Z26="","",LOOKUP(Z26,BASE!A$4:A$19,BASE!E$4:E$19)))*ServExt[[#This Row],[TOTAL HORAS]] -> 1376.1224 | AO26: =IF(ServExt[[#This Row],[TIPO H]]="NORMAL",ServExt[[#This Row],[PESSOAS]],0) -> 1 | AP26: =IFERROR(ServExt[[#This Row],[TOTAL3]]*(RESUMO!$F$22/RESUMO!$F$14),0) -> 63584.686 | AR26: 4 | AS26: Especialista Eletricista IV
B27: 3 | C27: Projetos | D27: Serviço | E27: 0 | F27: =LOOKUP('SERVICOS AUTPRO'!$E$25:$E$64,BASE!A$4:A$125,BASE!B$4:B$125) -> 0 | I27: 8.8 | J27: NORMAL | K27: =_xlfn.IFS('SERVICOS AUTPRO'!$J$25:$J$44="EXTRA 150%",((1)*2.5),'SERVICOS AUTPRO'!$J$25:$J$44="EXTRA 100%",((1)*2),'SERVICOS AUTPRO'!$J$25:$J$44="EXTRA 75%",((1)*1.75),'SERVICOS AUTPRO'!$J$25:$J$44="EXTRA 50%",((1)*1.5),'SERVICOS AUTPRO'!$J$25:$J$44="NORMAL",((1))) -> 1 | L27: =ServInt[[#This Row],[DIAS]]*ServInt[[#This Row],[PESSOAS]]*ServInt[[#This Row],[HORAS DIA]] -> 0 | M27: =(IF(ServInt[[#This Row],[CÓDIGO]]="","",LOOKUP(E27,BASE!A$4:A$125,BASE!G$4:G$125)))*ServInt[[#This Row],[HE CALC]] -> 0 | N27: =ServInt[[#This Row],[TOTAL HORAS]]*ServInt[[#This Row],[R$ / HORA]] -> 0 | O27: =BASE!$W$60 -> 0.66983974 | P27: =M27/O27 -> 0 | Q27: =N27/O27 -> 0 | S27: =(IF(E27="","",LOOKUP(E27,BASE!A$4:A$19,BASE!E$4:E$19)))*ServInt[[#This Row],[TOTAL HORAS]] -> 0 | T27: =IFERROR(ServInt[[#This Row],[TOTAL3]]*(RESUMO!$F$22/RESUMO!$F$14),0) -> 0 | W27: 3 | X27: Sistemas | Y27: Serviço | Z27: 65 | AA27: =LOOKUP(Z27,BASE!A$4:A$125,BASE!B$4:B$125) -> Instrumentista Tubista V | AB27: 45 | AC27: 1 | AD27: 10 | AE27: NORMAL | AF27: =_xlfn.IFS(ServExt[[#This Row],[TIPO H]]="EXTRA 150%",((1)*2.5),ServExt[[#This Row],[TIPO H]]="EXTRA 100%",((1)*2),ServExt[[#This Row],[TIPO H]]="EXTRA 75%",((1)*1.75),ServExt[[#This Row],[TIPO H]]="EXTRA 50%",((1)*1.5),ServExt[[#This Row],[TIPO H]]="NORMAL",((1))) -> 1 | AG27: =ServExt[[#This Row],[DIAS]]*ServExt[[#This Row],[PESSOAS]]*ServExt[[#This Row],[HORAS DIA]] -> 450 | AH27: =(IF(Z27="","",LOOKUP(Z27,BASE!A$4:A$125,BASE!H$4:H$125)))*ServExt[[#This Row],[HE CALC]] -> 42 | AI27: =ServExt[[#This Row],[TOTAL HORAS]]*ServExt[[#This Row],[R$ / HORA]] -> 18900 | AJ27: =BASE!$W$60 -> 0.66983974 | AK27: =AH27/AJ27 -> 62.701565 | AL27: =AI27/AJ27 -> 28215.704 | AM27: =IF(OR(ServExt[[#This Row],[TIPO H]]="NORMAL",ServExt[[#This Row],[HORAS DIA]]>=8),ServExt[[#This Row],[PESSOAS]]*ServExt[[#This Row],[DIAS]]*2,0) -> 90 | AN27: =(IF(Z27="","",LOOKUP(Z27,BASE!A$4:A$19,BASE!E$4:E$19)))*ServExt[[#This Row],[TOTAL HORAS]] -> 1376.1224 | AO27: =IF(ServExt[[#This Row],[TIPO H]]="NORMAL",ServExt[[#This Row],[PESSOAS]],0) -> 1 | AP27: =IFERROR(ServExt[[#This Row],[TOTAL3]]*(RESUMO!$F$22/RESUMO!$F$14),0) -> 31792.343 | AR27: 5 | AS27: Especialista Eletricista V
B28: 4 | C28: Projetos | D28: Serviço | E28: 0 | F28: =LOOKUP('SERVICOS AUTPRO'!$E$25:$E$64,BASE!A$4:A$125,BASE!B$4:B$125) -> 0 | I28: 8.8 | J28: NORMAL | K28: =_xlfn.IFS('SERVICOS AUTPRO'!$J$25:$J$44="EXTRA 150%",((1)*2.5),'SERVICOS AUTPRO'!$J$25:$J$44="EXTRA 100%",((1)*2),'SERVICOS AUTPRO'!$J$25:$J$44="EXTRA 75%",((1)*1.75),'SERVICOS AUTPRO'!$J$25:$J$44="EXTRA 50%",((1)*1.5),'SERVICOS AUTPRO'!$J$25:$J$44="NORMAL",((1))) -> 1 | L28: =ServInt[[#This Row],[DIAS]]*ServInt[[#This Row],[PESSOAS]]*ServInt[[#This Row],[HORAS DIA]] -> 0 | M28: =(IF(ServInt[[#This Row],[CÓDIGO]]="","",LOOKUP(E28,BASE!A$4:A$125,BASE!G$4:G$125)))*ServInt[[#This Row],[HE CALC]] -> 0 | N28: =ServInt[[#This Row],[TOTAL HORAS]]*ServInt[[#This Row],[R$ / HORA]] -> 0 | O28: =BASE!$W$60 -> 0.66983974 | P28: =M28/O28 -> 0 | Q28: =N28/O28 -> 0 | S28: =(IF(E28="","",LOOKUP(E28,BASE!A$4:A$19,BASE!E$4:E$19)))*ServInt[[#This Row],[TOTAL HORAS]] -> 0 | T28: =IFERROR(ServInt[[#This Row],[TOTAL3]]*(RESUMO!$F$22/RESUMO!$F$14),0) -> 0 | W28: 4 | X28: Sistemas | Y28: Serviço | Z28: 68 | AA28: =LOOKUP(Z28,BASE!A$4:A$125,BASE!B$4:B$125) -> Coodernador de Obras | AB28: 20 | AC28: 1 | AD28: 10 | AE28: NORMAL | AF28: =_xlfn.IFS(ServExt[[#This Row],[TIPO H]]="EXTRA 150%",((1)*2.5),ServExt[[#This Row],[TIPO H]]="EXTRA 100%",((1)*2),ServExt[[#This Row],[TIPO H]]="EXTRA 75%",((1)*1.75),ServExt[[#This Row],[TIPO H]]="EXTRA 50%",((1)*1.5),ServExt[[#This Row],[TIPO H]]="NORMAL",((1))) -> 1 | AG28: =ServExt[[#This Row],[DIAS]]*ServExt[[#This Row],[PESSOAS]]*ServExt[[#This Row],[HORAS DIA]] -> 200 | AH28: =(IF(Z28="","",LOOKUP(Z28,BASE!A$4:A$125,BASE!H$4:H$125)))*ServExt[[#This Row],[HE CALC]] -> 69 | AI28: =ServExt[[#This Row],[TOTAL HORAS]]*ServExt[[#This Row],[R$ / HORA]] -> 13800 | AJ28: =BASE!$W$60 -> 0.66983974 | AK28: =AH28/AJ28 -> 103.00971 | AL28: =AI28/AJ28 -> 20601.943 | AM28: =IF(OR(ServExt[[#This Row],[TIPO H]]="NORMAL",ServExt[[#This Row],[HORAS DIA]]>=8),ServExt[[#This Row],[PESSOAS]]*ServExt[[#This Row],[DIAS]]*2,0) -> 40 | AN28: =(IF(Z28="","",LOOKUP(Z28,BASE!A$4:A$19,BASE!E$4:E$19)))*ServExt[[#This Row],[TOTAL HORAS]] -> 611.60995 | AO28: =IF(ServExt[[#This Row],[TIPO H]]="NORMAL",ServExt[[#This Row],[PESSOAS]],0) -> 1 | AP28: =IFERROR(ServExt[[#This Row],[TOTAL3]]*(RESUMO!$F$22/RESUMO!$F$14),0) -> 23213.457 | AR28: 6 | AS28: Especialista Controle e Automação I
B29: 5 | C29: Projetos | D29: Serviço | E29: 0 | F29: =LOOKUP('SERVICOS AUTPRO'!$E$25:$E$64,BASE!A$4:A$125,BASE!B$4:B$125) -> 0 | I29: 8.8 | J29: NORMAL | K29: =_xlfn.IFS('SERVICOS AUTPRO'!$J$25:$J$44="EXTRA 150%",((1)*2.5),'SERVICOS AUTPRO'!$J$25:$J$44="EXTRA 100%",((1)*2),'SERVICOS AUTPRO'!$J$25:$J$44="EXTRA 75%",((1)*1.75),'SERVICOS AUTPRO'!$J$25:$J$44="EXTRA 50%",((1)*1.5),'SERVICOS AUTPRO'!$J$25:$J$44="NORMAL",((1))) -> 1 | L29: =ServInt[[#This Row],[DIAS]]*ServInt[[#This Row],[PESSOAS]]*ServInt[[#This Row],[HORAS DIA]] -> 0 | M29: =(IF(ServInt[[#This Row],[CÓDIGO]]="","",LOOKUP(E29,BASE!A$4:A$125,BASE!G$4:G$125)))*ServInt[[#This Row],[HE CALC]] -> 0 | N29: =ServInt[[#This Row],[TOTAL HORAS]]*ServInt[[#This Row],[R$ / HORA]] -> 0 | O29: =BASE!$W$60 -> 0.66983974 | P29: =M29/O29 -> 0 | Q29: =N29/O29 -> 0 | S29: =(IF(E29="","",LOOKUP(E29,BASE!A$4:A$19,BASE!E$4:E$19)))*ServInt[[#This Row],[TOTAL HORAS]] -> 0 | T29: =IFERROR(ServInt[[#This Row],[TOTAL3]]*(RESUMO!$F$22/RESUMO!$F$14),0) -> 0 | W29: 5 | X29: Sistemas | Y29: Serviço | Z29: 30 | AA29: =LOOKUP(Z29,BASE!A$4:A$125,BASE!B$4:B$125) -> Projetista Elétrico V | AB29: 10 | AC29: 1 | AD29: 10 | AE29: NORMAL | AF29: =_xlfn.IFS(ServExt[[#This Row],[TIPO H]]="EXTRA 150%",((1)*2.5),ServExt[[#This Row],[TIPO H]]="EXTRA 100%",((1)*2),ServExt[[#This Row],[TIPO H]]="EXTRA 75%",((1)*1.75),ServExt[[#This Row],[TIPO H]]="EXTRA 50%",((1)*1.5),ServExt[[#This Row],[TIPO H]]="NORMAL",((1))) -> 1 | AG29: =ServExt[[#This Row],[DIAS]]*ServExt[[#This Row],[PESSOAS]]*ServExt[[#This Row],[HORAS DIA]] -> 100 | AH29: =(IF(Z29="","",LOOKUP(Z29,BASE!A$4:A$125,BASE!H$4:H$125)))*ServExt[[#This Row],[HE CALC]] -> 45 | AI29: =ServExt[[#This Row],[TOTAL HORAS]]*ServExt[[#This Row],[R$ / HORA]] -> 4500 | AJ29: =BASE!$W$60 -> 0.66983974 | AK29: =AH29/AJ29 -> 67.180248 | AL29: =AI29/AJ29 -> 6718.0248 | AM29: =IF(OR(ServExt[[#This Row],[TIPO H]]="NORMAL",ServExt[[#This Row],[HORAS DIA]]>=8),ServExt[[#This Row],[PESSOAS]]*ServExt[[#This Row],[DIAS]]*2,0) -> 20 | AN29: =(IF(Z29="","",LOOKUP(Z29,BASE!A$4:A$19,BASE!E$4:E$19)))*ServExt[[#This Row],[TOTAL HORAS]] -> 305.80498 | AO29: =IF(ServExt[[#This Row],[TIPO H]]="NORMAL",ServExt[[#This Row],[PESSOAS]],0) -> 1 | AP29: =IFERROR(ServExt[[#This Row],[TOTAL3]]*(RESUMO!$F$22/RESUMO!$F$14),0) -> 7569.6055 | AR29: 7 | AS29: Especialista Controle e Automação Il
B30: 6 | C30: Projetos | D30: Serviço | E30: 0 | F30: =LOOKUP('SERVICOS AUTPRO'!$E$25:$E$64,BASE!A$4:A$125,BASE!B$4:B$125) -> 0 | I30: 8.8 | J30: NORMAL | K30: =_xlfn.IFS('SERVICOS AUTPRO'!$J$25:$J$44="EXTRA 150%",((1)*2.5),'SERVICOS AUTPRO'!$J$25:$J$44="EXTRA 100%",((1)*2),'SERVICOS AUTPRO'!$J$25:$J$44="EXTRA 75%",((1)*1.75),'SERVICOS AUTPRO'!$J$25:$J$44="EXTRA 50%",((1)*1.5),'SERVICOS AUTPRO'!$J$25:$J$44="NORMAL",((1))) -> 1 | L30: =ServInt[[#This Row],[DIAS]]*ServInt[[#This Row],[PESSOAS]]*ServInt[[#This Row],[HORAS DIA]] -> 0 | M30: =(IF(ServInt[[#This Row],[CÓDIGO]]="","",LOOKUP(E30,BASE!A$4:A$125,BASE!G$4:G$125)))*ServInt[[#This Row],[HE CALC]] -> 0 | N30: =ServInt[[#This Row],[TOTAL HORAS]]*ServInt[[#This Row],[R$ / HORA]] -> 0 | O30: =BASE!$W$60 -> 0.66983974 | P30: =M30/O30 -> 0 | Q30: =N30/O30 -> 0 | S30: =(IF(E30="","",LOOKUP(E30,BASE!A$4:A$19,BASE!E$4:E$19)))*ServInt[[#This Row],[TOTAL HORAS]] -> 0 | T30: =IFERROR(ServInt[[#This Row],[TOTAL3]]*(RESUMO!$F$22/RESUMO!$F$14),0) -> 0 | W30: 6 | X30: Sistemas | Y30: Serviço | Z30: 0 | AA30: =LOOKUP(Z30,BASE!A$4:A$125,BASE!B$4:B$125) -> 0 | AD30: 8.8 | AE30: NORMAL | AF30: =_xlfn.IFS(ServExt[[#This Row],[TIPO H]]="EXTRA 150%",((1)*2.5),ServExt[[#This Row],[TIPO H]]="EXTRA 100%",((1)*2),ServExt[[#This Row],[TIPO H]]="EXTRA 75%",((1)*1.75),ServExt[[#This Row],[TIPO H]]="EXTRA 50%",((1)*1.5),ServExt[[#This Row],[TIPO H]]="NORMAL",((1))) -> 1 | AG30: =ServExt[[#This Row],[DIAS]]*ServExt[[#This Row],[PESSOAS]]*ServExt[[#This Row],[HORAS DIA]] -> 0 | AH30: =(IF(Z30="","",LOOKUP(Z30,BASE!A$4:A$125,BASE!H$4:H$125)))*ServExt[[#This Row],[HE CALC]] -> 0 | AI30: =ServExt[[#This Row],[TOTAL HORAS]]*ServExt[[#This Row],[R$ / HORA]] -> 0 | AJ30: =BASE!$W$60 -> 0.66983974 | AK30: =AH30/AJ30 -> 0 | AL30: =AI30/AJ30 -> 0 | AM30: =IF(OR(ServExt[[#This Row],[TIPO H]]="NORMAL",ServExt[[#This Row],[HORAS DIA]]>=8),ServExt[[#This Row],[PESSOAS]]*ServExt[[#This Row],[DIAS]]*2,0) -> 0 | AN30: =(IF(Z30="","",LOOKUP(Z30,BASE!A$4:A$19,BASE!E$4:E$19)))*ServExt[[#This Row],[TOTAL HORAS]] -> 0 | AO30: =IF(ServExt[[#This Row],[TIPO H]]="NORMAL",ServExt[[#This Row],[PESSOAS]],0) -> 0 | AP30: =IFERROR(ServExt[[#This Row],[TOTAL3]]*(RESUMO!$F$22/RESUMO!$F$14),0) -> 0 | AR30: 8 | AS30: Especialista Controle e Automação III
B31: 7 | C31: Projetos | D31: Serviço | E31: 0 | F31: =LOOKUP('SERVICOS AUTPRO'!$E$25:$E$64,BASE!A$4:A$125,BASE!B$4:B$125) -> 0 | I31: 8.8 | J31: NORMAL | K31: =_xlfn.IFS('SERVICOS AUTPRO'!$J$25:$J$44="EXTRA 150%",((1)*2.5),'SERVICOS AUTPRO'!$J$25:$J$44="EXTRA 100%",((1)*2),'SERVICOS AUTPRO'!$J$25:$J$44="EXTRA 75%",((1)*1.75),'SERVICOS AUTPRO'!$J$25:$J$44="EXTRA 50%",((1)*1.5),'SERVICOS AUTPRO'!$J$25:$J$44="NORMAL",((1))) -> 1 | L31: =ServInt[[#This Row],[DIAS]]*ServInt[[#This Row],[PESSOAS]]*ServInt[[#This Row],[HORAS DIA]] -> 0 | M31: =(IF(ServInt[[#This Row],[CÓDIGO]]="","",LOOKUP(E31,BASE!A$4:A$125,BASE!G$4:G$125)))*ServInt[[#This Row],[HE CALC]] -> 0 | N31: =ServInt[[#This Row],[TOTAL HORAS]]*ServInt[[#This Row],[R$ / HORA]] -> 0 | O31: =BASE!$W$60 -> 0.66983974 | P31: =M31/O31 -> 0 | Q31: =N31/O31 -> 0 | S31: =(IF(E31="","",LOOKUP(E31,BASE!A$4:A$19,BASE!E$4:E$19)))*ServInt[[#This Row],[TOTAL HORAS]] -> 0 | T31: =IFERROR(ServInt[[#This Row],[TOTAL3]]*(RESUMO!$F$22/RESUMO!$F$14),0) -> 0 | W31: 7 | X31: Sistemas | Y31: Serviço | Z31: 0 | AA31: =LOOKUP(Z31,BASE!A$4:A$125,BASE!B$4:B$125) -> 0 | AD31: 8.8 | AE31: NORMAL | AF31: =_xlfn.IFS(ServExt[[#This Row],[TIPO H]]="EXTRA 150%",((1)*2.5),ServExt[[#This Row],[TIPO H]]="EXTRA 100%",((1)*2),ServExt[[#This Row],[TIPO H]]="EXTRA 75%",((1)*1.75),ServExt[[#This Row],[TIPO H]]="EXTRA 50%",((1)*1.5),ServExt[[#This Row],[TIPO H]]="NORMAL",((1))) -> 1 | AG31: =ServExt[[#This Row],[DIAS]]*ServExt[[#This Row],[PESSOAS]]*ServExt[[#This Row],[HORAS DIA]] -> 0 | AH31: =(IF(Z31="","",LOOKUP(Z31,BASE!A$4:A$125,BASE!H$4:H$125)))*ServExt[[#This Row],[HE CALC]] -> 0 | AI31: =ServExt[[#This Row],[TOTAL HORAS]]*ServExt[[#This Row],[R$ / HORA]] -> 0 | AJ31: =BASE!$W$60 -> 0.66983974 | AK31: =AH31/AJ31 -> 0 | AL31: =AI31/AJ31 -> 0 | AM31: =IF(OR(ServExt[[#This Row],[TIPO H]]="NORMAL",ServExt[[#This Row],[HORAS DIA]]>=8),ServExt[[#This Row],[PESSOAS]]*ServExt[[#This Row],[DIAS]]*2,0) -> 0 | AN31: =(IF(Z31="","",LOOKUP(Z31,BASE!A$4:A$19,BASE!E$4:E$19)))*ServExt[[#This Row],[TOTAL HORAS]] -> 0 | AO31: =IF(ServExt[[#This Row],[TIPO H]]="NORMAL",ServExt[[#This Row],[PESSOAS]],0) -> 0 | AP31: =IFERROR(ServExt[[#This Row],[TOTAL3]]*(RESUMO!$F$22/RESUMO!$F$14),0) -> 0 | AR31: 9 | AS31: Especialista Controle e Automação IV
B32: 8 | C32: Projetos | D32: Serviço | E32: 0 | F32: =LOOKUP('SERVICOS AUTPRO'!$E$25:$E$64,BASE!A$4:A$125,BASE!B$4:B$125) -> 0 | G32: 0 | I32: 8.8 | J32: NORMAL | K32: =_xlfn.IFS('SERVICOS AUTPRO'!$J$25:$J$44="EXTRA 150%",((1)*2.5),'SERVICOS AUTPRO'!$J$25:$J$44="EXTRA 100%",((1)*2),'SERVICOS AUTPRO'!$J$25:$J$44="EXTRA 75%",((1)*1.75),'SERVICOS AUTPRO'!$J$25:$J$44="EXTRA 50%",((1)*1.5),'SERVICOS AUTPRO'!$J$25:$J$44="NORMAL",((1))) -> 1 | L32: =ServInt[[#This Row],[DIAS]]*ServInt[[#This Row],[PESSOAS]]*ServInt[[#This Row],[HORAS DIA]] -> 0 | M32: =(IF(ServInt[[#This Row],[CÓDIGO]]="","",LOOKUP(E32,BASE!A$4:A$125,BASE!G$4:G$125)))*ServInt[[#This Row],[HE CALC]] -> 0 | N32: =ServInt[[#This Row],[TOTAL HORAS]]*ServInt[[#This Row],[R$ / HORA]] -> 0 | O32: =BASE!$W$60 -> 0.66983974 | P32: =M32/O32 -> 0 | Q32: =N32/O32 -> 0 | S32: =(IF(E32="","",LOOKUP(E32,BASE!A$4:A$19,BASE!E$4:E$19)))*ServInt[[#This Row],[TOTAL HORAS]] -> 0 | T32: =IFERROR(ServInt[[#This Row],[TOTAL3]]*(RESUMO!$F$22/RESUMO!$F$14),0) -> 0 | W32: 8 | X32: Sistemas | Y32: Serviço | Z32: 0 | AA32: =LOOKUP(Z32,BASE!A$4:A$125,BASE!B$4:B$125) -> 0 | AD32: 8.8 | AE32: NORMAL | AF32: =_xlfn.IFS(ServExt[[#This Row],[TIPO H]]="EXTRA 150%",((1)*2.5),ServExt[[#This Row],[TIPO H]]="EXTRA 100%",((1)*2),ServExt[[#This Row],[TIPO H]]="EXTRA 75%",((1)*1.75),ServExt[[#This Row],[TIPO H]]="EXTRA 50%",((1)*1.5),ServExt[[#This Row],[TIPO H]]="NORMAL",((1))) -> 1 | AG32: =ServExt[[#This Row],[DIAS]]*ServExt[[#This Row],[PESSOAS]]*ServExt[[#This Row],[HORAS DIA]] -> 0 | AH32: =(IF(Z32="","",LOOKUP(Z32,BASE!A$4:A$125,BASE!H$4:H$125)))*ServExt[[#This Row],[HE CALC]] -> 0 | AI32: =ServExt[[#This Row],[TOTAL HORAS]]*ServExt[[#This Row],[R$ / HORA]] -> 0 | AJ32: =BASE!$W$60 -> 0.66983974 | AK32: =AH32/AJ32 -> 0 | AL32: =AI32/AJ32 -> 0 | AM32: =IF(OR(ServExt[[#This Row],[TIPO H]]="NORMAL",ServExt[[#This Row],[HORAS DIA]]>=8),ServExt[[#This Row],[PESSOAS]]*ServExt[[#This Row],[DIAS]]*2,0) -> 0 | AN32: =(IF(Z32="","",LOOKUP(Z32,BASE!A$4:A$19,BASE!E$4:E$19)))*ServExt[[#This Row],[TOTAL HORAS]] -> 0 | AO32: =IF(ServExt[[#This Row],[TIPO H]]="NORMAL",ServExt[[#This Row],[PESSOAS]],0) -> 0 | AP32: =IFERROR(ServExt[[#This Row],[TOTAL3]]*(RESUMO!$F$22/RESUMO!$F$14),0) -> 0 | AR32: 10 | AS32: Especialista Controle e Automação V
B33: 9 | C33: Projetos | D33: Serviço | E33: 0 | F33: =LOOKUP('SERVICOS AUTPRO'!$E$25:$E$64,BASE!A$4:A$125,BASE!B$4:B$125) -> 0 | I33: 8.8 | J33: NORMAL | K33: =_xlfn.IFS('SERVICOS AUTPRO'!$J$25:$J$44="EXTRA 150%",((1)*2.5),'SERVICOS AUTPRO'!$J$25:$J$44="EXTRA 100%",((1)*2),'SERVICOS AUTPRO'!$J$25:$J$44="EXTRA 75%",((1)*1.75),'SERVICOS AUTPRO'!$J$25:$J$44="EXTRA 50%",((1)*1.5),'SERVICOS AUTPRO'!$J$25:$J$44="NORMAL",((1))) -> 1 | L33: =ServInt[[#This Row],[DIAS]]*ServInt[[#This Row],[PESSOAS]]*ServInt[[#This Row],[HORAS DIA]] -> 0 | M33: =(IF(ServInt[[#This Row],[CÓDIGO]]="","",LOOKUP(E33,BASE!A$4:A$125,BASE!G$4:G$125)))*ServInt[[#This Row],[HE CALC]] -> 0 | N33: =ServInt[[#This Row],[TOTAL HORAS]]*ServInt[[#This Row],[R$ / HORA]] -> 0 | O33: =BASE!$W$60 -> 0.66983974 | P33: =M33/O33 -> 0 | Q33: =N33/O33 -> 0 | S33: =(IF(E33="","",LOOKUP(E33,BASE!A$4:A$19,BASE!E$4:E$19)))*ServInt[[#This Row],[TOTAL HORAS]] -> 0 | T33: =IFERROR(ServInt[[#This Row],[TOTAL3]]*(RESUMO!$F$22/RESUMO!$F$14),0) -> 0 | W33: 9 | X33: Sistemas | Y33: Serviço | Z33: 0 | AA33: =LOOKUP(Z33,BASE!A$4:A$125,BASE!B$4:B$125) -> 0 | AD33: 8.8 | AE33: NORMAL | AF33: =_xlfn.IFS(ServExt[[#This Row],[TIPO H]]="EXTRA 150%",((1)*2.5),ServExt[[#This Row],[TIPO H]]="EXTRA 100%",((1)*2),ServExt[[#This Row],[TIPO H]]="EXTRA 75%",((1)*1.75),ServExt[[#This Row],[TIPO H]]="EXTRA 50%",((1)*1.5),ServExt[[#This Row],[TIPO H]]="NORMAL",((1))) -> 1 | AG33: =ServExt[[#This Row],[DIAS]]*ServExt[[#This Row],[PESSOAS]]*ServExt[[#This Row],[HORAS DIA]] -> 0 | AH33: =(IF(Z33="","",LOOKUP(Z33,BASE!A$4:A$125,BASE!H$4:H$125)))*ServExt[[#This Row],[HE CALC]] -> 0 | AI33: =ServExt[[#This Row],[TOTAL HORAS]]*ServExt[[#This Row],[R$ / HORA]] -> 0 | AJ33: =BASE!$W$60 -> 0.66983974 | AK33: =AH33/AJ33 -> 0 | AL33: =AI33/AJ33 -> 0 | AM33: =IF(OR(ServExt[[#This Row],[TIPO H]]="NORMAL",ServExt[[#This Row],[HORAS DIA]]>=8),ServExt[[#This Row],[PESSOAS]]*ServExt[[#This Row],[DIAS]]*2,0) -> 0 | AN33: =(IF(Z33="","",LOOKUP(Z33,BASE!A$4:A$19,BASE!E$4:E$19)))*ServExt[[#This Row],[TOTAL HORAS]] -> 0 | AO33: =IF(ServExt[[#This Row],[TIPO H]]="NORMAL",ServExt[[#This Row],[PESSOAS]],0) -> 0 | AP33: =IFERROR(ServExt[[#This Row],[TOTAL3]]*(RESUMO!$F$22/RESUMO!$F$14),0) -> 0 | AR33: 11 | AS33: Especialista em Computação I
B34: 10 | C34: Projetos | D34: Serviço | E34: 0 | F34: =LOOKUP('SERVICOS AUTPRO'!$E$25:$E$64,BASE!A$4:A$125,BASE!B$4:B$125) -> 0 | I34: 8.8 | J34: NORMAL | K34: =_xlfn.IFS('SERVICOS AUTPRO'!$J$25:$J$44="EXTRA 150%",((1)*2.5),'SERVICOS AUTPRO'!$J$25:$J$44="EXTRA 100%",((1)*2),'SERVICOS AUTPRO'!$J$25:$J$44="EXTRA 75%",((1)*1.75),'SERVICOS AUTPRO'!$J$25:$J$44="EXTRA 50%",((1)*1.5),'SERVICOS AUTPRO'!$J$25:$J$44="NORMAL",((1))) -> 1 | L34: =ServInt[[#This Row],[DIAS]]*ServInt[[#This Row],[PESSOAS]]*ServInt[[#This Row],[HORAS DIA]] -> 0 | M34: =(IF(ServInt[[#This Row],[CÓDIGO]]="","",LOOKUP(E34,BASE!A$4:A$125,BASE!G$4:G$125)))*ServInt[[#This Row],[HE CALC]] -> 0 | N34: =ServInt[[#This Row],[TOTAL HORAS]]*ServInt[[#This Row],[R$ / HORA]] -> 0 | O34: =BASE!$W$60 -> 0.66983974 | P34: =M34/O34 -> 0 | Q34: =N34/O34 -> 0 | S34: =(IF(E34="","",LOOKUP(E34,BASE!A$4:A$19,BASE!E$4:E$19)))*ServInt[[#This Row],[TOTAL HORAS]] -> 0 | T34: =IFERROR(ServInt[[#This Row],[TOTAL3]]*(RESUMO!$F$22/RESUMO!$F$14),0) -> 0 | W34: 10 | X34: Sistemas | Y34: Serviço | Z34: 0 | AA34: =LOOKUP(Z34,BASE!A$4:A$125,BASE!B$4:B$125) -> 0 | AD34: 8 | AE34: NORMAL | AF34: =_xlfn.IFS(ServExt[[#This Row],[TIPO H]]="EXTRA 150%",((1)*2.5),ServExt[[#This Row],[TIPO H]]="EXTRA 100%",((1)*2),ServExt[[#This Row],[TIPO H]]="EXTRA 75%",((1)*1.75),ServExt[[#This Row],[TIPO H]]="EXTRA 50%",((1)*1.5),ServExt[[#This Row],[TIPO H]]="NORMAL",((1))) -> 1 | AG34: =ServExt[[#This Row],[DIAS]]*ServExt[[#This Row],[PESSOAS]]*ServExt[[#This Row],[HORAS DIA]] -> 0 | AH34: =(IF(Z34="","",LOOKUP(Z34,BASE!A$4:A$125,BASE!H$4:H$125)))*ServExt[[#This Row],[HE CALC]] -> 0 | AI34: =ServExt[[#This Row],[TOTAL HORAS]]*ServExt[[#This Row],[R$ / HORA]] -> 0 | AJ34: =BASE!$W$60 -> 0.66983974 | AK34: =AH34/AJ34 -> 0 | AL34: =AI34/AJ34 -> 0 | AM34: =IF(OR(ServExt[[#This Row],[TIPO H]]="NORMAL",ServExt[[#This Row],[HORAS DIA]]>=8),ServExt[[#This Row],[PESSOAS]]*ServExt[[#This Row],[DIAS]]*2,0) -> 0 | AN34: =(IF(Z34="","",LOOKUP(Z34,BASE!A$4:A$19,BASE!E$4:E$19)))*ServExt[[#This Row],[TOTAL HORAS]] -> 0 | AO34: =IF(ServExt[[#This Row],[TIPO H]]="NORMAL",ServExt[[#This Row],[PESSOAS]],0) -> 0 | AP34: =IFERROR(ServExt[[#This Row],[TOTAL3]]*(RESUMO!$F$22/RESUMO!$F$14),0) -> 0 | AR34: 12 | AS34: Especialista em Computação II
B35: 11 | C35: Projetos | D35: Serviço | E35: 0 | F35: =LOOKUP('SERVICOS AUTPRO'!$E$25:$E$64,BASE!A$4:A$125,BASE!B$4:B$125) -> 0 | I35: 8.8 | J35: NORMAL | K35: =_xlfn.IFS('SERVICOS AUTPRO'!$J$25:$J$44="EXTRA 150%",((1)*2.5),'SERVICOS AUTPRO'!$J$25:$J$44="EXTRA 100%",((1)*2),'SERVICOS AUTPRO'!$J$25:$J$44="EXTRA 75%",((1)*1.75),'SERVICOS AUTPRO'!$J$25:$J$44="EXTRA 50%",((1)*1.5),'SERVICOS AUTPRO'!$J$25:$J$44="NORMAL",((1))) -> 1 | L35: =ServInt[[#This Row],[DIAS]]*ServInt[[#This Row],[PESSOAS]]*ServInt[[#This Row],[HORAS DIA]] -> 0 | M35: =(IF(ServInt[[#This Row],[CÓDIGO]]="","",LOOKUP(E35,BASE!A$4:A$125,BASE!G$4:G$125)))*ServInt[[#This Row],[HE CALC]] -> 0 | N35: =ServInt[[#This Row],[TOTAL HORAS]]*ServInt[[#This Row],[R$ / HORA]] -> 0 | O35: =BASE!$W$60 -> 0.66983974 | P35: =M35/O35 -> 0 | Q35: =N35/O35 -> 0 | S35: =(IF(E35="","",LOOKUP(E35,BASE!A$4:A$19,BASE!E$4:E$19)))*ServInt[[#This Row],[TOTAL HORAS]] -> 0 | T35: =IFERROR(ServInt[[#This Row],[TOTAL3]]*(RESUMO!$F$22/RESUMO!$F$14),0) -> 0 | W35: 11 | X35: Sistemas | Y35: Serviço | Z35: 0 | AA35: =LOOKUP(Z35,BASE!A$4:A$125,BASE!B$4:B$125) -> 0 | AD35: 8.8 | AE35: NORMAL | AF35: =_xlfn.IFS(ServExt[[#This Row],[TIPO H]]="EXTRA 150%",((1)*2.5),ServExt[[#This Row],[TIPO H]]="EXTRA 100%",((1)*2),ServExt[[#This Row],[TIPO H]]="EXTRA 75%",((1)*1.75),ServExt[[#This Row],[TIPO H]]="EXTRA 50%",((1)*1.5),ServExt[[#This Row],[TIPO H]]="NORMAL",((1))) -> 1 | AG35: =ServExt[[#This Row],[DIAS]]*ServExt[[#This Row],[PESSOAS]]*ServExt[[#This Row],[HORAS DIA]] -> 0 | AH35: =(IF(Z35="","",LOOKUP(Z35,BASE!A$4:A$125,BASE!H$4:H$125)))*ServExt[[#This Row],[HE CALC]] -> 0 | AI35: =ServExt[[#This Row],[TOTAL HORAS]]*ServExt[[#This Row],[R$ / HORA]] -> 0 | AJ35: =BASE!$W$60 -> 0.66983974 | AK35: =AH35/AJ35 -> 0 | AL35: =AI35/AJ35 -> 0 | AM35: =IF(OR(ServExt[[#This Row],[TIPO H]]="NORMAL",ServExt[[#This Row],[HORAS DIA]]>=8),ServExt[[#This Row],[PESSOAS]]*ServExt[[#This Row],[DIAS]]*2,0) -> 0 | AN35: =(IF(Z35="","",LOOKUP(Z35,BASE!A$4:A$19,BASE!E$4:E$19)))*ServExt[[#This Row],[TOTAL HORAS]] -> 0 | AO35: =IF(ServExt[[#This Row],[TIPO H]]="NORMAL",ServExt[[#This Row],[PESSOAS]],0) -> 0 | AP35: =IFERROR(ServExt[[#This Row],[TOTAL3]]*(RESUMO!$F$22/RESUMO!$F$14),0) -> 0 | AR35: 13 | AS35: Especialista Computação III
B36: 12 | C36: Projetos | D36: Serviço | E36: 0 | F36: =LOOKUP('SERVICOS AUTPRO'!$E$25:$E$64,BASE!A$4:A$125,BASE!B$4:B$125) -> 0 | I36: 8.8 | J36: NORMAL | K36: =_xlfn.IFS('SERVICOS AUTPRO'!$J$25:$J$44="EXTRA 150%",((1)*2.5),'SERVICOS AUTPRO'!$J$25:$J$44="EXTRA 100%",((1)*2),'SERVICOS AUTPRO'!$J$25:$J$44="EXTRA 75%",((1)*1.75),'SERVICOS AUTPRO'!$J$25:$J$44="EXTRA 50%",((1)*1.5),'SERVICOS AUTPRO'!$J$25:$J$44="NORMAL",((1))) -> 1 | L36: =ServInt[[#This Row],[DIAS]]*ServInt[[#This Row],[PESSOAS]]*ServInt[[#This Row],[HORAS DIA]] -> 0 | M36: =(IF(ServInt[[#This Row],[CÓDIGO]]="","",LOOKUP(E36,BASE!A$4:A$125,BASE!G$4:G$125)))*ServInt[[#This Row],[HE CALC]] -> 0 | N36: =ServInt[[#This Row],[TOTAL HORAS]]*ServInt[[#This Row],[R$ / HORA]] -> 0 | O36: =BASE!$W$60 -> 0.66983974 | P36: =M36/O36 -> 0 | Q36: =N36/O36 -> 0 | S36: =(IF(E36="","",LOOKUP(E36,BASE!A$4:A$19,BASE!E$4:E$19)))*ServInt[[#This Row],[TOTAL HORAS]] -> 0 | T36: =IFERROR(ServInt[[#This Row],[TOTAL3]]*(RESUMO!$F$22/RESUMO!$F$14),0) -> 0 | W36: 12 | X36: Sistemas | Y36: Serviço | Z36: 0 | AA36: =LOOKUP(Z36,BASE!A$4:A$125,BASE!B$4:B$125) -> 0 | AD36: 8.8 | AE36: NORMAL | AF36: =_xlfn.IFS(ServExt[[#This Row],[TIPO H]]="EXTRA 150%",((1)*2.5),ServExt[[#This Row],[TIPO H]]="EXTRA 100%",((1)*2),ServExt[[#This Row],[TIPO H]]="EXTRA 75%",((1)*1.75),ServExt[[#This Row],[TIPO H]]="EXTRA 50%",((1)*1.5),ServExt[[#This Row],[TIPO H]]="NORMAL",((1))) -> 1 | AG36: =ServExt[[#This Row],[DIAS]]*ServExt[[#This Row],[PESSOAS]]*ServExt[[#This Row],[HORAS DIA]] -> 0 | AH36: =(IF(Z36="","",LOOKUP(Z36,BASE!A$4:A$125,BASE!H$4:H$125)))*ServExt[[#This Row],[HE CALC]] -> 0 | AI36: =ServExt[[#This Row],[TOTAL HORAS]]*ServExt[[#This Row],[R$ / HORA]] -> 0 | AJ36: =BASE!$W$60 -> 0.66983974 | AK36: =AH36/AJ36 -> 0 | AL36: =AI36/AJ36 -> 0 | AM36: =IF(OR(ServExt[[#This Row],[TIPO H]]="NORMAL",ServExt[[#This Row],[HORAS DIA]]>=8),ServExt[[#This Row],[PESSOAS]]*ServExt[[#This Row],[DIAS]]*2,0) -> 0 | AN36: =(IF(Z36="","",LOOKUP(Z36,BASE!A$4:A$19,BASE!E$4:E$19)))*ServExt[[#This Row],[TOTAL HORAS]] -> 0 | AO36: =IF(ServExt[[#This Row],[TIPO H]]="NORMAL",ServExt[[#This Row],[PESSOAS]],0) -> 0 | AP36: =IFERROR(ServExt[[#This Row],[TOTAL3]]*(RESUMO!$F$22/RESUMO!$F$14),0) -> 0 | AR36: 14 | AS36: Especialista Computação IV
B37: 13 | C37: Projetos | D37: Serviço | E37: 0 | F37: =LOOKUP('SERVICOS AUTPRO'!$E$25:$E$64,BASE!A$4:A$125,BASE!B$4:B$125) -> 0 | I37: 8.8 | J37: NORMAL | K37: =_xlfn.IFS('SERVICOS AUTPRO'!$J$25:$J$44="EXTRA 150%",((1)*2.5),'SERVICOS AUTPRO'!$J$25:$J$44="EXTRA 100%",((1)*2),'SERVICOS AUTPRO'!$J$25:$J$44="EXTRA 75%",((1)*1.75),'SERVICOS AUTPRO'!$J$25:$J$44="EXTRA 50%",((1)*1.5),'SERVICOS AUTPRO'!$J$25:$J$44="NORMAL",((1))) -> 1 | L37: =ServInt[[#This Row],[DIAS]]*ServInt[[#This Row],[PESSOAS]]*ServInt[[#This Row],[HORAS DIA]] -> 0 | M37: =(IF(ServInt[[#This Row],[CÓDIGO]]="","",LOOKUP(E37,BASE!A$4:A$125,BASE!G$4:G$125)))*ServInt[[#This Row],[HE CALC]] -> 0 | N37: =ServInt[[#This Row],[TOTAL HORAS]]*ServInt[[#This Row],[R$ / HORA]] -> 0 | O37: =BASE!$W$60 -> 0.66983974 | P37: =M37/O37 -> 0 | Q37: =N37/O37 -> 0 | S37: =(IF(E37="","",LOOKUP(E37,BASE!A$4:A$19,BASE!E$4:E$19)))*ServInt[[#This Row],[TOTAL HORAS]] -> 0 | T37: =IFERROR(ServInt[[#This Row],[TOTAL3]]*(RESUMO!$F$22/RESUMO!$F$14),0) -> 0 | W37: 13 | X37: Sistemas | Y37: Serviço | Z37: 0 | AA37: =LOOKUP(Z37,BASE!A$4:A$125,BASE!B$4:B$125) -> 0 | AD37: 8.8 | AE37: NORMAL | AF37: =_xlfn.IFS(ServExt[[#This Row],[TIPO H]]="EXTRA 150%",((1)*2.5),ServExt[[#This Row],[TIPO H]]="EXTRA 100%",((1)*2),ServExt[[#This Row],[TIPO H]]="EXTRA 75%",((1)*1.75),ServExt[[#This Row],[TIPO H]]="EXTRA 50%",((1)*1.5),ServExt[[#This Row],[TIPO H]]="NORMAL",((1))) -> 1 | AG37: =ServExt[[#This Row],[DIAS]]*ServExt[[#This Row],[PESSOAS]]*ServExt[[#This Row],[HORAS DIA]] -> 0 | AH37: =(IF(Z37="","",LOOKUP(Z37,BASE!A$4:A$125,BASE!H$4:H$125)))*ServExt[[#This Row],[HE CALC]] -> 0 | AI37: =ServExt[[#This Row],[TOTAL HORAS]]*ServExt[[#This Row],[R$ / HORA]] -> 0 | AJ37: =BASE!$W$60 -> 0.66983974 | AK37: =AH37/AJ37 -> 0 | AL37: =AI37/AJ37 -> 0 | AM37: =IF(OR(ServExt[[#This Row],[TIPO H]]="NORMAL",ServExt[[#This Row],[HORAS DIA]]>=8),ServExt[[#This Row],[PESSOAS]]*ServExt[[#This Row],[DIAS]]*2,0) -> 0 | AN37: =(IF(Z37="","",LOOKUP(Z37,BASE!A$4:A$19,BASE!E$4:E$19)))*ServExt[[#This Row],[TOTAL HORAS]] -> 0 | AO37: =IF(ServExt[[#This Row],[TIPO H]]="NORMAL",ServExt[[#This Row],[PESSOAS]],0) -> 0 | AP37: =IFERROR(ServExt[[#This Row],[TOTAL3]]*(RESUMO!$F$22/RESUMO!$F$14),0) -> 0 | AR37: 15 | AS37: Especialista Computação V
B38: 14 | C38: Projetos | D38: Serviço | E38: 0 | F38: =LOOKUP('SERVICOS AUTPRO'!$E$25:$E$64,BASE!A$4:A$125,BASE!B$4:B$125) -> 0 | I38: 8.8 | J38: NORMAL | K38: =_xlfn.IFS('SERVICOS AUTPRO'!$J$25:$J$44="EXTRA 150%",((1)*2.5),'SERVICOS AUTPRO'!$J$25:$J$44="EXTRA 100%",((1)*2),'SERVICOS AUTPRO'!$J$25:$J$44="EXTRA 75%",((1)*1.75),'SERVICOS AUTPRO'!$J$25:$J$44="EXTRA 50%",((1)*1.5),'SERVICOS AUTPRO'!$J$25:$J$44="NORMAL",((1))) -> 1 | L38: =ServInt[[#This Row],[DIAS]]*ServInt[[#This Row],[PESSOAS]]*ServInt[[#This Row],[HORAS DIA]] -> 0 | M38: =(IF(ServInt[[#This Row],[CÓDIGO]]="","",LOOKUP(E38,BASE!A$4:A$125,BASE!G$4:G$125)))*ServInt[[#This Row],[HE CALC]] -> 0 | N38: =ServInt[[#This Row],[TOTAL HORAS]]*ServInt[[#This Row],[R$ / HORA]] -> 0 | O38: =BASE!$W$60 -> 0.66983974 | P38: =M38/O38 -> 0 | Q38: =N38/O38 -> 0 | S38: =(IF(E38="","",LOOKUP(E38,BASE!A$4:A$19,BASE!E$4:E$19)))*ServInt[[#This Row],[TOTAL HORAS]] -> 0 | T38: =IFERROR(ServInt[[#This Row],[TOTAL3]]*(RESUMO!$F$22/RESUMO!$F$14),0) -> 0 | W38: 14 | X38: Sistemas | Y38: Serviço | Z38: 0 | AA38: =LOOKUP(Z38,BASE!A$4:A$125,BASE!B$4:B$125) -> 0 | AD38: 8.8 | AE38: NORMAL | AF38: =_xlfn.IFS(ServExt[[#This Row],[TIPO H]]="EXTRA 150%",((1)*2.5),ServExt[[#This Row],[TIPO H]]="EXTRA 100%",((1)*2),ServExt[[#This Row],[TIPO H]]="EXTRA 75%",((1)*1.75),ServExt[[#This Row],[TIPO H]]="EXTRA 50%",((1)*1.5),ServExt[[#This Row],[TIPO H]]="NORMAL",((1))) -> 1 | AG38: =ServExt[[#This Row],[DIAS]]*ServExt[[#This Row],[PESSOAS]]*ServExt[[#This Row],[HORAS DIA]] -> 0 | AH38: =(IF(Z38="","",LOOKUP(Z38,BASE!A$4:A$125,BASE!H$4:H$125)))*ServExt[[#This Row],[HE CALC]] -> 0 | AI38: =ServExt[[#This Row],[TOTAL HORAS]]*ServExt[[#This Row],[R$ / HORA]] -> 0 | AJ38: =BASE!$W$60 -> 0.66983974 | AK38: =AH38/AJ38 -> 0 | AL38: =AI38/AJ38 -> 0 | AM38: =IF(OR(ServExt[[#This Row],[TIPO H]]="NORMAL",ServExt[[#This Row],[HORAS DIA]]>=8),ServExt[[#This Row],[PESSOAS]]*ServExt[[#This Row],[DIAS]]*2,0) -> 0 | AN38: =(IF(Z38="","",LOOKUP(Z38,BASE!A$4:A$19,BASE!E$4:E$19)))*ServExt[[#This Row],[TOTAL HORAS]] -> 0 | AO38: =IF(ServExt[[#This Row],[TIPO H]]="NORMAL",ServExt[[#This Row],[PESSOAS]],0) -> 0 | AP38: =IFERROR(ServExt[[#This Row],[TOTAL3]]*(RESUMO!$F$22/RESUMO!$F$14),0) -> 0 | AR38: 16 | AS38: Analista de Sistemas de Automação I
B39: 15 | C39: Projetos | D39: Serviço | E39: 0 | F39: =LOOKUP('SERVICOS AUTPRO'!$E$25:$E$64,BASE!A$4:A$125,BASE!B$4:B$125) -> 0 | I39: 8.8 | J39: NORMAL | K39: =_xlfn.IFS('SERVICOS AUTPRO'!$J$25:$J$44="EXTRA 150%",((1)*2.5),'SERVICOS AUTPRO'!$J$25:$J$44="EXTRA 100%",((1)*2),'SERVICOS AUTPRO'!$J$25:$J$44="EXTRA 75%",((1)*1.75),'SERVICOS AUTPRO'!$J$25:$J$44="EXTRA 50%",((1)*1.5),'SERVICOS AUTPRO'!$J$25:$J$44="NORMAL",((1))) -> 1 | L39: =ServInt[[#This Row],[DIAS]]*ServInt[[#This Row],[PESSOAS]]*ServInt[[#This Row],[HORAS DIA]] -> 0 | M39: =(IF(ServInt[[#This Row],[CÓDIGO]]="","",LOOKUP(E39,BASE!A$4:A$125,BASE!G$4:G$125)))*ServInt[[#This Row],[HE CALC]] -> 0 | N39: =ServInt[[#This Row],[TOTAL HORAS]]*ServInt[[#This Row],[R$ / HORA]] -> 0 | O39: =BASE!$W$60 -> 0.66983974 | P39: =M39/O39 -> 0 | Q39: =N39/O39 -> 0 | S39: =(IF(E39="","",LOOKUP(E39,BASE!A$4:A$19,BASE!E$4:E$19)))*ServInt[[#This Row],[TOTAL HORAS]] -> 0 | T39: =IFERROR(ServInt[[#This Row],[TOTAL3]]*(RESUMO!$F$22/RESUMO!$F$14),0) -> 0 | W39: 15 | X39: Sistemas | Y39: Serviço | Z39: 0 | AA39: =LOOKUP(Z39,BASE!A$4:A$125,BASE!B$4:B$125) -> 0 | AD39: 8.8 | AE39: NORMAL | AF39: =_xlfn.IFS(ServExt[[#This Row],[TIPO H]]="EXTRA 150%",((1)*2.5),ServExt[[#This Row],[TIPO H]]="EXTRA 100%",((1)*2),ServExt[[#This Row],[TIPO H]]="EXTRA 75%",((1)*1.75),ServExt[[#This Row],[TIPO H]]="EXTRA 50%",((1)*1.5),ServExt[[#This Row],[TIPO H]]="NORMAL",((1))) -> 1 | AG39: =ServExt[[#This Row],[DIAS]]*ServExt[[#This Row],[PESSOAS]]*ServExt[[#This Row],[HORAS DIA]] -> 0 | AH39: =(IF(Z39="","",LOOKUP(Z39,BASE!A$4:A$125,BASE!H$4:H$125)))*ServExt[[#This Row],[HE CALC]] -> 0 | AI39: =ServExt[[#This Row],[TOTAL HORAS]]*ServExt[[#This Row],[R$ / HORA]] -> 0 | AJ39: =BASE!$W$60 -> 0.66983974 | AK39: =AH39/AJ39 -> 0 | AL39: =AI39/AJ39 -> 0 | AM39: =IF(OR(ServExt[[#This Row],[TIPO H]]="NORMAL",ServExt[[#This Row],[HORAS DIA]]>=8),ServExt[[#This Row],[PESSOAS]]*ServExt[[#This Row],[DIAS]]*2,0) -> 0 | AN39: =(IF(Z39="","",LOOKUP(Z39,BASE!A$4:A$19,BASE!E$4:E$19)))*ServExt[[#This Row],[TOTAL HORAS]] -> 0 | AO39: =IF(ServExt[[#This Row],[TIPO H]]="NORMAL",ServExt[[#This Row],[PESSOAS]],0) -> 0 | AP39: =IFERROR(ServExt[[#This Row],[TOTAL3]]*(RESUMO!$F$22/RESUMO!$F$14),0) -> 0 | AR39: 17 | AS39: Analista de Sistemas de Automação II
B40: 16 | C40: Projetos | D40: Serviço | E40: 0 | F40: =LOOKUP('SERVICOS AUTPRO'!$E$25:$E$64,BASE!A$4:A$125,BASE!B$4:B$125) -> 0 | I40: 8.8 | J40: NORMAL | K40: =_xlfn.IFS('SERVICOS AUTPRO'!$J$25:$J$44="EXTRA 150%",((1)*2.5),'SERVICOS AUTPRO'!$J$25:$J$44="EXTRA 100%",((1)*2),'SERVICOS AUTPRO'!$J$25:$J$44="EXTRA 75%",((1)*1.75),'SERVICOS AUTPRO'!$J$25:$J$44="EXTRA 50%",((1)*1.5),'SERVICOS AUTPRO'!$J$25:$J$44="NORMAL",((1))) -> 1 | L40: =ServInt[[#This Row],[DIAS]]*ServInt[[#This Row],[PESSOAS]]*ServInt[[#This Row],[HORAS DIA]] -> 0 | M40: =(IF(ServInt[[#This Row],[CÓDIGO]]="","",LOOKUP(E40,BASE!A$4:A$125,BASE!G$4:G$125)))*ServInt[[#This Row],[HE CALC]] -> 0 | N40: =ServInt[[#This Row],[TOTAL HORAS]]*ServInt[[#This Row],[R$ / HORA]] -> 0 | O40: =BASE!$W$60 -> 0.66983974 | P40: =M40/O40 -> 0 | Q40: =N40/O40 -> 0 | S40: =(IF(E40="","",LOOKUP(E40,BASE!A$4:A$19,BASE!E$4:E$19)))*ServInt[[#This Row],[TOTAL HORAS]] -> 0 | T40: =IFERROR(ServInt[[#This Row],[TOTAL3]]*(RESUMO!$F$22/RESUMO!$F$14),0) -> 0 | W40: 16 | X40: Sistemas | Y40: Serviço | Z40: 0 | AA40: =LOOKUP(Z40,BASE!A$4:A$125,BASE!B$4:B$125) -> 0 | AD40: 8.8 | AE40: NORMAL | AF40: =_xlfn.IFS(ServExt[[#This Row],[TIPO H]]="EXTRA 150%",((1)*2.5),ServExt[[#This Row],[TIPO H]]="EXTRA 100%",((1)*2),ServExt[[#This Row],[TIPO H]]="EXTRA 75%",((1)*1.75),ServExt[[#This Row],[TIPO H]]="EXTRA 50%",((1)*1.5),ServExt[[#This Row],[TIPO H]]="NORMAL",((1))) -> 1 | AG40: =ServExt[[#This Row],[DIAS]]*ServExt[[#This Row],[PESSOAS]]*ServExt[[#This Row],[HORAS DIA]] -> 0 | AH40: =(IF(Z40="","",LOOKUP(Z40,BASE!A$4:A$125,BASE!H$4:H$125)))*ServExt[[#This Row],[HE CALC]] -> 0 | AI40: =ServExt[[#This Row],[TOTAL HORAS]]*ServExt[[#This Row],[R$ / HORA]] -> 0 | AJ40: =BASE!$W$60 -> 0.66983974 | AK40: =AH40/AJ40 -> 0 | AL40: =AI40/AJ40 -> 0 | AM40: =IF(OR(ServExt[[#This Row],[TIPO H]]="NORMAL",ServExt[[#This Row],[HORAS DIA]]>=8),ServExt[[#This Row],[PESSOAS]]*ServExt[[#This Row],[DIAS]]*2,0) -> 0 | AN40: =(IF(Z40="","",LOOKUP(Z40,BASE!A$4:A$19,BASE!E$4:E$19)))*ServExt[[#This Row],[TOTAL HORAS]] -> 0 | AO40: =IF(ServExt[[#This Row],[TIPO H]]="NORMAL",ServExt[[#This Row],[PESSOAS]],0) -> 0 | AP40: =IFERROR(ServExt[[#This Row],[TOTAL3]]*(RESUMO!$F$22/RESUMO!$F$14),0) -> 0 | AR40: 18 | AS40: Analista de Sistemas de Automação III
B41: 17 | C41: Projetos | D41: Serviço | E41: 0 | F41: =LOOKUP('SERVICOS AUTPRO'!$E$25:$E$64,BASE!A$4:A$125,BASE!B$4:B$125) -> 0 | I41: 8.8 | J41: NORMAL | K41: =_xlfn.IFS('SERVICOS AUTPRO'!$J$25:$J$44="EXTRA 150%",((1)*2.5),'SERVICOS AUTPRO'!$J$25:$J$44="EXTRA 100%",((1)*2),'SERVICOS AUTPRO'!$J$25:$J$44="EXTRA 75%",((1)*1.75),'SERVICOS AUTPRO'!$J$25:$J$44="EXTRA 50%",((1)*1.5),'SERVICOS AUTPRO'!$J$25:$J$44="NORMAL",((1))) -> 1 | L41: =ServInt[[#This Row],[DIAS]]*ServInt[[#This Row],[PESSOAS]]*ServInt[[#This Row],[HORAS DIA]] -> 0 | M41: =(IF(ServInt[[#This Row],[CÓDIGO]]="","",LOOKUP(E41,BASE!A$4:A$125,BASE!G$4:G$125)))*ServInt[[#This Row],[HE CALC]] -> 0 | N41: =ServInt[[#This Row],[TOTAL HORAS]]*ServInt[[#This Row],[R$ / HORA]] -> 0 | O41: =BASE!$W$60 -> 0.66983974 | P41: =M41/O41 -> 0 | Q41: =N41/O41 -> 0 | S41: =(IF(E41="","",LOOKUP(E41,BASE!A$4:A$19,BASE!E$4:E$19)))*ServInt[[#This Row],[TOTAL HORAS]] -> 0 | T41: =IFERROR(ServInt[[#This Row],[TOTAL3]]*(RESUMO!$F$22/RESUMO!$F$14),0) -> 0 | W41: 17 | X41: Sistemas | Y41: Serviço | Z41: 0 | AA41: =LOOKUP(Z41,BASE!A$4:A$125,BASE!B$4:B$125) -> 0 | AD41: 8.8 | AE41: NORMAL | AF41: =_xlfn.IFS(ServExt[[#This Row],[TIPO H]]="EXTRA 150%",((1)*2.5),ServExt[[#This Row],[TIPO H]]="EXTRA 100%",((1)*2),ServExt[[#This Row],[TIPO H]]="EXTRA 75%",((1)*1.75),ServExt[[#This Row],[TIPO H]]="EXTRA 50%",((1)*1.5),ServExt[[#This Row],[TIPO H]]="NORMAL",((1))) -> 1 | AG41: =ServExt[[#This Row],[DIAS]]*ServExt[[#This Row],[PESSOAS]]*ServExt[[#This Row],[HORAS DIA]] -> 0 | AH41: =(IF(Z41="","",LOOKUP(Z41,BASE!A$4:A$125,BASE!H$4:H$125)))*ServExt[[#This Row],[HE CALC]] -> 0 | AI41: =ServExt[[#This Row],[TOTAL HORAS]]*ServExt[[#This Row],[R$ / HORA]] -> 0 | AJ41: =BASE!$W$60 -> 0.66983974 | AK41: =AH41/AJ41 -> 0 | AL41: =AI41/AJ41 -> 0 | AM41: =IF(OR(ServExt[[#This Row],[TIPO H]]="NORMAL",ServExt[[#This Row],[HORAS DIA]]>=8),ServExt[[#This Row],[PESSOAS]]*ServExt[[#This Row],[DIAS]]*2,0) -> 0 | AN41: =(IF(Z41="","",LOOKUP(Z41,BASE!A$4:A$19,BASE!E$4:E$19)))*ServExt[[#This Row],[TOTAL HORAS]] -> 0 | AO41: =IF(ServExt[[#This Row],[TIPO H]]="NORMAL",ServExt[[#This Row],[PESSOAS]],0) -> 0 | AP41: =IFERROR(ServExt[[#This Row],[TOTAL3]]*(RESUMO!$F$22/RESUMO!$F$14),0) -> 0 | AR41: 19 | AS41: Analista de Sistemas de Automação IV
B42: 18 | C42: Projetos | D42: Serviço | E42: 0 | F42: =LOOKUP('SERVICOS AUTPRO'!$E$25:$E$64,BASE!A$4:A$125,BASE!B$4:B$125) -> 0 | I42: 8.8 | J42: NORMAL | K42: =_xlfn.IFS('SERVICOS AUTPRO'!$J$25:$J$44="EXTRA 150%",((1)*2.5),'SERVICOS AUTPRO'!$J$25:$J$44="EXTRA 100%",((1)*2),'SERVICOS AUTPRO'!$J$25:$J$44="EXTRA 75%",((1)*1.75),'SERVICOS AUTPRO'!$J$25:$J$44="EXTRA 50%",((1)*1.5),'SERVICOS AUTPRO'!$J$25:$J$44="NORMAL",((1))) -> 1 | L42: =ServInt[[#This Row],[DIAS]]*ServInt[[#This Row],[PESSOAS]]*ServInt[[#This Row],[HORAS DIA]] -> 0 | M42: =(IF(ServInt[[#This Row],[CÓDIGO]]="","",LOOKUP(E42,BASE!A$4:A$125,BASE!G$4:G$125)))*ServInt[[#This Row],[HE CALC]] -> 0 | N42: =ServInt[[#This Row],[TOTAL HORAS]]*ServInt[[#This Row],[R$ / HORA]] -> 0 | O42: =BASE!$W$60 -> 0.66983974 | P42: =M42/O42 -> 0 | Q42: =N42/O42 -> 0 | S42: =(IF(E42="","",LOOKUP(E42,BASE!A$4:A$19,BASE!E$4:E$19)))*ServInt[[#This Row],[TOTAL HORAS]] -> 0 | T42: =IFERROR(ServInt[[#This Row],[TOTAL3]]*(RESUMO!$F$22/RESUMO!$F$14),0) -> 0 | W42: 18 | X42: Sistemas | Y42: Serviço | Z42: 0 | AA42: =LOOKUP(Z42,BASE!A$4:A$125,BASE!B$4:B$125) -> 0 | AD42: 8.8 | AE42: NORMAL | AF42: =_xlfn.IFS(ServExt[[#This Row],[TIPO H]]="EXTRA 150%",((1)*2.5),ServExt[[#This Row],[TIPO H]]="EXTRA 100%",((1)*2),ServExt[[#This Row],[TIPO H]]="EXTRA 75%",((1)*1.75),ServExt[[#This Row],[TIPO H]]="EXTRA 50%",((1)*1.5),ServExt[[#This Row],[TIPO H]]="NORMAL",((1))) -> 1 | AG42: =ServExt[[#This Row],[DIAS]]*ServExt[[#This Row],[PESSOAS]]*ServExt[[#This Row],[HORAS DIA]] -> 0 | AH42: =(IF(Z42="","",LOOKUP(Z42,BASE!A$4:A$125,BASE!H$4:H$125)))*ServExt[[#This Row],[HE CALC]] -> 0 | AI42: =ServExt[[#This Row],[TOTAL HORAS]]*ServExt[[#This Row],[R$ / HORA]] -> 0 | AJ42: =BASE!$W$60 -> 0.66983974 | AK42: =AH42/AJ42 -> 0 | AL42: =AI42/AJ42 -> 0 | AM42: =IF(OR(ServExt[[#This Row],[TIPO H]]="NORMAL",ServExt[[#This Row],[HORAS DIA]]>=8),ServExt[[#This Row],[PESSOAS]]*ServExt[[#This Row],[DIAS]]*2,0) -> 0 | AN42: =(IF(Z42="","",LOOKUP(Z42,BASE!A$4:A$19,BASE!E$4:E$19)))*ServExt[[#This Row],[TOTAL HORAS]] -> 0 | AO42: =IF(ServExt[[#This Row],[TIPO H]]="NORMAL",ServExt[[#This Row],[PESSOAS]],0) -> 0 | AP42: =IFERROR(ServExt[[#This Row],[TOTAL3]]*(RESUMO!$F$22/RESUMO!$F$14),0) -> 0 | AR42: 20 | AS42: Analista de Sistemas de Automação V
B43: 19 | C43: Projetos | D43: Serviço | E43: 0 | F43: =LOOKUP('SERVICOS AUTPRO'!$E$25:$E$64,BASE!A$4:A$125,BASE!B$4:B$125) -> 0 | I43: 8.8 | J43: NORMAL | K43: =_xlfn.IFS('SERVICOS AUTPRO'!$J$25:$J$44="EXTRA 150%",((1)*2.5),'SERVICOS AUTPRO'!$J$25:$J$44="EXTRA 100%",((1)*2),'SERVICOS AUTPRO'!$J$25:$J$44="EXTRA 75%",((1)*1.75),'SERVICOS AUTPRO'!$J$25:$J$44="EXTRA 50%",((1)*1.5),'SERVICOS AUTPRO'!$J$25:$J$44="NORMAL",((1))) -> 1 | L43: =ServInt[[#This Row],[DIAS]]*ServInt[[#This Row],[PESSOAS]]*ServInt[[#This Row],[HORAS DIA]] -> 0 | M43: =(IF(ServInt[[#This Row],[CÓDIGO]]="","",LOOKUP(E43,BASE!A$4:A$125,BASE!G$4:G$125)))*ServInt[[#This Row],[HE CALC]] -> 0 | N43: =ServInt[[#This Row],[TOTAL HORAS]]*ServInt[[#This Row],[R$ / HORA]] -> 0 | O43: =BASE!$W$60 -> 0.66983974 | P43: =M43/O43 -> 0 | Q43: =N43/O43 -> 0 | S43: =(IF(E43="","",LOOKUP(E43,BASE!A$4:A$19,BASE!E$4:E$19)))*ServInt[[#This Row],[TOTAL HORAS]] -> 0 | T43: =IFERROR(ServInt[[#This Row],[TOTAL3]]*(RESUMO!$F$22/RESUMO!$F$14),0) -> 0 | W43: 19 | X43: Sistemas | Y43: Serviço | Z43: 0 | AA43: =LOOKUP(Z43,BASE!A$4:A$125,BASE!B$4:B$125) -> 0 | AB43: 0 | AD43: 8.8 | AE43: NORMAL | AF43: =_xlfn.IFS(ServExt[[#This Row],[TIPO H]]="EXTRA 150%",((1)*2.5),ServExt[[#This Row],[TIPO H]]="EXTRA 100%",((1)*2),ServExt[[#This Row],[TIPO H]]="EXTRA 75%",((1)*1.75),ServExt[[#This Row],[TIPO H]]="EXTRA 50%",((1)*1.5),ServExt[[#This Row],[TIPO H]]="NORMAL",((1))) -> 1 | AG43: =ServExt[[#This Row],[DIAS]]*ServExt[[#This Row],[PESSOAS]]*ServExt[[#This Row],[HORAS DIA]] -> 0 | AH43: =(IF(Z43="","",LOOKUP(Z43,BASE!A$4:A$125,BASE!H$4:H$125)))*ServExt[[#This Row],[HE CALC]] -> 0 | AI43: =ServExt[[#This Row],[TOTAL HORAS]]*ServExt[[#This Row],[R$ / HORA]] -> 0 | AJ43: =BASE!$W$60 -> 0.66983974 | AK43: =AH43/AJ43 -> 0 | AL43: =AI43/AJ43 -> 0 | AM43: =IF(OR(ServExt[[#This Row],[TIPO H]]="NORMAL",ServExt[[#This Row],[HORAS DIA]]>=8),ServExt[[#This Row],[PESSOAS]]*ServExt[[#This Row],[DIAS]]*2,0) -> 0 | AN43: =(IF(Z43="","",LOOKUP(Z43,BASE!A$4:A$19,BASE!E$4:E$19)))*ServExt[[#This Row],[TOTAL HORAS]] -> 0 | AO43: =IF(ServExt[[#This Row],[TIPO H]]="NORMAL",ServExt[[#This Row],[PESSOAS]],0) -> 0 | AP43: =IFERROR(ServExt[[#This Row],[TOTAL3]]*(RESUMO!$F$22/RESUMO!$F$14),0) -> 0 | AR43: 21 | AS43: Desenhista Projetista I
B44: 20 | C44: Projetos | D44: Serviço | E44: 0 | F44: =LOOKUP('SERVICOS AUTPRO'!$E$25:$E$64,BASE!A$4:A$125,BASE!B$4:B$125) -> 0 | I44: 8.8 | J44: NORMAL | K44: =_xlfn.IFS('SERVICOS AUTPRO'!$J$25:$J$44="EXTRA 150%",((1)*2.5),'SERVICOS AUTPRO'!$J$25:$J$44="EXTRA 100%",((1)*2),'SERVICOS AUTPRO'!$J$25:$J$44="EXTRA 75%",((1)*1.75),'SERVICOS AUTPRO'!$J$25:$J$44="EXTRA 50%",((1)*1.5),'SERVICOS AUTPRO'!$J$25:$J$44="NORMAL",((1))) -> 1 | L44: =ServInt[[#This Row],[DIAS]]*ServInt[[#This Row],[PESSOAS]]*ServInt[[#This Row],[HORAS DIA]] -> 0 | M44: =(IF(ServInt[[#This Row],[CÓDIGO]]="","",LOOKUP(E44,BASE!A$4:A$125,BASE!G$4:G$125)))*ServInt[[#This Row],[HE CALC]] -> 0 | N44: =ServInt[[#This Row],[TOTAL HORAS]]*ServInt[[#This Row],[R$ / HORA]] -> 0 | O44: =BASE!$W$60 -> 0.66983974 | P44: =M44/O44 -> 0 | Q44: =N44/O44 -> 0 | S44: =(IF(E44="","",LOOKUP(E44,BASE!A$4:A$19,BASE!E$4:E$19)))*ServInt[[#This Row],[TOTAL HORAS]] -> 0 | T44: =IFERROR(ServInt[[#This Row],[TOTAL3]]*(RESUMO!$F$22/RESUMO!$F$14),0) -> 0 | W44: 20 | X44: Sistemas | Y44: Serviço | Z44: 0 | AA44: =LOOKUP(Z44,BASE!A$4:A$125,BASE!B$4:B$125) -> 0 | AB44: 0 | AD44: 8.8 | AE44: NORMAL | AF44: =_xlfn.IFS(ServExt[[#This Row],[TIPO H]]="EXTRA 150%",((1)*2.5),ServExt[[#This Row],[TIPO H]]="EXTRA 100%",((1)*2),ServExt[[#This Row],[TIPO H]]="EXTRA 75%",((1)*1.75),ServExt[[#This Row],[TIPO H]]="EXTRA 50%",((1)*1.5),ServExt[[#This Row],[TIPO H]]="NORMAL",((1))) -> 1 | AG44: =ServExt[[#This Row],[DIAS]]*ServExt[[#This Row],[PESSOAS]]*ServExt[[#This Row],[HORAS DIA]] -> 0 | AH44: =(IF(Z44="","",LOOKUP(Z44,BASE!A$4:A$125,BASE!H$4:H$125)))*ServExt[[#This Row],[HE CALC]] -> 0 | AI44: =ServExt[[#This Row],[TOTAL HORAS]]*ServExt[[#This Row],[R$ / HORA]] -> 0 | AJ44: =BASE!$W$60 -> 0.66983974 | AK44: =AH44/AJ44 -> 0 | AL44: =AI44/AJ44 -> 0 | AM44: =IF(OR(ServExt[[#This Row],[TIPO H]]="NORMAL",ServExt[[#This Row],[HORAS DIA]]>=8),ServExt[[#This Row],[PESSOAS]]*ServExt[[#This Row],[DIAS]]*2,0) -> 0 | AN44: =(IF(Z44="","",LOOKUP(Z44,BASE!A$4:A$19,BASE!E$4:E$19)))*ServExt[[#This Row],[TOTAL HORAS]] -> 0 | AO44: =IF(ServExt[[#This Row],[TIPO H]]="NORMAL",ServExt[[#This Row],[PESSOAS]],0) -> 0 | AP44: =IFERROR(ServExt[[#This Row],[TOTAL3]]*(RESUMO!$F$22/RESUMO!$F$14),0) -> 0 | AR44: 22 | AS44: Desenhista Projetista II
B45: 21 | C45: Projetos | D45: Serviço | E45: 0 | F45: =LOOKUP('SERVICOS AUTPRO'!$E$25:$E$64,BASE!A$4:A$125,BASE!B$4:B$125) -> 0 | I45: 8.8 | J45: NORMAL | K45: =_xlfn.IFS('SERVICOS AUTPRO'!$J$25:$J$64="EXTRA 150%",((1)*2.5),'SERVICOS AUTPRO'!$J$25:$J$64="EXTRA 100%",((1)*2),'SERVICOS AUTPRO'!$J$25:$J$64="EXTRA 75%",((1)*1.75),'SERVICOS AUTPRO'!$J$25:$J$64="EXTRA 50%",((1)*1.5),'SERVICOS AUTPRO'!$J$25:$J$64="NORMAL",((1))) -> 1 | L45: =ServInt[[#This Row],[DIAS]]*ServInt[[#This Row],[PESSOAS]]*ServInt[[#This Row],[HORAS DIA]] -> 0 | M45: =(IF(ServInt[[#This Row],[CÓDIGO]]="","",LOOKUP(E45,BASE!A$4:A$125,BASE!G$4:G$125)))*ServInt[[#This Row],[HE CALC]] -> 0 | N45: =ServInt[[#This Row],[TOTAL HORAS]]*ServInt[[#This Row],[R$ / HORA]] -> 0 | O45: =BASE!$W$60 -> 0.66983974 | P45: =M45/O45 -> 0 | Q45: =N45/O45 -> 0 | S45: =(IF(E45="","",LOOKUP(E45,BASE!A$4:A$19,BASE!E$4:E$19)))*ServInt[[#This Row],[TOTAL HORAS]] -> 0 | T45: =IFERROR(ServInt[[#This Row],[TOTAL3]]*(RESUMO!$F$22/RESUMO!$F$14),0) -> 0 | W45: 21 | X45: Sistemas | Y45: Serviço | Z45: 0 | AA45: =LOOKUP(Z45,BASE!A$4:A$125,BASE!B$4:B$125) -> 0 | AD45: 8.8 | AE45: NORMAL | AF45: =_xlfn.IFS(ServExt[[#This Row],[TIPO H]]="EXTRA 150%",((1)*2.5),ServExt[[#This Row],[TIPO H]]="EXTRA 100%",((1)*2),ServExt[[#This Row],[TIPO H]]="EXTRA 75%",((1)*1.75),ServExt[[#This Row],[TIPO H]]="EXTRA 50%",((1)*1.5),ServExt[[#This Row],[TIPO H]]="NORMAL",((1))) -> 1 | AG45: =ServExt[[#This Row],[DIAS]]*ServExt[[#This Row],[PESSOAS]]*ServExt[[#This Row],[HORAS DIA]] -> 0 | AH45: =(IF(Z45="","",LOOKUP(Z45,BASE!A$4:A$125,BASE!H$4:H$125)))*ServExt[[#This Row],[HE CALC]] -> 0 | AI45: =ServExt[[#This Row],[TOTAL HORAS]]*ServExt[[#This Row],[R$ / HORA]] -> 0 | AJ45: =BASE!$W$60 -> 0.66983974 | AK45: =AH45/AJ45 -> 0 | AL45: =AI45/AJ45 -> 0 | AM45: =IF(OR(ServExt[[#This Row],[TIPO H]]="NORMAL",ServExt[[#This Row],[HORAS DIA]]>=8),ServExt[[#This Row],[PESSOAS]]*ServExt[[#This Row],[DIAS]]*2,0) -> 0 | AN45: =(IF(Z45="","",LOOKUP(Z45,BASE!A$4:A$19,BASE!E$4:E$19)))*ServExt[[#This Row],[TOTAL HORAS]] -> 0 | AO45: =IF(ServExt[[#This Row],[TIPO H]]="NORMAL",ServExt[[#This Row],[PESSOAS]],0) -> 0 | AP45: =IFERROR(ServExt[[#This Row],[TOTAL3]]*(RESUMO!$F$22/RESUMO!$F$14),0) -> 0 | AR45: 23 | AS45: Desenhista Projetista III
B46: 22 | C46: Projetos | D46: Serviço | E46: 0 | F46: =LOOKUP('SERVICOS AUTPRO'!$E$25:$E$64,BASE!A$4:A$125,BASE!B$4:B$125) -> 0 | I46: 8.8 | J46: NORMAL | K46: =_xlfn.IFS('SERVICOS AUTPRO'!$J$25:$J$64="EXTRA 150%",((1)*2.5),'SERVICOS AUTPRO'!$J$25:$J$64="EXTRA 100%",((1)*2),'SERVICOS AUTPRO'!$J$25:$J$64="EXTRA 75%",((1)*1.75),'SERVICOS AUTPRO'!$J$25:$J$64="EXTRA 50%",((1)*1.5),'SERVICOS AUTPRO'!$J$25:$J$64="NORMAL",((1))) -> 1 | L46: =ServInt[[#This Row],[DIAS]]*ServInt[[#This Row],[PESSOAS]]*ServInt[[#This Row],[HORAS DIA]] -> 0 | M46: =(IF(ServInt[[#This Row],[CÓDIGO]]="","",LOOKUP(E46,BASE!A$4:A$125,BASE!G$4:G$125)))*ServInt[[#This Row],[HE CALC]] -> 0 | N46: =ServInt[[#This Row],[TOTAL HORAS]]*ServInt[[#This Row],[R$ / HORA]] -> 0 | O46: =BASE!$W$60 -> 0.66983974 | P46: =M46/O46 -> 0 | Q46: =N46/O46 -> 0 | S46: =(IF(E46="","",LOOKUP(E46,BASE!A$4:A$19,BASE!E$4:E$19)))*ServInt[[#This Row],[TOTAL HORAS]] -> 0 | T46: =IFERROR(ServInt[[#This Row],[TOTAL3]]*(RESUMO!$F$22/RESUMO!$F$14),0) -> 0 | W46: 22 | X46: Sistemas | Y46: Serviço | Z46: 0 | AA46: =LOOKUP(Z46,BASE!A$4:A$125,BASE!B$4:B$125) -> 0 | AD46: 8.8 | AE46: NORMAL | AF46: =_xlfn.IFS(ServExt[[#This Row],[TIPO H]]="EXTRA 150%",((1)*2.5),ServExt[[#This Row],[TIPO H]]="EXTRA 100%",((1)*2),ServExt[[#This Row],[TIPO H]]="EXTRA 75%",((1)*1.75),ServExt[[#This Row],[TIPO H]]="EXTRA 50%",((1)*1.5),ServExt[[#This Row],[TIPO H]]="NORMAL",((1))) -> 1 | AG46: =ServExt[[#This Row],[DIAS]]*ServExt[[#This Row],[PESSOAS]]*ServExt[[#This Row],[HORAS DIA]] -> 0 | AH46: =(IF(Z46="","",LOOKUP(Z46,BASE!A$4:A$125,BASE!H$4:H$125)))*ServExt[[#This Row],[HE CALC]] -> 0 | AI46: =ServExt[[#This Row],[TOTAL HORAS]]*ServExt[[#This Row],[R$ / HORA]] -> 0 | AJ46: =BASE!$W$60 -> 0.66983974 | AK46: =AH46/AJ46 -> 0 | AL46: =AI46/AJ46 -> 0 | AM46: =IF(OR(ServExt[[#This Row],[TIPO H]]="NORMAL",ServExt[[#This Row],[HORAS DIA]]>=8),ServExt[[#This Row],[PESSOAS]]*ServExt[[#This Row],[DIAS]]*2,0) -> 0 | AN46: =(IF(Z46="","",LOOKUP(Z46,BASE!A$4:A$19,BASE!E$4:E$19)))*ServExt[[#This Row],[TOTAL HORAS]] -> 0 | AO46: =IF(ServExt[[#This Row],[TIPO H]]="NORMAL",ServExt[[#This Row],[PESSOAS]],0) -> 0 | AP46: =IFERROR(ServExt[[#This Row],[TOTAL3]]*(RESUMO!$F$22/RESUMO!$F$14),0) -> 0 | AR46: 24 | AS46: Desenhista Projetista IV
B47: 23 | C47: Projetos | D47: Serviço | E47: 0 | F47: =LOOKUP('SERVICOS AUTPRO'!$E$25:$E$64,BASE!A$4:A$125,BASE!B$4:B$125) -> 0 | I47: 8.8 | J47: NORMAL | K47: =_xlfn.IFS('SERVICOS AUTPRO'!$J$25:$J$62="EXTRA 150%",((1)*2.5),'SERVICOS AUTPRO'!$J$25:$J$62="EXTRA 100%",((1)*2),'SERVICOS AUTPRO'!$J$25:$J$62="EXTRA 75%",((1)*1.75),'SERVICOS AUTPRO'!$J$25:$J$62="EXTRA 50%",((1)*1.5),'SERVICOS AUTPRO'!$J$25:$J$62="NORMAL",((1))) -> 1 | L47: =ServInt[[#This Row],[DIAS]]*ServInt[[#This Row],[PESSOAS]]*ServInt[[#This Row],[HORAS DIA]] -> 0 | M47: =(IF(ServInt[[#This Row],[CÓDIGO]]="","",LOOKUP(E47,BASE!A$4:A$125,BASE!G$4:G$125)))*ServInt[[#This Row],[HE CALC]] -> 0 | N47: =ServInt[[#This Row],[TOTAL HORAS]]*ServInt[[#This Row],[R$ / HORA]] -> 0 | O47: =BASE!$W$60 -> 0.66983974 | P47: =M47/O47 -> 0 | Q47: =N47/O47 -> 0 | S47: =(IF(E47="","",LOOKUP(E47,BASE!A$4:A$19,BASE!E$4:E$19)))*ServInt[[#This Row],[TOTAL HORAS]] -> 0 | T47: =IFERROR(ServInt[[#This Row],[TOTAL3]]*(RESUMO!$F$22/RESUMO!$F$14),0) -> 0 | W47: 23 | X47: Sistemas | Y47: Serviço | Z47: 0 | AA47: =LOOKUP(Z47,BASE!A$4:A$125,BASE!B$4:B$125) -> 0 | AD47: 8.8 | AE47: NORMAL | AF47: =_xlfn.IFS(ServExt[[#This Row],[TIPO H]]="EXTRA 150%",((1)*2.5),ServExt[[#This Row],[TIPO H]]="EXTRA 100%",((1)*2),ServExt[[#This Row],[TIPO H]]="EXTRA 75%",((1)*1.75),ServExt[[#This Row],[TIPO H]]="EXTRA 50%",((1)*1.5),ServExt[[#This Row],[TIPO H]]="NORMAL",((1))) -> 1 | AG47: =ServExt[[#This Row],[DIAS]]*ServExt[[#This Row],[PESSOAS]]*ServExt[[#This Row],[HORAS DIA]] -> 0 | AH47: =(IF(Z47="","",LOOKUP(Z47,BASE!A$4:A$125,BASE!H$4:H$125)))*ServExt[[#This Row],[HE CALC]] -> 0 | AI47: =ServExt[[#This Row],[TOTAL HORAS]]*ServExt[[#This Row],[R$ / HORA]] -> 0 | AJ47: =BASE!$W$60 -> 0.66983974 | AK47: =AH47/AJ47 -> 0 | AL47: =AI47/AJ47 -> 0 | AM47: =IF(OR(ServExt[[#This Row],[TIPO H]]="NORMAL",ServExt[[#This Row],[HORAS DIA]]>=8),ServExt[[#This Row],[PESSOAS]]*ServExt[[#This Row],[DIAS]]*2,0) -> 0 | AN47: =(IF(Z47="","",LOOKUP(Z47,BASE!A$4:A$19,BASE!E$4:E$19)))*ServExt[[#This Row],[TOTAL HORAS]] -> 0 | AO47: =IF(ServExt[[#This Row],[TIPO H]]="NORMAL",ServExt[[#This Row],[PESSOAS]],0) -> 0 | AP47: =IFERROR(ServExt[[#This Row],[TOTAL3]]*(RESUMO!$F$22/RESUMO!$F$14),0) -> 0 | AR47: 25 | AS47: Desenhista Projetista V
B48: 24 | C48: Projetos | D48: Serviço | E48: 0 | F48: =LOOKUP('SERVICOS AUTPRO'!$E$25:$E$64,BASE!A$4:A$125,BASE!B$4:B$125) -> 0 | I48: 8.8 | J48: NORMAL | K48: =_xlfn.IFS('SERVICOS AUTPRO'!$J$25:$J$62="EXTRA 150%",((1)*2.5),'SERVICOS AUTPRO'!$J$25:$J$62="EXTRA 100%",((1)*2),'SERVICOS AUTPRO'!$J$25:$J$62="EXTRA 75%",((1)*1.75),'SERVICOS AUTPRO'!$J$25:$J$62="EXTRA 50%",((1)*1.5),'SERVICOS AUTPRO'!$J$25:$J$62="NORMAL",((1))) -> 1 | L48: =ServInt[[#This Row],[DIAS]]*ServInt[[#This Row],[PESSOAS]]*ServInt[[#This Row],[HORAS DIA]] -> 0 | M48: =(IF(ServInt[[#This Row],[CÓDIGO]]="","",LOOKUP(E48,BASE!A$4:A$125,BASE!G$4:G$125)))*ServInt[[#This Row],[HE CALC]] -> 0 | N48: =ServInt[[#This Row],[TOTAL HORAS]]*ServInt[[#This Row],[R$ / HORA]] -> 0 | O48: =BASE!$W$60 -> 0.66983974 | P48: =M48/O48 -> 0 | Q48: =N48/O48 -> 0 | S48: =(IF(E48="","",LOOKUP(E48,BASE!A$4:A$19,BASE!E$4:E$19)))*ServInt[[#This Row],[TOTAL HORAS]] -> 0 | T48: =IFERROR(ServInt[[#This Row],[TOTAL3]]*(RESUMO!$F$22/RESUMO!$F$14),0) -> 0 | W48: 24 | X48: Sistemas | Y48: Serviço | Z48: 0 | AA48: =LOOKUP(Z48,BASE!A$4:A$125,BASE!B$4:B$125) -> 0 | AD48: 8.8 | AE48: NORMAL | AF48: =_xlfn.IFS(ServExt[[#This Row],[TIPO H]]="EXTRA 150%",((1)*2.5),ServExt[[#This Row],[TIPO H]]="EXTRA 100%",((1)*2),ServExt[[#This Row],[TIPO H]]="EXTRA 75%",((1)*1.75),ServExt[[#This Row],[TIPO H]]="EXTRA 50%",((1)*1.5),ServExt[[#This Row],[TIPO H]]="NORMAL",((1))) -> 1 | AG48: =ServExt[[#This Row],[DIAS]]*ServExt[[#This Row],[PESSOAS]]*ServExt[[#This Row],[HORAS DIA]] -> 0 | AH48: =(IF(Z48="","",LOOKUP(Z48,BASE!A$4:A$125,BASE!H$4:H$125)))*ServExt[[#This Row],[HE CALC]] -> 0 | AI48: =ServExt[[#This Row],[TOTAL HORAS]]*ServExt[[#This Row],[R$ / HORA]] -> 0 | AJ48: =BASE!$W$60 -> 0.66983974 | AK48: =AH48/AJ48 -> 0 | AL48: =AI48/AJ48 -> 0 | AM48: =IF(OR(ServExt[[#This Row],[TIPO H]]="NORMAL",ServExt[[#This Row],[HORAS DIA]]>=8),ServExt[[#This Row],[PESSOAS]]*ServExt[[#This Row],[DIAS]]*2,0) -> 0 | AN48: =(IF(Z48="","",LOOKUP(Z48,BASE!A$4:A$19,BASE!E$4:E$19)))*ServExt[[#This Row],[TOTAL HORAS]] -> 0 | AO48: =IF(ServExt[[#This Row],[TIPO H]]="NORMAL",ServExt[[#This Row],[PESSOAS]],0) -> 0 | AP48: =IFERROR(ServExt[[#This Row],[TOTAL3]]*(RESUMO!$F$22/RESUMO!$F$14),0) -> 0 | AR48: 26 | AS48: Projetista Elétrico I
B49: 25 | C49: Projetos | D49: Serviço | E49: 0 | F49: =LOOKUP('SERVICOS AUTPRO'!$E$25:$E$64,BASE!A$4:A$125,BASE!B$4:B$125) -> 0 | I49: 8.8 | J49: NORMAL | K49: =_xlfn.IFS('SERVICOS AUTPRO'!$J$25:$J$62="EXTRA 150%",((1)*2.5),'SERVICOS AUTPRO'!$J$25:$J$62="EXTRA 100%",((1)*2),'SERVICOS AUTPRO'!$J$25:$J$62="EXTRA 75%",((1)*1.75),'SERVICOS AUTPRO'!$J$25:$J$62="EXTRA 50%",((1)*1.5),'SERVICOS AUTPRO'!$J$25:$J$62="NORMAL",((1))) -> 1 | L49: =ServInt[[#This Row],[DIAS]]*ServInt[[#This Row],[PESSOAS]]*ServInt[[#This Row],[HORAS DIA]] -> 0 | M49: =(IF(ServInt[[#This Row],[CÓDIGO]]="","",LOOKUP(E49,BASE!A$4:A$125,BASE!G$4:G$125)))*ServInt[[#This Row],[HE CALC]] -> 0 | N49: =ServInt[[#This Row],[TOTAL HORAS]]*ServInt[[#This Row],[R$ / HORA]] -> 0 | O49: =BASE!$W$60 -> 0.66983974 | P49: =M49/O49 -> 0 | Q49: =N49/O49 -> 0 | S49: =(IF(E49="","",LOOKUP(E49,BASE!A$4:A$19,BASE!E$4:E$19)))*ServInt[[#This Row],[TOTAL HORAS]] -> 0 | T49: =IFERROR(ServInt[[#This Row],[TOTAL3]]*(RESUMO!$F$22/RESUMO!$F$14),0) -> 0 | W49: 25 | X49: Sistemas | Y49: Serviço | Z49: 0 | AA49: =LOOKUP(Z49,BASE!A$4:A$125,BASE!B$4:B$125) -> 0 | AD49: 8.8 | AE49: NORMAL | AF49: =_xlfn.IFS(ServExt[[#This Row],[TIPO H]]="EXTRA 150%",((1)*2.5),ServExt[[#This Row],[TIPO H]]="EXTRA 100%",((1)*2),ServExt[[#This Row],[TIPO H]]="EXTRA 75%",((1)*1.75),ServExt[[#This Row],[TIPO H]]="EXTRA 50%",((1)*1.5),ServExt[[#This Row],[TIPO H]]="NORMAL",((1))) -> 1 | AG49: =ServExt[[#This Row],[DIAS]]*ServExt[[#This Row],[PESSOAS]]*ServExt[[#This Row],[HORAS DIA]] -> 0 | AH49: =(IF(Z49="","",LOOKUP(Z49,BASE!A$4:A$125,BASE!H$4:H$125)))*ServExt[[#This Row],[HE CALC]] -> 0 | AI49: =ServExt[[#This Row],[TOTAL HORAS]]*ServExt[[#This Row],[R$ / HORA]] -> 0 | AJ49: =BASE!$W$60 -> 0.66983974 | AK49: =AH49/AJ49 -> 0 | AL49: =AI49/AJ49 -> 0 | AM49: =IF(OR(ServExt[[#This Row],[TIPO H]]="NORMAL",ServExt[[#This Row],[HORAS DIA]]>=8),ServExt[[#This Row],[PESSOAS]]*ServExt[[#This Row],[DIAS]]*2,0) -> 0 | AN49: =(IF(Z49="","",LOOKUP(Z49,BASE!A$4:A$19,BASE!E$4:E$19)))*ServExt[[#This Row],[TOTAL HORAS]] -> 0 | AO49: =IF(ServExt[[#This Row],[TIPO H]]="NORMAL",ServExt[[#This Row],[PESSOAS]],0) -> 0 | AP49: =IFERROR(ServExt[[#This Row],[TOTAL3]]*(RESUMO!$F$22/RESUMO!$F$14),0) -> 0 | AR49: 27 | AS49: Projetista Elétrico II
B50: 26 | C50: Projetos | D50: Serviço | E50: 0 | F50: =LOOKUP('SERVICOS AUTPRO'!$E$25:$E$64,BASE!A$4:A$125,BASE!B$4:B$125) -> 0 | I50: 8.8 | J50: NORMAL | K50: =_xlfn.IFS('SERVICOS AUTPRO'!$J$25:$J$62="EXTRA 150%",((1)*2.5),'SERVICOS AUTPRO'!$J$25:$J$62="EXTRA 100%",((1)*2),'SERVICOS AUTPRO'!$J$25:$J$62="EXTRA 75%",((1)*1.75),'SERVICOS AUTPRO'!$J$25:$J$62="EXTRA 50%",((1)*1.5),'SERVICOS AUTPRO'!$J$25:$J$62="NORMAL",((1))) -> 1 | L50: =ServInt[[#This Row],[DIAS]]*ServInt[[#This Row],[PESSOAS]]*ServInt[[#This Row],[HORAS DIA]] -> 0 | M50: =(IF(ServInt[[#This Row],[CÓDIGO]]="","",LOOKUP(E50,BASE!A$4:A$125,BASE!G$4:G$125)))*ServInt[[#This Row],[HE CALC]] -> 0 | N50: =ServInt[[#This Row],[TOTAL HORAS]]*ServInt[[#This Row],[R$ / HORA]] -> 0 | O50: =BASE!$W$60 -> 0.66983974 | P50: =M50/O50 -> 0 | Q50: =N50/O50 -> 0 | S50: =(IF(E50="","",LOOKUP(E50,BASE!A$4:A$19,BASE!E$4:E$19)))*ServInt[[#This Row],[TOTAL HORAS]] -> 0 | T50: =IFERROR(ServInt[[#This Row],[TOTAL3]]*(RESUMO!$F$22/RESUMO!$F$14),0) -> 0 | W50: 26 | X50: Sistemas | Y50: Serviço | Z50: 0 | AA50: =LOOKUP(Z50,BASE!A$4:A$125,BASE!B$4:B$125) -> 0 | AD50: 8.8 | AE50: NORMAL | AF50: =_xlfn.IFS(ServExt[[#This Row],[TIPO H]]="EXTRA 150%",((1)*2.5),ServExt[[#This Row],[TIPO H]]="EXTRA 100%",((1)*2),ServExt[[#This Row],[TIPO H]]="EXTRA 75%",((1)*1.75),ServExt[[#This Row],[TIPO H]]="EXTRA 50%",((1)*1.5),ServExt[[#This Row],[TIPO H]]="NORMAL",((1))) -> 1 | AG50: =ServExt[[#This Row],[DIAS]]*ServExt[[#This Row],[PESSOAS]]*ServExt[[#This Row],[HORAS DIA]] -> 0 | AH50: =(IF(Z50="","",LOOKUP(Z50,BASE!A$4:A$125,BASE!H$4:H$125)))*ServExt[[#This Row],[HE CALC]] -> 0 | AI50: =ServExt[[#This Row],[TOTAL HORAS]]*ServExt[[#This Row],[R$ / HORA]] -> 0 | AJ50: =BASE!$W$60 -> 0.66983974 | AK50: =AH50/AJ50 -> 0 | AL50: =AI50/AJ50 -> 0 | AM50: =IF(OR(ServExt[[#This Row],[TIPO H]]="NORMAL",ServExt[[#This Row],[HORAS DIA]]>=8),ServExt[[#This Row],[PESSOAS]]*ServExt[[#This Row],[DIAS]]*2,0) -> 0 | AN50: =(IF(Z50="","",LOOKUP(Z50,BASE!A$4:A$19,BASE!E$4:E$19)))*ServExt[[#This Row],[TOTAL HORAS]] -> 0 | AO50: =IF(ServExt[[#This Row],[TIPO H]]="NORMAL",ServExt[[#This Row],[PESSOAS]],0) -> 0 | AP50: =IFERROR(ServExt[[#This Row],[TOTAL3]]*(RESUMO!$F$22/RESUMO!$F$14),0) -> 0 | AR50: 28 | AS50: Projetista Elétrico III
B51: 27 | C51: Projetos | D51: Serviço | E51: 0 | F51: =LOOKUP('SERVICOS AUTPRO'!$E$25:$E$64,BASE!A$4:A$125,BASE!B$4:B$125) -> 0 | I51: 8.8 | J51: NORMAL | K51: =_xlfn.IFS('SERVICOS AUTPRO'!$J$25:$J$62="EXTRA 150%",((1)*2.5),'SERVICOS AUTPRO'!$J$25:$J$62="EXTRA 100%",((1)*2),'SERVICOS AUTPRO'!$J$25:$J$62="EXTRA 75%",((1)*1.75),'SERVICOS AUTPRO'!$J$25:$J$62="EXTRA 50%",((1)*1.5),'SERVICOS AUTPRO'!$J$25:$J$62="NORMAL",((1))) -> 1 | L51: =ServInt[[#This Row],[DIAS]]*ServInt[[#This Row],[PESSOAS]]*ServInt[[#This Row],[HORAS DIA]] -> 0 | M51: =(IF(ServInt[[#This Row],[CÓDIGO]]="","",LOOKUP(E51,BASE!A$4:A$125,BASE!G$4:G$125)))*ServInt[[#This Row],[HE CALC]] -> 0 | N51: =ServInt[[#This Row],[TOTAL HORAS]]*ServInt[[#This Row],[R$ / HORA]] -> 0 | O51: =BASE!$W$60 -> 0.66983974 | P51: =M51/O51 -> 0 | Q51: =N51/O51 -> 0 | S51: =(IF(E51="","",LOOKUP(E51,BASE!A$4:A$19,BASE!E$4:E$19)))*ServInt[[#This Row],[TOTAL HORAS]] -> 0 | T51: =IFERROR(ServInt[[#This Row],[TOTAL3]]*(RESUMO!$F$22/RESUMO!$F$14),0) -> 0 | W51: 27 | X51: Sistemas | Y51: Serviço | Z51: 0 | AA51: =LOOKUP(Z51,BASE!A$4:A$125,BASE!B$4:B$125) -> 0 | AD51: 8.8 | AE51: NORMAL | AF51: =_xlfn.IFS(ServExt[[#This Row],[TIPO H]]="EXTRA 150%",((1)*2.5),ServExt[[#This Row],[TIPO H]]="EXTRA 100%",((1)*2),ServExt[[#This Row],[TIPO H]]="EXTRA 75%",((1)*1.75),ServExt[[#This Row],[TIPO H]]="EXTRA 50%",((1)*1.5),ServExt[[#This Row],[TIPO H]]="NORMAL",((1))) -> 1 | AG51: =ServExt[[#This Row],[DIAS]]*ServExt[[#This Row],[PESSOAS]]*ServExt[[#This Row],[HORAS DIA]] -> 0 | AH51: =(IF(Z51="","",LOOKUP(Z51,BASE!A$4:A$125,BASE!H$4:H$125)))*ServExt[[#This Row],[HE CALC]] -> 0 | AI51: =ServExt[[#This Row],[TOTAL HORAS]]*ServExt[[#This Row],[R$ / HORA]] -> 0 | AJ51: =BASE!$W$60 -> 0.66983974 | AK51: =AH51/AJ51 -> 0 | AL51: =AI51/AJ51 -> 0 | AM51: =IF(OR(ServExt[[#This Row],[TIPO H]]="NORMAL",ServExt[[#This Row],[HORAS DIA]]>=8),ServExt[[#This Row],[PESSOAS]]*ServExt[[#This Row],[DIAS]]*2,0) -> 0 | AN51: =(IF(Z51="","",LOOKUP(Z51,BASE!A$4:A$19,BASE!E$4:E$19)))*ServExt[[#This Row],[TOTAL HORAS]] -> 0 | AO51: =IF(ServExt[[#This Row],[TIPO H]]="NORMAL",ServExt[[#This Row],[PESSOAS]],0) -> 0 | AP51: =IFERROR(ServExt[[#This Row],[TOTAL3]]*(RESUMO!$F$22/RESUMO!$F$14),0) -> 0 | AR51: 29 | AS51: Projetista Elétrico IV
B52: 28 | C52: Projetos | D52: Serviço | E52: 0 | F52: =LOOKUP('SERVICOS AUTPRO'!$E$25:$E$64,BASE!A$4:A$125,BASE!B$4:B$125) -> 0 | I52: 8.8 | J52: NORMAL | K52: =_xlfn.IFS('SERVICOS AUTPRO'!$J$25:$J$62="EXTRA 150%",((1)*2.5),'SERVICOS AUTPRO'!$J$25:$J$62="EXTRA 100%",((1)*2),'SERVICOS AUTPRO'!$J$25:$J$62="EXTRA 75%",((1)*1.75),'SERVICOS AUTPRO'!$J$25:$J$62="EXTRA 50%",((1)*1.5),'SERVICOS AUTPRO'!$J$25:$J$62="NORMAL",((1))) -> 1 | L52: =ServInt[[#This Row],[DIAS]]*ServInt[[#This Row],[PESSOAS]]*ServInt[[#This Row],[HORAS DIA]] -> 0 | M52: =(IF(ServInt[[#This Row],[CÓDIGO]]="","",LOOKUP(E52,BASE!A$4:A$125,BASE!G$4:G$125)))*ServInt[[#This Row],[HE CALC]] -> 0 | N52: =ServInt[[#This Row],[TOTAL HORAS]]*ServInt[[#This Row],[R$ / HORA]] -> 0 | O52: =BASE!$W$60 -> 0.66983974 | P52: =M52/O52 -> 0 | Q52: =N52/O52 -> 0 | S52: =(IF(E52="","",LOOKUP(E52,BASE!A$4:A$19,BASE!E$4:E$19)))*ServInt[[#This Row],[TOTAL HORAS]] -> 0 | T52: =IFERROR(ServInt[[#This Row],[TOTAL3]]*(RESUMO!$F$22/RESUMO!$F$14),0) -> 0 | W52: 28 | X52: Sistemas | Y52: Serviço | Z52: 0 | AA52: =LOOKUP(Z52,BASE!A$4:A$125,BASE!B$4:B$125) -> 0 | AD52: 8.8 | AE52: NORMAL | AF52: =_xlfn.IFS(ServExt[[#This Row],[TIPO H]]="EXTRA 150%",((1)*2.5),ServExt[[#This Row],[TIPO H]]="EXTRA 100%",((1)*2),ServExt[[#This Row],[TIPO H]]="EXTRA 75%",((1)*1.75),ServExt[[#This Row],[TIPO H]]="EXTRA 50%",((1)*1.5),ServExt[[#This Row],[TIPO H]]="NORMAL",((1))) -> 1 | AG52: =ServExt[[#This Row],[DIAS]]*ServExt[[#This Row],[PESSOAS]]*ServExt[[#This Row],[HORAS DIA]] -> 0 | AH52: =(IF(Z52="","",LOOKUP(Z52,BASE!A$4:A$125,BASE!H$4:H$125)))*ServExt[[#This Row],[HE CALC]] -> 0 | AI52: =ServExt[[#This Row],[TOTAL HORAS]]*ServExt[[#This Row],[R$ / HORA]] -> 0 | AJ52: =BASE!$W$60 -> 0.66983974 | AK52: =AH52/AJ52 -> 0 | AL52: =AI52/AJ52 -> 0 | AM52: =IF(OR(ServExt[[#This Row],[TIPO H]]="NORMAL",ServExt[[#This Row],[HORAS DIA]]>=8),ServExt[[#This Row],[PESSOAS]]*ServExt[[#This Row],[DIAS]]*2,0) -> 0 | AN52: =(IF(Z52="","",LOOKUP(Z52,BASE!A$4:A$19,BASE!E$4:E$19)))*ServExt[[#This Row],[TOTAL HORAS]] -> 0 | AO52: =IF(ServExt[[#This Row],[TIPO H]]="NORMAL",ServExt[[#This Row],[PESSOAS]],0) -> 0 | AP52: =IFERROR(ServExt[[#This Row],[TOTAL3]]*(RESUMO!$F$22/RESUMO!$F$14),0) -> 0 | AR52: 30 | AS52: Projetista Elétrico V
B53: 29 | C53: Projetos | D53: Serviço | E53: 0 | F53: =LOOKUP('SERVICOS AUTPRO'!$E$25:$E$64,BASE!A$4:A$125,BASE!B$4:B$125) -> 0 | I53: 8.8 | J53: NORMAL | K53: =_xlfn.IFS('SERVICOS AUTPRO'!$J$25:$J$62="EXTRA 150%",((1)*2.5),'SERVICOS AUTPRO'!$J$25:$J$62="EXTRA 100%",((1)*2),'SERVICOS AUTPRO'!$J$25:$J$62="EXTRA 75%",((1)*1.75),'SERVICOS AUTPRO'!$J$25:$J$62="EXTRA 50%",((1)*1.5),'SERVICOS AUTPRO'!$J$25:$J$62="NORMAL",((1))) -> 1 | L53: =ServInt[[#This Row],[DIAS]]*ServInt[[#This Row],[PESSOAS]]*ServInt[[#This Row],[HORAS DIA]] -> 0 | M53: =(IF(ServInt[[#This Row],[CÓDIGO]]="","",LOOKUP(E53,BASE!A$4:A$125,BASE!G$4:G$125)))*ServInt[[#This Row],[HE CALC]] -> 0 | N53: =ServInt[[#This Row],[TOTAL HORAS]]*ServInt[[#This Row],[R$ / HORA]] -> 0 | O53: =BASE!$W$60 -> 0.66983974 | P53: =M53/O53 -> 0 | Q53: =N53/O53 -> 0 | S53: =(IF(E53="","",LOOKUP(E53,BASE!A$4:A$19,BASE!E$4:E$19)))*ServInt[[#This Row],[TOTAL HORAS]] -> 0 | T53: =IFERROR(ServInt[[#This Row],[TOTAL3]]*(RESUMO!$F$22/RESUMO!$F$14),0) -> 0 | W53: 29 | X53: Sistemas | Y53: Serviço | Z53: 0 | AA53: =LOOKUP(Z53,BASE!A$4:A$125,BASE!B$4:B$125) -> 0 | AD53: 8.8 | AE53: NORMAL | AF53: =_xlfn.IFS(ServExt[[#This Row],[TIPO H]]="EXTRA 150%",((1)*2.5),ServExt[[#This Row],[TIPO H]]="EXTRA 100%",((1)*2),ServExt[[#This Row],[TIPO H]]="EXTRA 75%",((1)*1.75),ServExt[[#This Row],[TIPO H]]="EXTRA 50%",((1)*1.5),ServExt[[#This Row],[TIPO H]]="NORMAL",((1))) -> 1 | AG53: =ServExt[[#This Row],[DIAS]]*ServExt[[#This Row],[PESSOAS]]*ServExt[[#This Row],[HORAS DIA]] -> 0 | AH53: =(IF(Z53="","",LOOKUP(Z53,BASE!A$4:A$125,BASE!H$4:H$125)))*ServExt[[#This Row],[HE CALC]] -> 0 | AI53: =ServExt[[#This Row],[TOTAL HORAS]]*ServExt[[#This Row],[R$ / HORA]] -> 0 | AJ53: =BASE!$W$60 -> 0.66983974 | AK53: =AH53/AJ53 -> 0 | AL53: =AI53/AJ53 -> 0 | AM53: =IF(OR(ServExt[[#This Row],[TIPO H]]="NORMAL",ServExt[[#This Row],[HORAS DIA]]>=8),ServExt[[#This Row],[PESSOAS]]*ServExt[[#This Row],[DIAS]]*2,0) -> 0 | AN53: =(IF(Z53="","",LOOKUP(Z53,BASE!A$4:A$19,BASE!E$4:E$19)))*ServExt[[#This Row],[TOTAL HORAS]] -> 0 | AO53: =IF(ServExt[[#This Row],[TIPO H]]="NORMAL",ServExt[[#This Row],[PESSOAS]],0) -> 0 | AP53: =IFERROR(ServExt[[#This Row],[TOTAL3]]*(RESUMO!$F$22/RESUMO!$F$14),0) -> 0 | AR53: 31 | AS53: Técnico Automação I
B54: 30 | C54: Projetos | D54: Serviço | E54: 0 | F54: =LOOKUP('SERVICOS AUTPRO'!$E$25:$E$64,BASE!A$4:A$125,BASE!B$4:B$125) -> 0 | I54: 8.8 | J54: NORMAL | K54: =_xlfn.IFS('SERVICOS AUTPRO'!$J$25:$J$62="EXTRA 150%",((1)*2.5),'SERVICOS AUTPRO'!$J$25:$J$62="EXTRA 100%",((1)*2),'SERVICOS AUTPRO'!$J$25:$J$62="EXTRA 75%",((1)*1.75),'SERVICOS AUTPRO'!$J$25:$J$62="EXTRA 50%",((1)*1.5),'SERVICOS AUTPRO'!$J$25:$J$62="NORMAL",((1))) -> 1 | L54: =ServInt[[#This Row],[DIAS]]*ServInt[[#This Row],[PESSOAS]]*ServInt[[#This Row],[HORAS DIA]] -> 0 | M54: =(IF(ServInt[[#This Row],[CÓDIGO]]="","",LOOKUP(E54,BASE!A$4:A$125,BASE!G$4:G$125)))*ServInt[[#This Row],[HE CALC]] -> 0 | N54: =ServInt[[#This Row],[TOTAL HORAS]]*ServInt[[#This Row],[R$ / HORA]] -> 0 | O54: =BASE!$W$60 -> 0.66983974 | P54: =M54/O54 -> 0 | Q54: =N54/O54 -> 0 | S54: =(IF(E54="","",LOOKUP(E54,BASE!A$4:A$19,BASE!E$4:E$19)))*ServInt[[#This Row],[TOTAL HORAS]] -> 0 | T54: =IFERROR(ServInt[[#This Row],[TOTAL3]]*(RESUMO!$F$22/RESUMO!$F$14),0) -> 0 | W54: 30 | X54: Sistemas | Y54: Serviço | Z54: 0 | AA54: =LOOKUP(Z54,BASE!A$4:A$125,BASE!B$4:B$125) -> 0 | AD54: 8.8 | AE54: NORMAL | AF54: =_xlfn.IFS(ServExt[[#This Row],[TIPO H]]="EXTRA 150%",((1)*2.5),ServExt[[#This Row],[TIPO H]]="EXTRA 100%",((1)*2),ServExt[[#This Row],[TIPO H]]="EXTRA 75%",((1)*1.75),ServExt[[#This Row],[TIPO H]]="EXTRA 50%",((1)*1.5),ServExt[[#This Row],[TIPO H]]="NORMAL",((1))) -> 1 | AG54: =ServExt[[#This Row],[DIAS]]*ServExt[[#This Row],[PESSOAS]]*ServExt[[#This Row],[HORAS DIA]] -> 0 | AH54: =(IF(Z54="","",LOOKUP(Z54,BASE!A$4:A$125,BASE!H$4:H$125)))*ServExt[[#This Row],[HE CALC]] -> 0 | AI54: =ServExt[[#This Row],[TOTAL HORAS]]*ServExt[[#This Row],[R$ / HORA]] -> 0 | AJ54: =BASE!$W$60 -> 0.66983974 | AK54: =AH54/AJ54 -> 0 | AL54: =AI54/AJ54 -> 0 | AM54: =IF(OR(ServExt[[#This Row],[TIPO H]]="NORMAL",ServExt[[#This Row],[HORAS DIA]]>=8),ServExt[[#This Row],[PESSOAS]]*ServExt[[#This Row],[DIAS]]*2,0) -> 0 | AN54: =(IF(Z54="","",LOOKUP(Z54,BASE!A$4:A$19,BASE!E$4:E$19)))*ServExt[[#This Row],[TOTAL HORAS]] -> 0 | AO54: =IF(ServExt[[#This Row],[TIPO H]]="NORMAL",ServExt[[#This Row],[PESSOAS]],0) -> 0 | AP54: =IFERROR(ServExt[[#This Row],[TOTAL3]]*(RESUMO!$F$22/RESUMO!$F$14),0) -> 0 | AR54: 32 | AS54: Técnico Automação II
B55: 31 | C55: Projetos | D55: Serviço | E55: 0 | F55: =LOOKUP('SERVICOS AUTPRO'!$E$25:$E$64,BASE!A$4:A$125,BASE!B$4:B$125) -> 0 | I55: 8.8 | J55: NORMAL | K55: =_xlfn.IFS('SERVICOS AUTPRO'!$J$25:$J$62="EXTRA 150%",((1)*2.5),'SERVICOS AUTPRO'!$J$25:$J$62="EXTRA 100%",((1)*2),'SERVICOS AUTPRO'!$J$25:$J$62="EXTRA 75%",((1)*1.75),'SERVICOS AUTPRO'!$J$25:$J$62="EXTRA 50%",((1)*1.5),'SERVICOS AUTPRO'!$J$25:$J$62="NORMAL",((1))) -> 1 | L55: =ServInt[[#This Row],[DIAS]]*ServInt[[#This Row],[PESSOAS]]*ServInt[[#This Row],[HORAS DIA]] -> 0 | M55: =(IF(ServInt[[#This Row],[CÓDIGO]]="","",LOOKUP(E55,BASE!A$4:A$125,BASE!G$4:G$125)))*ServInt[[#This Row],[HE CALC]] -> 0 | N55: =ServInt[[#This Row],[TOTAL HORAS]]*ServInt[[#This Row],[R$ / HORA]] -> 0 | O55: =BASE!$W$60 -> 0.66983974 | P55: =M55/O55 -> 0 | Q55: =N55/O55 -> 0 | S55: =(IF(E55="","",LOOKUP(E55,BASE!A$4:A$19,BASE!E$4:E$19)))*ServInt[[#This Row],[TOTAL HORAS]] -> 0 | T55: =IFERROR(ServInt[[#This Row],[TOTAL3]]*(RESUMO!$F$22/RESUMO!$F$14),0) -> 0 | W55: 31 | X55: Sistemas | Y55: Serviço | Z55: 0 | AA55: =LOOKUP(Z55,BASE!A$4:A$125,BASE!B$4:B$125) -> 0 | AD55: 8.8 | AE55: NORMAL | AF55: =_xlfn.IFS(ServExt[[#This Row],[TIPO H]]="EXTRA 150%",((1)*2.5),ServExt[[#This Row],[TIPO H]]="EXTRA 100%",((1)*2),ServExt[[#This Row],[TIPO H]]="EXTRA 75%",((1)*1.75),ServExt[[#This Row],[TIPO H]]="EXTRA 50%",((1)*1.5),ServExt[[#This Row],[TIPO H]]="NORMAL",((1))) -> 1 | AG55: =ServExt[[#This Row],[DIAS]]*ServExt[[#This Row],[PESSOAS]]*ServExt[[#This Row],[HORAS DIA]] -> 0 | AH55: =(IF(Z55="","",LOOKUP(Z55,BASE!A$4:A$125,BASE!H$4:H$125)))*ServExt[[#This Row],[HE CALC]] -> 0 | AI55: =ServExt[[#This Row],[TOTAL HORAS]]*ServExt[[#This Row],[R$ / HORA]] -> 0 | AJ55: =BASE!$W$60 -> 0.66983974 | AK55: =AH55/AJ55 -> 0 | AL55: =AI55/AJ55 -> 0 | AM55: =IF(OR(ServExt[[#This Row],[TIPO H]]="NORMAL",ServExt[[#This Row],[HORAS DIA]]>=8),ServExt[[#This Row],[PESSOAS]]*ServExt[[#This Row],[DIAS]]*2,0) -> 0 | AN55: =(IF(Z55="","",LOOKUP(Z55,BASE!A$4:A$19,BASE!E$4:E$19)))*ServExt[[#This Row],[TOTAL HORAS]] -> 0 | AO55: =IF(ServExt[[#This Row],[TIPO H]]="NORMAL",ServExt[[#This Row],[PESSOAS]],0) -> 0 | AP55: =IFERROR(ServExt[[#This Row],[TOTAL3]]*(RESUMO!$F$22/RESUMO!$F$14),0) -> 0 | AR55: 33 | AS55: Técnico Automação III
B56: 32 | C56: Projetos | D56: Serviço | E56: 0 | F56: =LOOKUP('SERVICOS AUTPRO'!$E$25:$E$64,BASE!A$4:A$125,BASE!B$4:B$125) -> 0 | I56: 8.8 | J56: NORMAL | K56: =_xlfn.IFS('SERVICOS AUTPRO'!$J$25:$J$62="EXTRA 150%",((1)*2.5),'SERVICOS AUTPRO'!$J$25:$J$62="EXTRA 100%",((1)*2),'SERVICOS AUTPRO'!$J$25:$J$62="EXTRA 75%",((1)*1.75),'SERVICOS AUTPRO'!$J$25:$J$62="EXTRA 50%",((1)*1.5),'SERVICOS AUTPRO'!$J$25:$J$62="NORMAL",((1))) -> 1 | L56: =ServInt[[#This Row],[DIAS]]*ServInt[[#This Row],[PESSOAS]]*ServInt[[#This Row],[HORAS DIA]] -> 0 | M56: =(IF(ServInt[[#This Row],[CÓDIGO]]="","",LOOKUP(E56,BASE!A$4:A$125,BASE!G$4:G$125)))*ServInt[[#This Row],[HE CALC]] -> 0 | N56: =ServInt[[#This Row],[TOTAL HORAS]]*ServInt[[#This Row],[R$ / HORA]] -> 0 | O56: =BASE!$W$60 -> 0.66983974 | P56: =M56/O56 -> 0 | Q56: =N56/O56 -> 0 | S56: =(IF(E56="","",LOOKUP(E56,BASE!A$4:A$19,BASE!E$4:E$19)))*ServInt[[#This Row],[TOTAL HORAS]] -> 0 | T56: =IFERROR(ServInt[[#This Row],[TOTAL3]]*(RESUMO!$F$22/RESUMO!$F$14),0) -> 0 | W56: 32 | X56: Sistemas | Y56: Serviço | Z56: 0 | AA56: =LOOKUP(Z56,BASE!A$4:A$125,BASE!B$4:B$125) -> 0 | AD56: 8.8 | AE56: NORMAL | AF56: =_xlfn.IFS(ServExt[[#This Row],[TIPO H]]="EXTRA 150%",((1)*2.5),ServExt[[#This Row],[TIPO H]]="EXTRA 100%",((1)*2),ServExt[[#This Row],[TIPO H]]="EXTRA 75%",((1)*1.75),ServExt[[#This Row],[TIPO H]]="EXTRA 50%",((1)*1.5),ServExt[[#This Row],[TIPO H]]="NORMAL",((1))) -> 1 | AG56: =ServExt[[#This Row],[DIAS]]*ServExt[[#This Row],[PESSOAS]]*ServExt[[#This Row],[HORAS DIA]] -> 0 | AH56: =(IF(Z56="","",LOOKUP(Z56,BASE!A$4:A$125,BASE!H$4:H$125)))*ServExt[[#This Row],[HE CALC]] -> 0 | AI56: =ServExt[[#This Row],[TOTAL HORAS]]*ServExt[[#This Row],[R$ / HORA]] -> 0 | AJ56: =BASE!$W$60 -> 0.66983974 | AK56: =AH56/AJ56 -> 0 | AL56: =AI56/AJ56 -> 0 | AM56: =IF(OR(ServExt[[#This Row],[TIPO H]]="NORMAL",ServExt[[#This Row],[HORAS DIA]]>=8),ServExt[[#This Row],[PESSOAS]]*ServExt[[#This Row],[DIAS]]*2,0) -> 0 | AN56: =(IF(Z56="","",LOOKUP(Z56,BASE!A$4:A$19,BASE!E$4:E$19)))*ServExt[[#This Row],[TOTAL HORAS]] -> 0 | AO56: =IF(ServExt[[#This Row],[TIPO H]]="NORMAL",ServExt[[#This Row],[PESSOAS]],0) -> 0 | AP56: =IFERROR(ServExt[[#This Row],[TOTAL3]]*(RESUMO!$F$22/RESUMO!$F$14),0) -> 0 | AR56: 34 | AS56: Técnico Automação IV
B57: 33 | C57: Projetos | D57: Serviço | E57: 0 | F57: =LOOKUP('SERVICOS AUTPRO'!$E$25:$E$64,BASE!A$4:A$125,BASE!B$4:B$125) -> 0 | I57: 8.8 | J57: NORMAL | K57: =_xlfn.IFS('SERVICOS AUTPRO'!$J$25:$J$62="EXTRA 150%",((1)*2.5),'SERVICOS AUTPRO'!$J$25:$J$62="EXTRA 100%",((1)*2),'SERVICOS AUTPRO'!$J$25:$J$62="EXTRA 75%",((1)*1.75),'SERVICOS AUTPRO'!$J$25:$J$62="EXTRA 50%",((1)*1.5),'SERVICOS AUTPRO'!$J$25:$J$62="NORMAL",((1))) -> 1 | L57: =ServInt[[#This Row],[DIAS]]*ServInt[[#This Row],[PESSOAS]]*ServInt[[#This Row],[HORAS DIA]] -> 0 | M57: =(IF(ServInt[[#This Row],[CÓDIGO]]="","",LOOKUP(E57,BASE!A$4:A$125,BASE!G$4:G$125)))*ServInt[[#This Row],[HE CALC]] -> 0 | N57: =ServInt[[#This Row],[TOTAL HORAS]]*ServInt[[#This Row],[R$ / HORA]] -> 0 | O57: =BASE!$W$60 -> 0.66983974 | P57: =M57/O57 -> 0 | Q57: =N57/O57 -> 0 | S57: =(IF(E57="","",LOOKUP(E57,BASE!A$4:A$19,BASE!E$4:E$19)))*ServInt[[#This Row],[TOTAL HORAS]] -> 0 | T57: =IFERROR(ServInt[[#This Row],[TOTAL3]]*(RESUMO!$F$22/RESUMO!$F$14),0) -> 0 | W57: 33 | X57: Sistemas | Y57: Serviço | Z57: 0 | AA57: =LOOKUP(Z57,BASE!A$4:A$125,BASE!B$4:B$125) -> 0 | AD57: 8.8 | AE57: NORMAL | AF57: =_xlfn.IFS(ServExt[[#This Row],[TIPO H]]="EXTRA 150%",((1)*2.5),ServExt[[#This Row],[TIPO H]]="EXTRA 100%",((1)*2),ServExt[[#This Row],[TIPO H]]="EXTRA 75%",((1)*1.75),ServExt[[#This Row],[TIPO H]]="EXTRA 50%",((1)*1.5),ServExt[[#This Row],[TIPO H]]="NORMAL",((1))) -> 1 | AG57: =ServExt[[#This Row],[DIAS]]*ServExt[[#This Row],[PESSOAS]]*ServExt[[#This Row],[HORAS DIA]] -> 0 | AH57: =(IF(Z57="","",LOOKUP(Z57,BASE!A$4:A$125,BASE!H$4:H$125)))*ServExt[[#This Row],[HE CALC]] -> 0 | AI57: =ServExt[[#This Row],[TOTAL HORAS]]*ServExt[[#This Row],[R$ / HORA]] -> 0 | AJ57: =BASE!$W$60 -> 0.66983974 | AK57: =AH57/AJ57 -> 0 | AL57: =AI57/AJ57 -> 0 | AM57: =IF(OR(ServExt[[#This Row],[TIPO H]]="NORMAL",ServExt[[#This Row],[HORAS DIA]]>=8),ServExt[[#This Row],[PESSOAS]]*ServExt[[#This Row],[DIAS]]*2,0) -> 0 | AN57: =(IF(Z57="","",LOOKUP(Z57,BASE!A$4:A$19,BASE!E$4:E$19)))*ServExt[[#This Row],[TOTAL HORAS]] -> 0 | AO57: =IF(ServExt[[#This Row],[TIPO H]]="NORMAL",ServExt[[#This Row],[PESSOAS]],0) -> 0 | AP57: =IFERROR(ServExt[[#This Row],[TOTAL3]]*(RESUMO!$F$22/RESUMO!$F$14),0) -> 0 | AR57: 35 | AS57: Técnico Automação V
B58: 34 | C58: Projetos | D58: Serviço | E58: 0 | F58: =LOOKUP('SERVICOS AUTPRO'!$E$25:$E$64,BASE!A$4:A$125,BASE!B$4:B$125) -> 0 | I58: 8.8 | J58: NORMAL | K58: =_xlfn.IFS('SERVICOS AUTPRO'!$J$25:$J$62="EXTRA 150%",((1)*2.5),'SERVICOS AUTPRO'!$J$25:$J$62="EXTRA 100%",((1)*2),'SERVICOS AUTPRO'!$J$25:$J$62="EXTRA 75%",((1)*1.75),'SERVICOS AUTPRO'!$J$25:$J$62="EXTRA 50%",((1)*1.5),'SERVICOS AUTPRO'!$J$25:$J$62="NORMAL",((1))) -> 1 | L58: =ServInt[[#This Row],[DIAS]]*ServInt[[#This Row],[PESSOAS]]*ServInt[[#This Row],[HORAS DIA]] -> 0 | M58: =(IF(ServInt[[#This Row],[CÓDIGO]]="","",LOOKUP(E58,BASE!A$4:A$125,BASE!G$4:G$125)))*ServInt[[#This Row],[HE CALC]] -> 0 | N58: =ServInt[[#This Row],[TOTAL HORAS]]*ServInt[[#This Row],[R$ / HORA]] -> 0 | O58: =BASE!$W$60 -> 0.66983974 | P58: =M58/O58 -> 0 | Q58: =N58/O58 -> 0 | S58: =(IF(E58="","",LOOKUP(E58,BASE!A$4:A$19,BASE!E$4:E$19)))*ServInt[[#This Row],[TOTAL HORAS]] -> 0 | T58: =IFERROR(ServInt[[#This Row],[TOTAL3]]*(RESUMO!$F$22/RESUMO!$F$14),0) -> 0 | W58: 34 | X58: Sistemas | Y58: Serviço | Z58: 0 | AA58: =LOOKUP(Z58,BASE!A$4:A$125,BASE!B$4:B$125) -> 0 | AD58: 8.8 | AE58: NORMAL | AF58: =_xlfn.IFS(ServExt[[#This Row],[TIPO H]]="EXTRA 150%",((1)*2.5),ServExt[[#This Row],[TIPO H]]="EXTRA 100%",((1)*2),ServExt[[#This Row],[TIPO H]]="EXTRA 75%",((1)*1.75),ServExt[[#This Row],[TIPO H]]="EXTRA 50%",((1)*1.5),ServExt[[#This Row],[TIPO H]]="NORMAL",((1))) -> 1 | AG58: =ServExt[[#This Row],[DIAS]]*ServExt[[#This Row],[PESSOAS]]*ServExt[[#This Row],[HORAS DIA]] -> 0 | AH58: =(IF(Z58="","",LOOKUP(Z58,BASE!A$4:A$125,BASE!H$4:H$125)))*ServExt[[#This Row],[HE CALC]] -> 0 | AI58: =ServExt[[#This Row],[TOTAL HORAS]]*ServExt[[#This Row],[R$ / HORA]] -> 0 | AJ58: =BASE!$W$60 -> 0.66983974 | AK58: =AH58/AJ58 -> 0 | AL58: =AI58/AJ58 -> 0 | AM58: =IF(OR(ServExt[[#This Row],[TIPO H]]="NORMAL",ServExt[[#This Row],[HORAS DIA]]>=8),ServExt[[#This Row],[PESSOAS]]*ServExt[[#This Row],[DIAS]]*2,0) -> 0 | AN58: =(IF(Z58="","",LOOKUP(Z58,BASE!A$4:A$19,BASE!E$4:E$19)))*ServExt[[#This Row],[TOTAL HORAS]] -> 0 | AO58: =IF(ServExt[[#This Row],[TIPO H]]="NORMAL",ServExt[[#This Row],[PESSOAS]],0) -> 0 | AP58: =IFERROR(ServExt[[#This Row],[TOTAL3]]*(RESUMO!$F$22/RESUMO!$F$14),0) -> 0 | AR58: 36 | AS58: Técnico Mecatrônica I
... B62: 38 | C62: Projetos | D62: Serviço | E62: 0 | F62: =LOOKUP('SERVICOS AUTPRO'!$E$25:$E$64,BASE!A$4:A$125,BASE!B$4:B$125) -> 0 | I62: 8.8 | J62: NORMAL | K62: =_xlfn.IFS('SERVICOS AUTPRO'!$J$25:$J$62="EXTRA 150%",((1)*2.5),'SERVICOS AUTPRO'!$J$25:$J$62="EXTRA 100%",((1)*2),'SERVICOS AUTPRO'!$J$25:$J$62="EXTRA 75%",((1)*1.75),'SERVICOS AUTPRO'!$J$25:$J$62="EXTRA 50%",((1)*1.5),'SERVICOS AUTPRO'!$J$25:$J$62="NORMAL",((1))) -> 1 | L62: =ServInt[[#This Row],[DIAS]]*ServInt[[#This Row],[PESSOAS]]*ServInt[[#This Row],[HORAS DIA]] -> 0 | M62: =(IF(ServInt[[#This Row],[CÓDIGO]]="","",LOOKUP(E62,BASE!A$4:A$125,BASE!G$4:G$125)))*ServInt[[#This Row],[HE CALC]] -> 0 | N62: =ServInt[[#This Row],[TOTAL HORAS]]*ServInt[[#This Row],[R$ / HORA]] -> 0 | O62: =BASE!$W$60 -> 0.66983974 | P62: =M62/O62 -> 0 | Q62: =N62/O62 -> 0 | S62: =(IF(E62="","",LOOKUP(E62,BASE!A$4:A$19,BASE!E$4:E$19)))*ServInt[[#This Row],[TOTAL HORAS]] -> 0 | T62: =IFERROR(ServInt[[#This Row],[TOTAL3]]*(RESUMO!$F$22/RESUMO!$F$14),0) -> 0 | W62: 38 | X62: Sistemas | Y62: Serviço | Z62: 0 | AA62: =LOOKUP(Z62,BASE!A$4:A$125,BASE!B$4:B$125) -> 0 | AD62: 8.8 | AE62: NORMAL | AF62: =_xlfn.IFS(ServExt[[#This Row],[TIPO H]]="EXTRA 150%",((1)*2.5),ServExt[[#This Row],[TIPO H]]="EXTRA 100%",((1)*2),ServExt[[#This Row],[TIPO H]]="EXTRA 75%",((1)*1.75),ServExt[[#This Row],[TIPO H]]="EXTRA 50%",((1)*1.5),ServExt[[#This Row],[TIPO H]]="NORMAL",((1))) -> 1 | AG62: =ServExt[[#This Row],[DIAS]]*ServExt[[#This Row],[PESSOAS]]*ServExt[[#This Row],[HORAS DIA]] -> 0 | AH62: =(IF(Z62="","",LOOKUP(Z62,BASE!A$4:A$125,BASE!H$4:H$125)))*ServExt[[#This Row],[HE CALC]] -> 0 | AI62: =ServExt[[#This Row],[TOTAL HORAS]]*ServExt[[#This Row],[R$ / HORA]] -> 0 | AJ62: =BASE!$W$60 -> 0.66983974 | AK62: =AH62/AJ62 -> 0 | AL62: =AI62/AJ62 -> 0 | AM62: =IF(OR(ServExt[[#This Row],[TIPO H]]="NORMAL",ServExt[[#This Row],[HORAS DIA]]>=8),ServExt[[#This Row],[PESSOAS]]*ServExt[[#This Row],[DIAS]]*2,0) -> 0 | AN62: =(IF(Z62="","",LOOKUP(Z62,BASE!A$4:A$19,BASE!E$4:E$19)))*ServExt[[#This Row],[TOTAL HORAS]] -> 0 | AO62: =IF(ServExt[[#This Row],[TIPO H]]="NORMAL",ServExt[[#This Row],[PESSOAS]],0) -> 0 | AP62: =IFERROR(ServExt[[#This Row],[TOTAL3]]*(RESUMO!$F$22/RESUMO!$F$14),0) -> 0 | AR62: 40 | AS62: Técnico Mecatrônica V
B63: 38 | C63: Projetos | D63: Serviço | E63: 0 | F63: =LOOKUP('SERVICOS AUTPRO'!$E$25:$E$64,BASE!A$4:A$125,BASE!B$4:B$125) -> 0 | I63: 8.8 | J63: NORMAL | K63: =_xlfn.IFS('SERVICOS AUTPRO'!$J$25:$J$64="EXTRA 150%",((1)*2.5),'SERVICOS AUTPRO'!$J$25:$J$64="EXTRA 100%",((1)*2),'SERVICOS AUTPRO'!$J$25:$J$64="EXTRA 75%",((1)*1.75),'SERVICOS AUTPRO'!$J$25:$J$64="EXTRA 50%",((1)*1.5),'SERVICOS AUTPRO'!$J$25:$J$64="NORMAL",((1))) -> 1 | L63: =ServInt[[#This Row],[DIAS]]*ServInt[[#This Row],[PESSOAS]]*ServInt[[#This Row],[HORAS DIA]] -> 0 | M63: =(IF(ServInt[[#This Row],[CÓDIGO]]="","",LOOKUP(E63,BASE!A$4:A$125,BASE!G$4:G$125)))*ServInt[[#This Row],[HE CALC]] -> 0 | N63: =ServInt[[#This Row],[TOTAL HORAS]]*ServInt[[#This Row],[R$ / HORA]] -> 0 | O63: =BASE!$W$60 -> 0.66983974 | P63: =M63/O63 -> 0 | Q63: =N63/O63 -> 0 | S63: =(IF(E63="","",LOOKUP(E63,BASE!A$4:A$19,BASE!E$4:E$19)))*ServInt[[#This Row],[TOTAL HORAS]] -> 0 | T63: =IFERROR(ServInt[[#This Row],[TOTAL3]]*(RESUMO!$F$22/RESUMO!$F$14),0) -> 0 | W63: 38 | X63: Sistemas | Y63: Serviço | Z63: 0 | AA63: =LOOKUP(Z63,BASE!A$4:A$125,BASE!B$4:B$125) -> 0 | AD63: 8.8 | AE63: NORMAL | AF63: =_xlfn.IFS(ServExt[[#This Row],[TIPO H]]="EXTRA 150%",((1)*2.5),ServExt[[#This Row],[TIPO H]]="EXTRA 100%",((1)*2),ServExt[[#This Row],[TIPO H]]="EXTRA 75%",((1)*1.75),ServExt[[#This Row],[TIPO H]]="EXTRA 50%",((1)*1.5),ServExt[[#This Row],[TIPO H]]="NORMAL",((1))) -> 1 | AG63: =ServExt[[#This Row],[DIAS]]*ServExt[[#This Row],[PESSOAS]]*ServExt[[#This Row],[HORAS DIA]] -> 0 | AH63: =(IF(Z63="","",LOOKUP(Z63,BASE!A$4:A$125,BASE!H$4:H$125)))*ServExt[[#This Row],[HE CALC]] -> 0 | AI63: =ServExt[[#This Row],[TOTAL HORAS]]*ServExt[[#This Row],[R$ / HORA]] -> 0 | AJ63: =BASE!$W$60 -> 0.66983974 | AK63: =AH63/AJ63 -> 0 | AL63: =AI63/AJ63 -> 0 | AM63: =IF(OR(ServExt[[#This Row],[TIPO H]]="NORMAL",ServExt[[#This Row],[HORAS DIA]]>=8),ServExt[[#This Row],[PESSOAS]]*ServExt[[#This Row],[DIAS]]*2,0) -> 0 | AN63: =(IF(Z63="","",LOOKUP(Z63,BASE!A$4:A$19,BASE!E$4:E$19)))*ServExt[[#This Row],[TOTAL HORAS]] -> 0 | AO63: =IF(ServExt[[#This Row],[TIPO H]]="NORMAL",ServExt[[#This Row],[PESSOAS]],0) -> 0 | AP63: =IFERROR(ServExt[[#This Row],[TOTAL3]]*(RESUMO!$F$22/RESUMO!$F$14),0) -> 0 | AR63: 41 | AS63: Eletricista Instalador I
B64: 38 | C64: Projetos | D64: Serviço | E64: 0 | F64: =LOOKUP('SERVICOS AUTPRO'!$E$25:$E$64,BASE!A$4:A$125,BASE!B$4:B$125) -> 0 | I64: 8.8 | J64: NORMAL | K64: =_xlfn.IFS('SERVICOS AUTPRO'!$J$25:$J$64="EXTRA 150%",((1)*2.5),'SERVICOS AUTPRO'!$J$25:$J$64="EXTRA 100%",((1)*2),'SERVICOS AUTPRO'!$J$25:$J$64="EXTRA 75%",((1)*1.75),'SERVICOS AUTPRO'!$J$25:$J$64="EXTRA 50%",((1)*1.5),'SERVICOS AUTPRO'!$J$25:$J$64="NORMAL",((1))) -> 1 | L64: =ServInt[[#This Row],[DIAS]]*ServInt[[#This Row],[PESSOAS]]*ServInt[[#This Row],[HORAS DIA]] -> 0 | M64: =(IF(ServInt[[#This Row],[CÓDIGO]]="","",LOOKUP(E64,BASE!A$4:A$125,BASE!G$4:G$125)))*ServInt[[#This Row],[HE CALC]] -> 0 | N64: =ServInt[[#This Row],[TOTAL HORAS]]*ServInt[[#This Row],[R$ / HORA]] -> 0 | O64: =BASE!$W$60 -> 0.66983974 | P64: =M64/O64 -> 0 | Q64: =N64/O64 -> 0 | S64: =(IF(E64="","",LOOKUP(E64,BASE!A$4:A$19,BASE!E$4:E$19)))*ServInt[[#This Row],[TOTAL HORAS]] -> 0 | T64: =IFERROR(ServInt[[#This Row],[TOTAL3]]*(RESUMO!$F$22/RESUMO!$F$14),0) -> 0 | W64: 38 | X64: Sistemas | Y64: Serviço | Z64: 0 | AA64: =LOOKUP(Z64,BASE!A$4:A$125,BASE!B$4:B$125) -> 0 | AD64: 8.8 | AE64: NORMAL | AF64: =_xlfn.IFS(ServExt[[#This Row],[TIPO H]]="EXTRA 150%",((1)*2.5),ServExt[[#This Row],[TIPO H]]="EXTRA 100%",((1)*2),ServExt[[#This Row],[TIPO H]]="EXTRA 75%",((1)*1.75),ServExt[[#This Row],[TIPO H]]="EXTRA 50%",((1)*1.5),ServExt[[#This Row],[TIPO H]]="NORMAL",((1))) -> 1 | AG64: =ServExt[[#This Row],[DIAS]]*ServExt[[#This Row],[PESSOAS]]*ServExt[[#This Row],[HORAS DIA]] -> 0 | AH64: =(IF(Z64="","",LOOKUP(Z64,BASE!A$4:A$125,BASE!H$4:H$125)))*ServExt[[#This Row],[HE CALC]] -> 0 | AI64: =ServExt[[#This Row],[TOTAL HORAS]]*ServExt[[#This Row],[R$ / HORA]] -> 0 | AJ64: =BASE!$W$60 -> 0.66983974 | AK64: =AH64/AJ64 -> 0 | AL64: =AI64/AJ64 -> 0 | AM64: =IF(OR(ServExt[[#This Row],[TIPO H]]="NORMAL",ServExt[[#This Row],[HORAS DIA]]>=8),ServExt[[#This Row],[PESSOAS]]*ServExt[[#This Row],[DIAS]]*2,0) -> 0 | AN64: =(IF(Z64="","",LOOKUP(Z64,BASE!A$4:A$19,BASE!E$4:E$19)))*ServExt[[#This Row],[TOTAL HORAS]] -> 0 | AO64: =IF(ServExt[[#This Row],[TIPO H]]="NORMAL",ServExt[[#This Row],[PESSOAS]],0) -> 0 | AP64: =IFERROR(ServExt[[#This Row],[TOTAL3]]*(RESUMO!$F$22/RESUMO!$F$14),0) -> 0 | AR64: 42 | AS64: Eletricista Instalador II
B65: 8 | G65: =SUBTOTAL(109,ServInt[DIAS]) -> 40 | I65: =SUBTOTAL(101,ServInt[HORAS DIA]) -> 10.585 | L65: =SUBTOTAL(109,ServInt[TOTAL HORAS]) -> 360 | N65: =SUBTOTAL(109,ServInt[TOTAL]) -> 14688 | Q65: =SUBTOTAL(109,ServInt[TOTAL3]) -> 21927.633 | R65: =SUBTOTAL(103,ServInt[TOTAL4]) -> 0 | S65: =SUBTOTAL(109,ServInt[MULTA]) -> 1100.8979 | T65: =SUBTOTAL(109,ServInt[VENDA COM IMPOSTOS]) -> 24707.192 | W65: Total | AB65: =SUBTOTAL(109,ServExt[DIAS]) -> 140 | AC65: =SUBTOTAL(109,ServExt[PESSOAS]) -> 5 | AD65: =SUBTOTAL(101,ServExt[HORAS DIA]) -> 8.93 | AG65: =SUBTOTAL(109,ServExt[TOTAL HORAS]) -> 1400 | AI65: =SUBTOTAL(109,ServExt[TOTAL]) -> 82800 | AL65: =SUBTOTAL(109,ServExt[TOTAL3]) -> 123611.66 | AM65: =SUBTOTAL(109,ServExt[TOTAL4]) -> 280 | AN65: =SUBTOTAL(109,ServExt[MULTA]) -> 4281.2697 | AO65: =SUBTOTAL(109,ServExt[Coluna1]) -> 5 | AP65: =SUBTOTAL(109,ServExt[VENDA COM IMPOSTOS]) -> 139280.74 | AR65: 43 | AS65: Eletricista Instalador III
B66: 0 | AR66: 44 | AS66: Eletricista Instalador IV
AR67: 45 | AS67: Eletricista Instalador V
AR68: 46 | AS68: Eletricista Força e Comando I
AR69: 47 | AS69: Eletricista Força e Comando II
AR70: 48 | AS70: Eletricista Força e Comando III
AR71: 49 | AS71: Eletricista Força e Comando IV
AR72: 50 | AS72: Eletricista Força e Comando V
AR73: 51 | AS73: Especialista de Manutenção I
AR74: 52 | AS74: Especialista de Manutenção II
AR75: 53 | AS75: Especialista de Manutenção III
AR76: 54 | AS76: Especialista de Manutenção IV
AR77: 55 | AS77: Especialista de Manutenção V
AR78: 56 | AS78: Eletricista de Instalações Industriais I
... AR143: 121 | AS143: Pintor V

Sheet SERVICOS MONTAGEM
F1: ORÇAMENTO DETALHADO
D5: HOSPEDAGEM | H5: CUSTO | L5: CUSTO
D6: DESCRIÇÃO | E6: QUANTIDADE | F6: TOTAL | H6: VALOR HOTEL | L6: CUSTO
D7: HOSPEDAGEM | E7: =ServExt8[[#Totals],[TOTAL4]]/2 -> 1245 | F7: =(E7*H7)/O71 -> 140572.31 | H7: 90 | L7: =(E7*H7) -> 112050
D9: ALIMENTAÇÃO | H9: CUSTO | L9: CUSTO
D10: DESCRIÇÃO | E10: QUANTIDADE | F10: TOTAL | H10: VALOR REFEIÇÃO | L10: CUSTO
D11: REFEIÇÕES | E11: =ServExt8[[#Totals],[TOTAL4]] -> 2490 | F11: =(E11*H11)/O75 -> 78095.73 | H11: 25 | L11: =(E11*H11) -> 62250
D13: TRANSPORTE | J13: MESES | L13: CUSTO
D14: DESCRIÇÃO | E14: VIAGENS | F14: PEDÁGIOS | G14: KM | H14: TOTAL | L14: TOTAL
D15: MOBILIZAÇÃO (POR TRANSLADO) | E15: 8 | F15: 75 | G15: 234 | H15: =(((G15*E15*BASE!M3)+(F15*E15))/O79) -> 3101.2473 | J15: 5 | L15: =((G15*E15*BASE!M3)+(F15*E15)) -> 2472
D16: ALOJAMENTO PARA OBRA | E16: 220 | G16: 10 | H16: =(((G16*E16*BASE!M4)+(F16*E16))/O80) -> 2346.0083 | L16: =((G16*E16*BASE!M4)+(F16*E16)) -> 1870 | O16: DATA | Q16: 43420
D17: ALUGUEL CARRO MENSAL | E17: Carros: | G17: =ROUNDUP(ServExt8[[#Totals],[Coluna1]]/4,0) -> 4 | H17: =(L17/O81) -> 63982.044 | L17: =IF(ServExt8[[#Totals],[DIAS]]>=30,BASE!W3*(J15),ServExt8[[#Totals],[DIAS]]*BASE!W4*1.3)*G17 -> 51000
D18: PASSAGEM AEREA | E18: 0 | F18: 0 | H18: =L18/O82 -> 0 | L18: =F18*E18 -> 0
D19: TOTAL: | H19: =SUM(H15:I18) -> 69429.299 | L19: =SUM(L15:L18) -> 55342
B21: SERVIÇOS INTERNOS | W21: SERVIÇOS EXTERNOS | AU21: LEGENDA
B22: DESCRIÇÃO | E22: PROFISSIONAL | F22: Profissional | G22: REGIME DE TRABALHO | K22: CUSTO | O22: VENDA | W22: DESCRIÇÃO | Z22: PROFISSIONAL | AA22: Profissional | AB22: REGIME DE TRABALHO | AF22: CUSTO | AJ22: VENDA | AP22: VENDA | AU22: 1 | AV22: Especialista Eletricista I
B23: ITEM | C23: CENTRO DE CUSTO | D23: SERVIÇO | E23: CÓDIGO | F23: DESCRIÇÃO FUNÇÃO | G23: DIAS | H23: PESSOAS | I23: HORAS DIA | J23: TIPO H | K23: HE CALC | L23: TOTAL HORAS | M23: R$ / HORA | N23: TOTAL | O23: MARK-UP | P23: HORA | Q23: TOTAL3 | R23: TOTAL4 | S23: MULTA | T23: VENDA COM IMPOSTOS | W23: ITEM | X23: CENTRO DE CUSTO | Y23: SERVIÇO | Z23: CÓDIGO | AA23: DESCRIÇÃO FUNÇÃO | AB23: DIAS | AC23: PESSOAS | AD23: HORAS DIA | AE23: TIPO H | AF23: HE CALC | AG23: TOTAL HORAS | AH23: R$ / HORA | AI23: TOTAL | AJ23: MARK-UP | AK23: HORA | AL23: TOTAL3 | AM23: TOTAL4 | AN23: MULTA | AO23: Coluna1 | AP23: VENDA COM IMPOSTOS | AU23: 2 | AV23: Especialista Eletricista II
B24: 1 | C24: Sistemas | D24: Serviço | E24: 0 | F24: =LOOKUP('SERVICOS MONTAGEM'!$E$24:$E$63,BASE!A$4:A$125,BASE!B$4:B$125) -> 0 | I24: 8.8 | J24: NORMAL | K24: =_xlfn.IFS('SERVICOS MONTAGEM'!$J$24:$J$63="EXTRA 150%",((1)*2.5),'SERVICOS MONTAGEM'!$J$24:$J$63="EXTRA 100%",((1)*2),'SERVICOS MONTAGEM'!$J$24:$J$63="EXTRA 75%",((1)*1.75),'SERVICOS MONTAGEM'!$J$24:$J$63="EXTRA 50%",((1)*1.5),'SERVICOS MONTAGEM'!$J$24:$J$63="NORMAL",((1))) -> 1 | L24: =ServInt10[[#This Row],[DIAS]]*ServInt10[[#This Row],[PESSOAS]]*ServInt10[[#This Row],[HORAS DIA]] -> 0 | M24: =(IF(ServInt10[[#This Row],[CÓDIGO]]="","",LOOKUP(ServInt10[[#This Row],[CÓDIGO]],BASE!A$4:A$125,BASE!G$4:G$125)))*ServInt10[[#This Row],[HE CALC]] -> 0 | N24: =ServInt10[[#This Row],[TOTAL HORAS]]*ServInt10[[#This Row],[R$ / HORA]] -> 0 | O24: =BASE!$W$54 -> 0.79709864 | P24: =ServInt10[[#This Row],[R$ / HORA]]/ServInt10[[#This Row],[MARK-UP]] -> 0 | Q24: =ServInt10[[#This Row],[TOTAL]]/ServInt10[[#This Row],[MARK-UP]] -> 0 | S24: =(IF(E24="","",LOOKUP(E24,BASE!A$4:A$125,BASE!E$4:E$125)))*ServInt10[[#This Row],[TOTAL HORAS]] -> 0 | T24: =IFERROR(ServInt10[[#This Row],[TOTAL3]]*(RESUMO!$F$32/RESUMO!$F$24),0) -> 0 | W24: 1 | X24: Sistemas | Y24: MONTAGEM | Z24: 86 | AA24: =LOOKUP(Z24,BASE!A$4:A$125,BASE!B$4:B$125) -> Montador de Instalações Elétricas III | AB24: 83 | AC24: 6 | AD24: 8.8 | AE24: NORMAL | AF24: =_xlfn.IFS(ServExt8[[#This Row],[TIPO H]]="EXTRA 150%",((1)*2.5),ServExt8[[#This Row],[TIPO H]]="EXTRA 100%",((1)*2),ServExt8[[#This Row],[TIPO H]]="EXTRA 75%",((1)*1.75),ServExt8[[#This Row],[TIPO H]]="EXTRA 50%",((1)*1.5),ServExt8[[#This Row],[TIPO H]]="NORMAL",((1))) -> 1 | AG24: =AC24*AB24*AD24 -> 4382.4 | AH24: =(IF(Z24="","",LOOKUP(Z24,BASE!A$4:A$125,BASE!H$4:H$125)))*ServExt8[[#This Row],[HE CALC]] -> 27 | AI24: =ServExt8[[#This Row],[TOTAL HORAS]]*ServExt8[[#This Row],[R$ / HORA]] -> 118324.8 | AJ24: =BASE!$W$54 -> 0.79709864 | AK24: =AH24/AJ24 -> 33.872847 | AL24: =AI24/AJ24 -> 148444.36 | AM24: =IF(OR(ServExt8[[#This Row],[TIPO H]]="NORMAL",ServExt8[[#This Row],[HORAS DIA]]>=8),ServExt8[[#This Row],[PESSOAS]]*ServExt8[[#This Row],[DIAS]]*2,0) -> 996 | AN24: =(IF(Z24="","",LOOKUP(Z24,BASE!A$4:A$125,BASE!E$4:E$125)))*ServExt8[[#This Row],[TOTAL HORAS]] -> 4233.5288 | AO24: =IF(ServExt8[[#This Row],[TIPO H]]="NORMAL",ServExt8[[#This Row],[PESSOAS]],0) -> 6 | AP24: =IFERROR(ServExt8[[#This Row],[TOTAL3]]*(RESUMO!$F$32/RESUMO!$F$24),0) -> 167261.25 | AU24: 3 | AV24: Especialista Eletricista III
B25: 2 | C25: Sistemas | D25: Serviço | E25: 0 | F25: =LOOKUP('SERVICOS MONTAGEM'!$E$24:$E$63,BASE!A$4:A$125,BASE!B$4:B$125) -> 0 | I25: 8.8 | J25: NORMAL | K25: =_xlfn.IFS('SERVICOS MONTAGEM'!$J$24:$J$63="EXTRA 150%",((1)*2.5),'SERVICOS MONTAGEM'!$J$24:$J$63="EXTRA 100%",((1)*2),'SERVICOS MONTAGEM'!$J$24:$J$63="EXTRA 75%",((1)*1.75),'SERVICOS MONTAGEM'!$J$24:$J$63="EXTRA 50%",((1)*1.5),'SERVICOS MONTAGEM'!$J$24:$J$63="NORMAL",((1))) -> 1 | L25: =ServInt10[[#This Row],[DIAS]]*ServInt10[[#This Row],[PESSOAS]]*ServInt10[[#This Row],[HORAS DIA]] -> 0 | M25: =(IF(ServInt10[[#This Row],[CÓDIGO]]="","",LOOKUP(ServInt10[[#This Row],[CÓDIGO]],BASE!A$4:A$125,BASE!G$4:G$125)))*ServInt10[[#This Row],[HE CALC]] -> 0 | N25: =ServInt10[[#This Row],[TOTAL HORAS]]*ServInt10[[#This Row],[R$ / HORA]] -> 0 | O25: =BASE!$W$54 -> 0.79709864 | P25: =ServInt10[[#This Row],[R$ / HORA]]/ServInt10[[#This Row],[MARK-UP]] -> 0 | Q25: =ServInt10[[#This Row],[TOTAL]]/ServInt10[[#This Row],[MARK-UP]] -> 0 | S25: =(IF(E25="","",LOOKUP(E25,BASE!A$4:A$125,BASE!E$4:E$125)))*ServInt10[[#This Row],[TOTAL HORAS]] -> 0 | T25: =IFERROR(ServInt10[[#This Row],[TOTAL3]]*(RESUMO!$F$32/RESUMO!$F$24),0) -> 0 | W25: 2 | X25: Sistemas | Y25: MONTAGEM | Z25: 99 | AA25: =LOOKUP(Z25,BASE!A$4:A$125,BASE!B$4:B$125) -> Ajudante de Montador | AB25: 83 | AC25: 5 | AD25: 8.8 | AE25: NORMAL | AF25: =_xlfn.IFS(ServExt8[[#This Row],[TIPO H]]="EXTRA 150%",((1)*2.5),ServExt8[[#This Row],[TIPO H]]="EXTRA 100%",((1)*2),ServExt8[[#This Row],[TIPO H]]="EXTRA 75%",((1)*1.75),ServExt8[[#This Row],[TIPO H]]="EXTRA 50%",((1)*1.5),ServExt8[[#This Row],[TIPO H]]="NORMAL",((1))) -> 1 | AG25: =AC25*AB25*AD25 -> 3652 | AH25: =(IF(Z25="","",LOOKUP(Z25,BASE!A$4:A$125,BASE!H$4:H$125)))*ServExt8[[#This Row],[HE CALC]] -> 17 | AI25: =ServExt8[[#This Row],[TOTAL HORAS]]*ServExt8[[#This Row],[R$ / HORA]] -> 62084 | AJ25: =BASE!$W$54 -> 0.79709864 | AK25: =AH25/AJ25 -> 21.327348 | AL25: =AI25/AJ25 -> 77887.475 | AM25: =IF(OR(ServExt8[[#This Row],[TIPO H]]="NORMAL",ServExt8[[#This Row],[HORAS DIA]]>=8),ServExt8[[#This Row],[PESSOAS]]*ServExt8[[#This Row],[DIAS]]*2,0) -> 830 | AN25: =(IF(Z25="","",LOOKUP(Z25,BASE!A$4:A$125,BASE!E$4:E$125)))*ServExt8[[#This Row],[TOTAL HORAS]] -> 2275.1296 | AO25: =IF(ServExt8[[#This Row],[TIPO H]]="NORMAL",ServExt8[[#This Row],[PESSOAS]],0) -> 5 | AP25: =IFERROR(ServExt8[[#This Row],[TOTAL3]]*(RESUMO!$F$32/RESUMO!$F$24),0) -> 87760.535 | AU25: 4 | AV25: Especialista Eletricista IV
B26: 3 | C26: Sistemas | D26: Serviço | E26: 0 | F26: =LOOKUP('SERVICOS MONTAGEM'!$E$24:$E$63,BASE!A$4:A$125,BASE!B$4:B$125) -> 0 | I26: 8.8 | J26: NORMAL | K26: =_xlfn.IFS('SERVICOS MONTAGEM'!$J$24:$J$63="EXTRA 150%",((1)*2.5),'SERVICOS MONTAGEM'!$J$24:$J$63="EXTRA 100%",((1)*2),'SERVICOS MONTAGEM'!$J$24:$J$63="EXTRA 75%",((1)*1.75),'SERVICOS MONTAGEM'!$J$24:$J$63="EXTRA 50%",((1)*1.5),'SERVICOS MONTAGEM'!$J$24:$J$63="NORMAL",((1))) -> 1 | L26: =ServInt10[[#This Row],[DIAS]]*ServInt10[[#This Row],[PESSOAS]]*ServInt10[[#This Row],[HORAS DIA]] -> 0 | M26: =(IF(ServInt10[[#This Row],[CÓDIGO]]="","",LOOKUP(ServInt10[[#This Row],[CÓDIGO]],BASE!A$4:A$125,BASE!G$4:G$125)))*ServInt10[[#This Row],[HE CALC]] -> 0 | N26: =ServInt10[[#This Row],[TOTAL HORAS]]*ServInt10[[#This Row],[R$ / HORA]] -> 0 | O26: =BASE!$W$54 -> 0.79709864 | P26: =ServInt10[[#This Row],[R$ / HORA]]/ServInt10[[#This Row],[MARK-UP]] -> 0 | Q26: =ServInt10[[#This Row],[TOTAL]]/ServInt10[[#This Row],[MARK-UP]] -> 0 | S26: =(IF(E26="","",LOOKUP(E26,BASE!A$4:A$125,BASE!E$4:E$125)))*ServInt10[[#This Row],[TOTAL HORAS]] -> 0 | T26: =IFERROR(ServInt10[[#This Row],[TOTAL3]]*(RESUMO!$F$32/RESUMO!$F$24),0) -> 0 | W26: 3 | X26: Sistemas | Y26: SUPERVISÃO DE MONTAGEM | Z26: 76 | AA26: =LOOKUP(Z26,BASE!A$4:A$125,BASE!B$4:B$125) -> Encarregado de Instalações Elétricas III | AB26: 83 | AC26: 1 | AD26: 8.8 | AE26: NORMAL | AF26: =_xlfn.IFS(ServExt8[[#This Row],[TIPO H]]="EXTRA 150%",((1)*2.5),ServExt8[[#This Row],[TIPO H]]="EXTRA 100%",((1)*2),ServExt8[[#This Row],[TIPO H]]="EXTRA 75%",((1)*1.75),ServExt8[[#This Row],[TIPO H]]="EXTRA 50%",((1)*1.5),ServExt8[[#This Row],[TIPO H]]="NORMAL",((1))) -> 1 | AG26: =AC26*AB26*AD26 -> 730.4 | AH26: =(IF(Z26="","",LOOKUP(Z26,BASE!A$4:A$125,BASE!H$4:H$125)))*ServExt8[[#This Row],[HE CALC]] -> 35 | AI26: =ServExt8[[#This Row],[TOTAL HORAS]]*ServExt8[[#This Row],[R$ / HORA]] -> 25564 | AJ26: =BASE!$W$54 -> 0.79709864 | AK26: =AH26/AJ26 -> 43.909246 | AL26: =AI26/AJ26 -> 32071.313 | AM26: =IF(OR(ServExt8[[#This Row],[TIPO H]]="NORMAL",ServExt8[[#This Row],[HORAS DIA]]>=8),ServExt8[[#This Row],[PESSOAS]]*ServExt8[[#This Row],[DIAS]]*2,0) -> 166 | AN26: =(IF(Z26="","",LOOKUP(Z26,BASE!A$4:A$125,BASE!E$4:E$125)))*ServExt8[[#This Row],[TOTAL HORAS]] -> 923.22115 | AO26: =IF(ServExt8[[#This Row],[TIPO H]]="NORMAL",ServExt8[[#This Row],[PESSOAS]],0) -> 1 | AP26: =IFERROR(ServExt8[[#This Row],[TOTAL3]]*(RESUMO!$F$32/RESUMO!$F$24),0) -> 36136.691 | AU26: 5 | AV26: Especialista Eletricista V
B27: 4 | C27: Sistemas | D27: Serviço | E27: 0 | F27: =LOOKUP('SERVICOS MONTAGEM'!$E$24:$E$63,BASE!A$4:A$125,BASE!B$4:B$125) -> 0 | I27: 8.8 | J27: NORMAL | K27: =_xlfn.IFS('SERVICOS MONTAGEM'!$J$24:$J$63="EXTRA 150%",((1)*2.5),'SERVICOS MONTAGEM'!$J$24:$J$63="EXTRA 100%",((1)*2),'SERVICOS MONTAGEM'!$J$24:$J$63="EXTRA 75%",((1)*1.75),'SERVICOS MONTAGEM'!$J$24:$J$63="EXTRA 50%",((1)*1.5),'SERVICOS MONTAGEM'!$J$24:$J$63="NORMAL",((1))) -> 1 | L27: =ServInt10[[#This Row],[DIAS]]*ServInt10[[#This Row],[PESSOAS]]*ServInt10[[#This Row],[HORAS DIA]] -> 0 | M27: =(IF(ServInt10[[#This Row],[CÓDIGO]]="","",LOOKUP(ServInt10[[#This Row],[CÓDIGO]],BASE!A$4:A$125,BASE!G$4:G$125)))*ServInt10[[#This Row],[HE CALC]] -> 0 | N27: =ServInt10[[#This Row],[TOTAL HORAS]]*ServInt10[[#This Row],[R$ / HORA]] -> 0 | O27: =BASE!$W$54 -> 0.79709864 | P27: =ServInt10[[#This Row],[R$ / HORA]]/ServInt10[[#This Row],[MARK-UP]] -> 0 | Q27: =ServInt10[[#This Row],[TOTAL]]/ServInt10[[#This Row],[MARK-UP]] -> 0 | S27: =(IF(E27="","",LOOKUP(E27,BASE!A$4:A$125,BASE!E$4:E$125)))*ServInt10[[#This Row],[TOTAL HORAS]] -> 0 | T27: =IFERROR(ServInt10[[#This Row],[TOTAL3]]*(RESUMO!$F$32/RESUMO!$F$24),0) -> 0 | W27: 4 | X27: Sistemas | Y27: ADMINISTRATIVO E ALMOXARIFADO | Z27: 84 | AA27: =LOOKUP(Z27,BASE!A$4:A$125,BASE!B$4:B$125) -> Montador de Instalações Elétricas I | AB27: 83 | AC27: 1 | AD27: 8.8 | AE27: NORMAL | AF27: =_xlfn.IFS(ServExt8[[#This Row],[TIPO H]]="EXTRA 150%",((1)*2.5),ServExt8[[#This Row],[TIPO H]]="EXTRA 100%",((1)*2),ServExt8[[#This Row],[TIPO H]]="EXTRA 75%",((1)*1.75),ServExt8[[#This Row],[TIPO H]]="EXTRA 50%",((1)*1.5),ServExt8[[#This Row],[TIPO H]]="NORMAL",((1))) -> 1 | AG27: =AC27*AB27*AD27 -> 730.4 | AH27: =(IF(Z27="","",LOOKUP(Z27,BASE!A$4:A$125,BASE!H$4:H$125)))*ServExt8[[#This Row],[HE CALC]] -> 19 | AI27: =ServExt8[[#This Row],[TOTAL HORAS]]*ServExt8[[#This Row],[R$ / HORA]] -> 13877.6 | AJ27: =BASE!$W$54 -> 0.79709864 | AK27: =AH27/AJ27 -> 23.836448 | AL27: =AI27/AJ27 -> 17410.141 | AM27: =IF(OR(ServExt8[[#This Row],[TIPO H]]="NORMAL",ServExt8[[#This Row],[HORAS DIA]]>=8),ServExt8[[#This Row],[PESSOAS]]*ServExt8[[#This Row],[DIAS]]*2,0) -> 166 | AN27: =(IF(Z27="","",LOOKUP(Z27,BASE!A$4:A$125,BASE!E$4:E$125)))*ServExt8[[#This Row],[TOTAL HORAS]] -> 503.99238 | AO27: =IF(ServExt8[[#This Row],[TIPO H]]="NORMAL",ServExt8[[#This Row],[PESSOAS]],0) -> 1 | AP27: =IFERROR(ServExt8[[#This Row],[TOTAL3]]*(RESUMO!$F$32/RESUMO!$F$24),0) -> 19617.061 | AU27: 6 | AV27: Especialista Controle e Automação I
B28: 5 | C28: Sistemas | D28: Serviço | E28: 0 | F28: =LOOKUP('SERVICOS MONTAGEM'!$E$24:$E$63,BASE!A$4:A$125,BASE!B$4:B$125) -> 0 | I28: 8.8 | J28: NORMAL | K28: =_xlfn.IFS('SERVICOS MONTAGEM'!$J$24:$J$63="EXTRA 150%",((1)*2.5),'SERVICOS MONTAGEM'!$J$24:$J$63="EXTRA 100%",((1)*2),'SERVICOS MONTAGEM'!$J$24:$J$63="EXTRA 75%",((1)*1.75),'SERVICOS MONTAGEM'!$J$24:$J$63="EXTRA 50%",((1)*1.5),'SERVICOS MONTAGEM'!$J$24:$J$63="NORMAL",((1))) -> 1 | L28: =ServInt10[[#This Row],[DIAS]]*ServInt10[[#This Row],[PESSOAS]]*ServInt10[[#This Row],[HORAS DIA]] -> 0 | M28: =(IF(ServInt10[[#This Row],[CÓDIGO]]="","",LOOKUP(ServInt10[[#This Row],[CÓDIGO]],BASE!A$4:A$125,BASE!G$4:G$125)))*ServInt10[[#This Row],[HE CALC]] -> 0 | N28: =ServInt10[[#This Row],[TOTAL HORAS]]*ServInt10[[#This Row],[R$ / HORA]] -> 0 | O28: =BASE!$W$54 -> 0.79709864 | P28: =ServInt10[[#This Row],[R$ / HORA]]/ServInt10[[#This Row],[MARK-UP]] -> 0 | Q28: =ServInt10[[#This Row],[TOTAL]]/ServInt10[[#This Row],[MARK-UP]] -> 0 | S28: =(IF(E28="","",LOOKUP(E28,BASE!A$4:A$125,BASE!E$4:E$125)))*ServInt10[[#This Row],[TOTAL HORAS]] -> 0 | T28: =IFERROR(ServInt10[[#This Row],[TOTAL3]]*(RESUMO!$F$32/RESUMO!$F$24),0) -> 0 | W28: 5 | X28: Sistemas | Y28: SEGURANÇA DO TRABALHO | Z28: 102 | AA28: =LOOKUP(Z28,BASE!A$4:A$125,BASE!B$4:B$125) -> Técnico em Segurança do Trabalho III | AB28: 83 | AC28: 1 | AD28: 8.8 | AE28: NORMAL | AF28: =_xlfn.IFS(ServExt8[[#This Row],[TIPO H]]="EXTRA 150%",((1)*2.5),ServExt8[[#This Row],[TIPO H]]="EXTRA 100%",((1)*2),ServExt8[[#This Row],[TIPO H]]="EXTRA 75%",((1)*1.75),ServExt8[[#This Row],[TIPO H]]="EXTRA 50%",((1)*1.5),ServExt8[[#This Row],[TIPO H]]="NORMAL",((1))) -> 1 | AG28: =AC28*AB28*AD28 -> 730.4 | AH28: =(IF(Z28="","",LOOKUP(Z28,BASE!A$4:A$125,BASE!H$4:H$125)))*ServExt8[[#This Row],[HE CALC]] -> 45 | AI28: =ServExt8[[#This Row],[TOTAL HORAS]]*ServExt8[[#This Row],[R$ / HORA]] -> 32868 | AJ28: =BASE!$W$54 -> 0.79709864 | AK28: =AH28/AJ28 -> 56.454744 | AL28: =AI28/AJ28 -> 41234.545 | AM28: =IF(OR(ServExt8[[#This Row],[TIPO H]]="NORMAL",ServExt8[[#This Row],[HORAS DIA]]>=8),ServExt8[[#This Row],[PESSOAS]]*ServExt8[[#This Row],[DIAS]]*2,0) -> 166 | AN28: =(IF(Z28="","",LOOKUP(Z28,BASE!A$4:A$125,BASE!E$4:E$125)))*ServExt8[[#This Row],[TOTAL HORAS]] -> 1191.2531 | AO28: =IF(ServExt8[[#This Row],[TIPO H]]="NORMAL",ServExt8[[#This Row],[PESSOAS]],0) -> 1 | AP28: =IFERROR(ServExt8[[#This Row],[TOTAL3]]*(RESUMO!$F$32/RESUMO!$F$24),0) -> 46461.46 | AU28: 7 | AV28: Especialista Controle e Automação Il
B29: 6 | C29: Sistemas | D29: Serviço | E29: 0 | F29: =LOOKUP('SERVICOS MONTAGEM'!$E$24:$E$63,BASE!A$4:A$125,BASE!B$4:B$125) -> 0 | I29: 8.8 | J29: NORMAL | K29: =_xlfn.IFS('SERVICOS MONTAGEM'!$J$24:$J$63="EXTRA 150%",((1)*2.5),'SERVICOS MONTAGEM'!$J$24:$J$63="EXTRA 100%",((1)*2),'SERVICOS MONTAGEM'!$J$24:$J$63="EXTRA 75%",((1)*1.75),'SERVICOS MONTAGEM'!$J$24:$J$63="EXTRA 50%",((1)*1.5),'SERVICOS MONTAGEM'!$J$24:$J$63="NORMAL",((1))) -> 1 | L29: =ServInt10[[#This Row],[DIAS]]*ServInt10[[#This Row],[PESSOAS]]*ServInt10[[#This Row],[HORAS DIA]] -> 0 | M29: =(IF(ServInt10[[#This Row],[CÓDIGO]]="","",LOOKUP(ServInt10[[#This Row],[CÓDIGO]],BASE!A$4:A$125,BASE!G$4:G$125)))*ServInt10[[#This Row],[HE CALC]] -> 0 | N29: =ServInt10[[#This Row],[TOTAL HORAS]]*ServInt10[[#This Row],[R$ / HORA]] -> 0 | O29: =BASE!$W$54 -> 0.79709864 | P29: =ServInt10[[#This Row],[R$ / HORA]]/ServInt10[[#This Row],[MARK-UP]] -> 0 | Q29: =ServInt10[[#This Row],[TOTAL]]/ServInt10[[#This Row],[MARK-UP]] -> 0 | S29: =(IF(E29="","",LOOKUP(E29,BASE!A$4:A$125,BASE!E$4:E$125)))*ServInt10[[#This Row],[TOTAL HORAS]] -> 0 | T29: =IFERROR(ServInt10[[#This Row],[TOTAL3]]*(RESUMO!$F$32/RESUMO!$F$24),0) -> 0 | W29: 6 | X29: Sistemas | Y29: PLANEJADOR | Z29: 85 | AA29: =LOOKUP(Z29,BASE!A$4:A$125,BASE!B$4:B$125) -> Montador de Instalações Elétricas II | AB29: 83 | AC29: 1 | AD29: 8.8 | AE29: NORMAL | AF29: =_xlfn.IFS(ServExt8[[#This Row],[TIPO H]]="EXTRA 150%",((1)*2.5),ServExt8[[#This Row],[TIPO H]]="EXTRA 100%",((1)*2),ServExt8[[#This Row],[TIPO H]]="EXTRA 75%",((1)*1.75),ServExt8[[#This Row],[TIPO H]]="EXTRA 50%",((1)*1.5),ServExt8[[#This Row],[TIPO H]]="NORMAL",((1))) -> 1 | AG29: =AC29*AB29*AD29 -> 730.4 | AH29: =(IF(Z29="","",LOOKUP(Z29,BASE!A$4:A$125,BASE!H$4:H$125)))*ServExt8[[#This Row],[HE CALC]] -> 23 | AI29: =ServExt8[[#This Row],[TOTAL HORAS]]*ServExt8[[#This Row],[R$ / HORA]] -> 16799.2 | AJ29: =BASE!$W$54 -> 0.79709864 | AK29: =AH29/AJ29 -> 28.854647 | AL29: =AI29/AJ29 -> 21075.434 | AM29: =IF(OR(ServExt8[[#This Row],[TIPO H]]="NORMAL",ServExt8[[#This Row],[HORAS DIA]]>=8),ServExt8[[#This Row],[PESSOAS]]*ServExt8[[#This Row],[DIAS]]*2,0) -> 166 | AN29: =(IF(Z29="","",LOOKUP(Z29,BASE!A$4:A$125,BASE!E$4:E$125)))*ServExt8[[#This Row],[TOTAL HORAS]] -> 604.79026 | AO29: =IF(ServExt8[[#This Row],[TIPO H]]="NORMAL",ServExt8[[#This Row],[PESSOAS]],0) -> 1 | AP29: =IFERROR(ServExt8[[#This Row],[TOTAL3]]*(RESUMO!$F$32/RESUMO!$F$24),0) -> 23746.968 | AU29: 8 | AV29: Especialista Controle e Automação III
B30: 7 | C30: Sistemas | D30: Serviço | E30: 0 | F30: =LOOKUP('SERVICOS MONTAGEM'!$E$24:$E$63,BASE!A$4:A$125,BASE!B$4:B$125) -> 0 | I30: 8.8 | J30: NORMAL | K30: =_xlfn.IFS('SERVICOS MONTAGEM'!$J$24:$J$63="EXTRA 150%",((1)*2.5),'SERVICOS MONTAGEM'!$J$24:$J$63="EXTRA 100%",((1)*2),'SERVICOS MONTAGEM'!$J$24:$J$63="EXTRA 75%",((1)*1.75),'SERVICOS MONTAGEM'!$J$24:$J$63="EXTRA 50%",((1)*1.5),'SERVICOS MONTAGEM'!$J$24:$J$63="NORMAL",((1))) -> 1 | L30: =ServInt10[[#This Row],[DIAS]]*ServInt10[[#This Row],[PESSOAS]]*ServInt10[[#This Row],[HORAS DIA]] -> 0 | M30: =(IF(ServInt10[[#This Row],[CÓDIGO]]="","",LOOKUP(ServInt10[[#This Row],[CÓDIGO]],BASE!A$4:A$125,BASE!G$4:G$125)))*ServInt10[[#This Row],[HE CALC]] -> 0 | N30: =ServInt10[[#This Row],[TOTAL HORAS]]*ServInt10[[#This Row],[R$ / HORA]] -> 0 | O30: =BASE!$W$54 -> 0.79709864 | P30: =ServInt10[[#This Row],[R$ / HORA]]/ServInt10[[#This Row],[MARK-UP]] -> 0 | Q30: =ServInt10[[#This Row],[TOTAL]]/ServInt10[[#This Row],[MARK-UP]] -> 0 | S30: =(IF(E30="","",LOOKUP(E30,BASE!A$4:A$125,BASE!E$4:E$125)))*ServInt10[[#This Row],[TOTAL HORAS]] -> 0 | T30: =IFERROR(ServInt10[[#This Row],[TOTAL3]]*(RESUMO!$F$32/RESUMO!$F$24),0) -> 0 | W30: 7 | X30: Sistemas | Z30: 0 | AA30: =LOOKUP(Z30,BASE!A$4:A$125,BASE!B$4:B$125) -> 0 | AD30: 8.8 | AE30: NORMAL | AF30: =_xlfn.IFS(ServExt8[[#This Row],[TIPO H]]="EXTRA 150%",((1)*2.5),ServExt8[[#This Row],[TIPO H]]="EXTRA 100%",((1)*2),ServExt8[[#This Row],[TIPO H]]="EXTRA 75%",((1)*1.75),ServExt8[[#This Row],[TIPO H]]="EXTRA 50%",((1)*1.5),ServExt8[[#This Row],[TIPO H]]="NORMAL",((1))) -> 1 | AG30: =AC30*AB30*AD30 -> 0 | AH30: =(IF(Z30="","",LOOKUP(Z30,BASE!A$4:A$125,BASE!H$4:H$125)))*ServExt8[[#This Row],[HE CALC]] -> 0 | AI30: =ServExt8[[#This Row],[TOTAL HORAS]]*ServExt8[[#This Row],[R$ / HORA]] -> 0 | AJ30: =BASE!$W$54 -> 0.79709864 | AK30: =AH30/AJ30 -> 0 | AL30: =AI30/AJ30 -> 0 | AM30: =IF(OR(ServExt8[[#This Row],[TIPO H]]="NORMAL",ServExt8[[#This Row],[HORAS DIA]]>=8),ServExt8[[#This Row],[PESSOAS]]*ServExt8[[#This Row],[DIAS]]*2,0) -> 0 | AN30: =(IF(Z30="","",LOOKUP(Z30,BASE!A$4:A$125,BASE!E$4:E$125)))*ServExt8[[#This Row],[TOTAL HORAS]] -> 0 | AO30: =IF(ServExt8[[#This Row],[TIPO H]]="NORMAL",ServExt8[[#This Row],[PESSOAS]],0) -> 0 | AP30: =IFERROR(ServExt8[[#This Row],[TOTAL3]]*(RESUMO!$F$32/RESUMO!$F$24),0) -> 0 | AU30: 9 | AV30: Especialista Controle e Automação IV
B31: 8 | C31: Sistemas | D31: Serviço | E31: 0 | F31: =LOOKUP('SERVICOS MONTAGEM'!$E$24:$E$63,BASE!A$4:A$125,BASE!B$4:B$125) -> 0 | I31: 8.8 | J31: NORMAL | K31: =_xlfn.IFS('SERVICOS MONTAGEM'!$J$24:$J$63="EXTRA 150%",((1)*2.5),'SERVICOS MONTAGEM'!$J$24:$J$63="EXTRA 100%",((1)*2),'SERVICOS MONTAGEM'!$J$24:$J$63="EXTRA 75%",((1)*1.75),'SERVICOS MONTAGEM'!$J$24:$J$63="EXTRA 50%",((1)*1.5),'SERVICOS MONTAGEM'!$J$24:$J$63="NORMAL",((1))) -> 1 | L31: =ServInt10[[#This Row],[DIAS]]*ServInt10[[#This Row],[PESSOAS]]*ServInt10[[#This Row],[HORAS DIA]] -> 0 | M31: =(IF(ServInt10[[#This Row],[CÓDIGO]]="","",LOOKUP(ServInt10[[#This Row],[CÓDIGO]],BASE!A$4:A$125,BASE!G$4:G$125)))*ServInt10[[#This Row],[HE CALC]] -> 0 | N31: =ServInt10[[#This Row],[TOTAL HORAS]]*ServInt10[[#This Row],[R$ / HORA]] -> 0 | O31: =BASE!$W$54 -> 0.79709864 | P31: =ServInt10[[#This Row],[R$ / HORA]]/ServInt10[[#This Row],[MARK-UP]] -> 0 | Q31: =ServInt10[[#This Row],[TOTAL]]/ServInt10[[#This Row],[MARK-UP]] -> 0 | S31: =(IF(E31="","",LOOKUP(E31,BASE!A$4:A$125,BASE!E$4:E$125)))*ServInt10[[#This Row],[TOTAL HORAS]] -> 0 | T31: =IFERROR(ServInt10[[#This Row],[TOTAL3]]*(RESUMO!$F$32/RESUMO!$F$24),0) -> 0 | W31: 8 | X31: Sistemas | Z31: 0 | AA31: =LOOKUP(Z31,BASE!A$4:A$125,BASE!B$4:B$125) -> 0 | AD31: 8.8 | AE31: NORMAL | AF31: =_xlfn.IFS(ServExt8[[#This Row],[TIPO H]]="EXTRA 150%",((1)*2.5),ServExt8[[#This Row],[TIPO H]]="EXTRA 100%",((1)*2),ServExt8[[#This Row],[TIPO H]]="EXTRA 75%",((1)*1.75),ServExt8[[#This Row],[TIPO H]]="EXTRA 50%",((1)*1.5),ServExt8[[#This Row],[TIPO H]]="NORMAL",((1))) -> 1 | AG31: =AC31*AB31*AD31 -> 0 | AH31: =(IF(Z31="","",LOOKUP(Z31,BASE!A$4:A$125,BASE!H$4:H$125)))*ServExt8[[#This Row],[HE CALC]] -> 0 | AI31: =ServExt8[[#This Row],[TOTAL HORAS]]*ServExt8[[#This Row],[R$ / HORA]] -> 0 | AJ31: =BASE!$W$54 -> 0.79709864 | AK31: =AH31/AJ31 -> 0 | AL31: =AI31/AJ31 -> 0 | AM31: =IF(OR(ServExt8[[#This Row],[TIPO H]]="NORMAL",ServExt8[[#This Row],[HORAS DIA]]>=8),ServExt8[[#This Row],[PESSOAS]]*ServExt8[[#This Row],[DIAS]]*2,0) -> 0 | AN31: =(IF(Z31="","",LOOKUP(Z31,BASE!A$4:A$125,BASE!E$4:E$125)))*ServExt8[[#This Row],[TOTAL HORAS]] -> 0 | AO31: =IF(ServExt8[[#This Row],[TIPO H]]="NORMAL",ServExt8[[#This Row],[PESSOAS]],0) -> 0 | AP31: =IFERROR(ServExt8[[#This Row],[TOTAL3]]*(RESUMO!$F$32/RESUMO!$F$24),0) -> 0 | AU31: 10 | AV31: Especialista Controle e Automação V
B32: 9 | C32: Sistemas | D32: Serviço | E32: 0 | F32: =LOOKUP('SERVICOS MONTAGEM'!$E$24:$E$63,BASE!A$4:A$125,BASE!B$4:B$125) -> 0 | I32: 8.8 | J32: NORMAL | K32: =_xlfn.IFS('SERVICOS MONTAGEM'!$J$24:$J$63="EXTRA 150%",((1)*2.5),'SERVICOS MONTAGEM'!$J$24:$J$63="EXTRA 100%",((1)*2),'SERVICOS MONTAGEM'!$J$24:$J$63="EXTRA 75%",((1)*1.75),'SERVICOS MONTAGEM'!$J$24:$J$63="EXTRA 50%",((1)*1.5),'SERVICOS MONTAGEM'!$J$24:$J$63="NORMAL",((1))) -> 1 | L32: =ServInt10[[#This Row],[DIAS]]*ServInt10[[#This Row],[PESSOAS]]*ServInt10[[#This Row],[HORAS DIA]] -> 0 | M32: =(IF(ServInt10[[#This Row],[CÓDIGO]]="","",LOOKUP(ServInt10[[#This Row],[CÓDIGO]],BASE!A$4:A$125,BASE!G$4:G$125)))*ServInt10[[#This Row],[HE CALC]] -> 0 | N32: =ServInt10[[#This Row],[TOTAL HORAS]]*ServInt10[[#This Row],[R$ / HORA]] -> 0 | O32: =BASE!$W$54 -> 0.79709864 | P32: =ServInt10[[#This Row],[R$ / HORA]]/ServInt10[[#This Row],[MARK-UP]] -> 0 | Q32: =ServInt10[[#This Row],[TOTAL]]/ServInt10[[#This Row],[MARK-UP]] -> 0 | S32: =(IF(E32="","",LOOKUP(E32,BASE!A$4:A$125,BASE!E$4:E$125)))*ServInt10[[#This Row],[TOTAL HORAS]] -> 0 | T32: =IFERROR(ServInt10[[#This Row],[TOTAL3]]*(RESUMO!$F$32/RESUMO!$F$24),0) -> 0 | W32: 9 | X32: Sistemas | Z32: 0 | AA32: =LOOKUP(Z32,BASE!A$4:A$125,BASE!B$4:B$125) -> 0 | AD32: 8.8 | AE32: NORMAL | AF32: =_xlfn.IFS(ServExt8[[#This Row],[TIPO H]]="EXTRA 150%",((1)*2.5),ServExt8[[#This Row],[TIPO H]]="EXTRA 100%",((1)*2),ServExt8[[#This Row],[TIPO H]]="EXTRA 75%",((1)*1.75),ServExt8[[#This Row],[TIPO H]]="EXTRA 50%",((1)*1.5),ServExt8[[#This Row],[TIPO H]]="NORMAL",((1))) -> 1 | AG32: =AC32*AB32*AD32 -> 0 | AH32: =(IF(Z32="","",LOOKUP(Z32,BASE!A$4:A$125,BASE!H$4:H$125)))*ServExt8[[#This Row],[HE CALC]] -> 0 | AI32: =ServExt8[[#This Row],[TOTAL HORAS]]*ServExt8[[#This Row],[R$ / HORA]] -> 0 | AJ32: =BASE!$W$54 -> 0.79709864 | AK32: =AH32/AJ32 -> 0 | AL32: =AI32/AJ32 -> 0 | AM32: =IF(OR(ServExt8[[#This Row],[TIPO H]]="NORMAL",ServExt8[[#This Row],[HORAS DIA]]>=8),ServExt8[[#This Row],[PESSOAS]]*ServExt8[[#This Row],[DIAS]]*2,0) -> 0 | AN32: =(IF(Z32="","",LOOKUP(Z32,BASE!A$4:A$125,BASE!E$4:E$125)))*ServExt8[[#This Row],[TOTAL HORAS]] -> 0 | AO32: =IF(ServExt8[[#This Row],[TIPO H]]="NORMAL",ServExt8[[#This Row],[PESSOAS]],0) -> 0 | AP32: =IFERROR(ServExt8[[#This Row],[TOTAL3]]*(RESUMO!$F$32/RESUMO!$F$24),0) -> 0 | AU32: 11 | AV32: Especialista em Computação I
B33: 10 | C33: Sistemas | D33: Serviço | E33: 0 | F33: =LOOKUP('SERVICOS MONTAGEM'!$E$24:$E$63,BASE!A$4:A$125,BASE!B$4:B$125) -> 0 | I33: 8.8 | J33: NORMAL | K33: =_xlfn.IFS('SERVICOS MONTAGEM'!$J$24:$J$63="EXTRA 150%",((1)*2.5),'SERVICOS MONTAGEM'!$J$24:$J$63="EXTRA 100%",((1)*2),'SERVICOS MONTAGEM'!$J$24:$J$63="EXTRA 75%",((1)*1.75),'SERVICOS MONTAGEM'!$J$24:$J$63="EXTRA 50%",((1)*1.5),'SERVICOS MONTAGEM'!$J$24:$J$63="NORMAL",((1))) -> 1 | L33: =ServInt10[[#This Row],[DIAS]]*ServInt10[[#This Row],[PESSOAS]]*ServInt10[[#This Row],[HORAS DIA]] -> 0 | M33: =(IF(ServInt10[[#This Row],[CÓDIGO]]="","",LOOKUP(ServInt10[[#This Row],[CÓDIGO]],BASE!A$4:A$125,BASE!G$4:G$125)))*ServInt10[[#This Row],[HE CALC]] -> 0 | N33: =ServInt10[[#This Row],[TOTAL HORAS]]*ServInt10[[#This Row],[R$ / HORA]] -> 0 | O33: =BASE!$W$54 -> 0.79709864 | P33: =ServInt10[[#This Row],[R$ / HORA]]/ServInt10[[#This Row],[MARK-UP]] -> 0 | Q33: =ServInt10[[#This Row],[TOTAL]]/ServInt10[[#This Row],[MARK-UP]] -> 0 | S33: =(IF(E33="","",LOOKUP(E33,BASE!A$4:A$125,BASE!E$4:E$125)))*ServInt10[[#This Row],[TOTAL HORAS]] -> 0 | T33: =IFERROR(ServInt10[[#This Row],[TOTAL3]]*(RESUMO!$F$32/RESUMO!$F$24),0) -> 0 | W33: 10 | X33: Sistemas | Z33: 0 | AA33: =LOOKUP(Z33,BASE!A$4:A$125,BASE!B$4:B$125) -> 0 | AD33: 8.8 | AE33: NORMAL | AF33: =_xlfn.IFS(ServExt8[[#This Row],[TIPO H]]="EXTRA 150%",((1)*2.5),ServExt8[[#This Row],[TIPO H]]="EXTRA 100%",((1)*2),ServExt8[[#This Row],[TIPO H]]="EXTRA 75%",((1)*1.75),ServExt8[[#This Row],[TIPO H]]="EXTRA 50%",((1)*1.5),ServExt8[[#This Row],[TIPO H]]="NORMAL",((1))) -> 1 | AG33: =AC33*AB33*AD33 -> 0 | AH33: =(IF(Z33="","",LOOKUP(Z33,BASE!A$4:A$125,BASE!H$4:H$125)))*ServExt8[[#This Row],[HE CALC]] -> 0 | AI33: =ServExt8[[#This Row],[TOTAL HORAS]]*ServExt8[[#This Row],[R$ / HORA]] -> 0 | AJ33: =BASE!$W$54 -> 0.79709864 | AK33: =AH33/AJ33 -> 0 | AL33: =AI33/AJ33 -> 0 | AM33: =IF(OR(ServExt8[[#This Row],[TIPO H]]="NORMAL",ServExt8[[#This Row],[HORAS DIA]]>=8),ServExt8[[#This Row],[PESSOAS]]*ServExt8[[#This Row],[DIAS]]*2,0) -> 0 | AN33: =(IF(Z33="","",LOOKUP(Z33,BASE!A$4:A$125,BASE!E$4:E$125)))*ServExt8[[#This Row],[TOTAL HORAS]] -> 0 | AO33: =IF(ServExt8[[#This Row],[TIPO H]]="NORMAL",ServExt8[[#This Row],[PESSOAS]],0) -> 0 | AP33: =IFERROR(ServExt8[[#This Row],[TOTAL3]]*(RESUMO!$F$32/RESUMO!$F$24),0) -> 0 | AU33: 12 | AV33: Especialista em Computação II
B34: 11 | C34: Sistemas | D34: Serviço | E34: 0 | F34: =LOOKUP('SERVICOS MONTAGEM'!$E$24:$E$63,BASE!A$4:A$125,BASE!B$4:B$125) -> 0 | I34: 8.8 | J34: NORMAL | K34: =_xlfn.IFS('SERVICOS MONTAGEM'!$J$24:$J$63="EXTRA 150%",((1)*2.5),'SERVICOS MONTAGEM'!$J$24:$J$63="EXTRA 100%",((1)*2),'SERVICOS MONTAGEM'!$J$24:$J$63="EXTRA 75%",((1)*1.75),'SERVICOS MONTAGEM'!$J$24:$J$63="EXTRA 50%",((1)*1.5),'SERVICOS MONTAGEM'!$J$24:$J$63="NORMAL",((1))) -> 1 | L34: =ServInt10[[#This Row],[DIAS]]*ServInt10[[#This Row],[PESSOAS]]*ServInt10[[#This Row],[HORAS DIA]] -> 0 | M34: =(IF(ServInt10[[#This Row],[CÓDIGO]]="","",LOOKUP(ServInt10[[#This Row],[CÓDIGO]],BASE!A$4:A$125,BASE!G$4:G$125)))*ServInt10[[#This Row],[HE CALC]] -> 0 | N34: =ServInt10[[#This Row],[TOTAL HORAS]]*ServInt10[[#This Row],[R$ / HORA]] -> 0 | O34: =BASE!$W$54 -> 0.79709864 | P34: =ServInt10[[#This Row],[R$ / HORA]]/ServInt10[[#This Row],[MARK-UP]] -> 0 | Q34: =ServInt10[[#This Row],[TOTAL]]/ServInt10[[#This Row],[MARK-UP]] -> 0 | S34: =(IF(E34="","",LOOKUP(E34,BASE!A$4:A$125,BASE!E$4:E$125)))*ServInt10[[#This Row],[TOTAL HORAS]] -> 0 | T34: =IFERROR(ServInt10[[#This Row],[TOTAL3]]*(RESUMO!$F$32/RESUMO!$F$24),0) -> 0 | W34: 11 | X34: Sistemas | Z34: 0 | AA34: =LOOKUP(Z34,BASE!A$4:A$125,BASE!B$4:B$125) -> 0 | AD34: 8.8 | AE34: NORMAL | AF34: =_xlfn.IFS(ServExt8[[#This Row],[TIPO H]]="EXTRA 150%",((1)*2.5),ServExt8[[#This Row],[TIPO H]]="EXTRA 100%",((1)*2),ServExt8[[#This Row],[TIPO H]]="EXTRA 75%",((1)*1.75),ServExt8[[#This Row],[TIPO H]]="EXTRA 50%",((1)*1.5),ServExt8[[#This Row],[TIPO H]]="NORMAL",((1))) -> 1 | AG34: =AC34*AB34*AD34 -> 0 | AH34: =(IF(Z34="","",LOOKUP(Z34,BASE!A$4:A$125,BASE!H$4:H$125)))*ServExt8[[#This Row],[HE CALC]] -> 0 | AI34: =ServExt8[[#This Row],[TOTAL HORAS]]*ServExt8[[#This Row],[R$ / HORA]] -> 0 | AJ34: =BASE!$W$54 -> 0.79709864 | AK34: =AH34/AJ34 -> 0 | AL34: =AI34/AJ34 -> 0 | AM34: =IF(OR(ServExt8[[#This Row],[TIPO H]]="NORMAL",ServExt8[[#This Row],[HORAS DIA]]>=8),ServExt8[[#This Row],[PESSOAS]]*ServExt8[[#This Row],[DIAS]]*2,0) -> 0 | AN34: =(IF(Z34="","",LOOKUP(Z34,BASE!A$4:A$125,BASE!E$4:E$125)))*ServExt8[[#This Row],[TOTAL HORAS]] -> 0 | AO34: =IF(ServExt8[[#This Row],[TIPO H]]="NORMAL",ServExt8[[#This Row],[PESSOAS]],0) -> 0 | AP34: =IFERROR(ServExt8[[#This Row],[TOTAL3]]*(RESUMO!$F$32/RESUMO!$F$24),0) -> 0 | AU34: 13 | AV34: Especialista Computação III
B35: 12 | C35: Sistemas | D35: Serviço | E35: 0 | F35: =LOOKUP('SERVICOS MONTAGEM'!$E$24:$E$63,BASE!A$4:A$125,BASE!B$4:B$125) -> 0 | I35: 8.8 | J35: NORMAL | K35: =_xlfn.IFS('SERVICOS MONTAGEM'!$J$24:$J$63="EXTRA 150%",((1)*2.5),'SERVICOS MONTAGEM'!$J$24:$J$63="EXTRA 100%",((1)*2),'SERVICOS MONTAGEM'!$J$24:$J$63="EXTRA 75%",((1)*1.75),'SERVICOS MONTAGEM'!$J$24:$J$63="EXTRA 50%",((1)*1.5),'SERVICOS MONTAGEM'!$J$24:$J$63="NORMAL",((1))) -> 1 | L35: =ServInt10[[#This Row],[DIAS]]*ServInt10[[#This Row],[PESSOAS]]*ServInt10[[#This Row],[HORAS DIA]] -> 0 | M35: =(IF(ServInt10[[#This Row],[CÓDIGO]]="","",LOOKUP(ServInt10[[#This Row],[CÓDIGO]],BASE!A$4:A$125,BASE!G$4:G$125)))*ServInt10[[#This Row],[HE CALC]] -> 0 | N35: =ServInt10[[#This Row],[TOTAL HORAS]]*ServInt10[[#This Row],[R$ / HORA]] -> 0 | O35: =BASE!$W$54 -> 0.79709864 | P35: =ServInt10[[#This Row],[R$ / HORA]]/ServInt10[[#This Row],[MARK-UP]] -> 0 | Q35: =ServInt10[[#This Row],[TOTAL]]/ServInt10[[#This Row],[MARK-UP]] -> 0 | S35: =(IF(E35="","",LOOKUP(E35,BASE!A$4:A$125,BASE!E$4:E$125)))*ServInt10[[#This Row],[TOTAL HORAS]] -> 0 | T35: =IFERROR(ServInt10[[#This Row],[TOTAL3]]*(RESUMO!$F$32/RESUMO!$F$24),0) -> 0 | W35: 12 | X35: Sistemas | Z35: 0 | AA35: =LOOKUP(Z35,BASE!A$4:A$125,BASE!B$4:B$125) -> 0 | AD35: 8.8 | AE35: NORMAL | AF35: =_xlfn.IFS(ServExt8[[#This Row],[TIPO H]]="EXTRA 150%",((1)*2.5),ServExt8[[#This Row],[TIPO H]]="EXTRA 100%",((1)*2),ServExt8[[#This Row],[TIPO H]]="EXTRA 75%",((1)*1.75),ServExt8[[#This Row],[TIPO H]]="EXTRA 50%",((1)*1.5),ServExt8[[#This Row],[TIPO H]]="NORMAL",((1))) -> 1 | AG35: =AC35*AB35*AD35 -> 0 | AH35: =(IF(Z35="","",LOOKUP(Z35,BASE!A$4:A$125,BASE!H$4:H$125)))*ServExt8[[#This Row],[HE CALC]] -> 0 | AI35: =ServExt8[[#This Row],[TOTAL HORAS]]*ServExt8[[#This Row],[R$ / HORA]] -> 0 | AJ35: =BASE!$W$54 -> 0.79709864 | AK35: =AH35/AJ35 -> 0 | AL35: =AI35/AJ35 -> 0 | AM35: =IF(OR(ServExt8[[#This Row],[TIPO H]]="NORMAL",ServExt8[[#This Row],[HORAS DIA]]>=8),ServExt8[[#This Row],[PESSOAS]]*ServExt8[[#This Row],[DIAS]]*2,0) -> 0 | AN35: =(IF(Z35="","",LOOKUP(Z35,BASE!A$4:A$125,BASE!E$4:E$125)))*ServExt8[[#This Row],[TOTAL HORAS]] -> 0 | AO35: =IF(ServExt8[[#This Row],[TIPO H]]="NORMAL",ServExt8[[#This Row],[PESSOAS]],0) -> 0 | AP35: =IFERROR(ServExt8[[#This Row],[TOTAL3]]*(RESUMO!$F$32/RESUMO!$F$24),0) -> 0 | AU35: 14 | AV35: Especialista Computação IV
B36: 13 | C36: Sistemas | D36: Serviço | E36: 0 | F36: =LOOKUP('SERVICOS MONTAGEM'!$E$24:$E$63,BASE!A$4:A$125,BASE!B$4:B$125) -> 0 | I36: 8.8 | J36: NORMAL | K36: =_xlfn.IFS('SERVICOS MONTAGEM'!$J$24:$J$63="EXTRA 150%",((1)*2.5),'SERVICOS MONTAGEM'!$J$24:$J$63="EXTRA 100%",((1)*2),'SERVICOS MONTAGEM'!$J$24:$J$63="EXTRA 75%",((1)*1.75),'SERVICOS MONTAGEM'!$J$24:$J$63="EXTRA 50%",((1)*1.5),'SERVICOS MONTAGEM'!$J$24:$J$63="NORMAL",((1))) -> 1 | L36: =ServInt10[[#This Row],[DIAS]]*ServInt10[[#This Row],[PESSOAS]]*ServInt10[[#This Row],[HORAS DIA]] -> 0 | M36: =(IF(ServInt10[[#This Row],[CÓDIGO]]="","",LOOKUP(ServInt10[[#This Row],[CÓDIGO]],BASE!A$4:A$125,BASE!G$4:G$125)))*ServInt10[[#This Row],[HE CALC]] -> 0 | N36: =ServInt10[[#This Row],[TOTAL HORAS]]*ServInt10[[#This Row],[R$ / HORA]] -> 0 | O36: =BASE!$W$54 -> 0.79709864 | P36: =ServInt10[[#This Row],[R$ / HORA]]/ServInt10[[#This Row],[MARK-UP]] -> 0 | Q36: =ServInt10[[#This Row],[TOTAL]]/ServInt10[[#This Row],[MARK-UP]] -> 0 | S36: =(IF(E36="","",LOOKUP(E36,BASE!A$4:A$125,BASE!E$4:E$125)))*ServInt10[[#This Row],[TOTAL HORAS]] -> 0 | T36: =IFERROR(ServInt10[[#This Row],[TOTAL3]]*(RESUMO!$F$32/RESUMO!$F$24),0) -> 0 | W36: 13 | X36: Sistemas | Z36: 0 | AA36: =LOOKUP(Z36,BASE!A$4:A$125,BASE!B$4:B$125) -> 0 | AD36: 8.8 | AE36: NORMAL | AF36: =_xlfn.IFS(ServExt8[[#This Row],[TIPO H]]="EXTRA 150%",((1)*2.5),ServExt8[[#This Row],[TIPO H]]="EXTRA 100%",((1)*2),ServExt8[[#This Row],[TIPO H]]="EXTRA 75%",((1)*1.75),ServExt8[[#This Row],[TIPO H]]="EXTRA 50%",((1)*1.5),ServExt8[[#This Row],[TIPO H]]="NORMAL",((1))) -> 1 | AG36: =AC36*AB36*AD36 -> 0 | AH36: =(IF(Z36="","",LOOKUP(Z36,BASE!A$4:A$125,BASE!H$4:H$125)))*ServExt8[[#This Row],[HE CALC]] -> 0 | AI36: =ServExt8[[#This Row],[TOTAL HORAS]]*ServExt8[[#This Row],[R$ / HORA]] -> 0 | AJ36: =BASE!$W$54 -> 0.79709864 | AK36: =AH36/AJ36 -> 0 | AL36: =AI36/AJ36 -> 0 | AM36: =IF(OR(ServExt8[[#This Row],[TIPO H]]="NORMAL",ServExt8[[#This Row],[HORAS DIA]]>=8),ServExt8[[#This Row],[PESSOAS]]*ServExt8[[#This Row],[DIAS]]*2,0) -> 0 | AN36: =(IF(Z36="","",LOOKUP(Z36,BASE!A$4:A$125,BASE!E$4:E$125)))*ServExt8[[#This Row],[TOTAL HORAS]] -> 0 | AO36: =IF(ServExt8[[#This Row],[TIPO H]]="NORMAL",ServExt8[[#This Row],[PESSOAS]],0) -> 0 | AP36: =IFERROR(ServExt8[[#This Row],[TOTAL3]]*(RESUMO!$F$32/RESUMO!$F$24),0) -> 0 | AU36: 15 | AV36: Especialista Computação V
B37: 14 | C37: Sistemas | D37: Serviço | E37: 0 | F37: =LOOKUP('SERVICOS MONTAGEM'!$E$24:$E$63,BASE!A$4:A$125,BASE!B$4:B$125) -> 0 | I37: 8.8 | J37: NORMAL | K37: =_xlfn.IFS('SERVICOS MONTAGEM'!$J$24:$J$63="EXTRA 150%",((1)*2.5),'SERVICOS MONTAGEM'!$J$24:$J$63="EXTRA 100%",((1)*2),'SERVICOS MONTAGEM'!$J$24:$J$63="EXTRA 75%",((1)*1.75),'SERVICOS MONTAGEM'!$J$24:$J$63="EXTRA 50%",((1)*1.5),'SERVICOS MONTAGEM'!$J$24:$J$63="NORMAL",((1))) -> 1 | L37: =ServInt10[[#This Row],[DIAS]]*ServInt10[[#This Row],[PESSOAS]]*ServInt10[[#This Row],[HORAS DIA]] -> 0 | M37: =(IF(ServInt10[[#This Row],[CÓDIGO]]="","",LOOKUP(ServInt10[[#This Row],[CÓDIGO]],BASE!A$4:A$125,BASE!G$4:G$125)))*ServInt10[[#This Row],[HE CALC]] -> 0 | N37: =ServInt10[[#This Row],[TOTAL HORAS]]*ServInt10[[#This Row],[R$ / HORA]] -> 0 | O37: =BASE!$W$54 -> 0.79709864 | P37: =ServInt10[[#This Row],[R$ / HORA]]/ServInt10[[#This Row],[MARK-UP]] -> 0 | Q37: =ServInt10[[#This Row],[TOTAL]]/ServInt10[[#This Row],[MARK-UP]] -> 0 | S37: =(IF(E37="","",LOOKUP(E37,BASE!A$4:A$125,BASE!E$4:E$125)))*ServInt10[[#This Row],[TOTAL HORAS]] -> 0 | T37: =IFERROR(ServInt10[[#This Row],[TOTAL3]]*(RESUMO!$F$32/RESUMO!$F$24),0) -> 0 | W37: 14 | X37: Sistemas | Z37: 0 | AA37: =LOOKUP(Z37,BASE!A$4:A$125,BASE!B$4:B$125) -> 0 | AD37: 8.8 | AE37: NORMAL | AF37: =_xlfn.IFS(ServExt8[[#This Row],[TIPO H]]="EXTRA 150%",((1)*2.5),ServExt8[[#This Row],[TIPO H]]="EXTRA 100%",((1)*2),ServExt8[[#This Row],[TIPO H]]="EXTRA 75%",((1)*1.75),ServExt8[[#This Row],[TIPO H]]="EXTRA 50%",((1)*1.5),ServExt8[[#This Row],[TIPO H]]="NORMAL",((1))) -> 1 | AG37: =AC37*AB37*AD37 -> 0 | AH37: =(IF(Z37="","",LOOKUP(Z37,BASE!A$4:A$125,BASE!H$4:H$125)))*ServExt8[[#This Row],[HE CALC]] -> 0 | AI37: =ServExt8[[#This Row],[TOTAL HORAS]]*ServExt8[[#This Row],[R$ / HORA]] -> 0 | AJ37: =BASE!$W$54 -> 0.79709864 | AK37: =AH37/AJ37 -> 0 | AL37: =AI37/AJ37 -> 0 | AM37: =IF(OR(ServExt8[[#This Row],[TIPO H]]="NORMAL",ServExt8[[#This Row],[HORAS DIA]]>=8),ServExt8[[#This Row],[PESSOAS]]*ServExt8[[#This Row],[DIAS]]*2,0) -> 0 | AN37: =(IF(Z37="","",LOOKUP(Z37,BASE!A$4:A$125,BASE!E$4:E$125)))*ServExt8[[#This Row],[TOTAL HORAS]] -> 0 | AO37: =IF(ServExt8[[#This Row],[TIPO H]]="NORMAL",ServExt8[[#This Row],[PESSOAS]],0) -> 0 | AP37: =IFERROR(ServExt8[[#This Row],[TOTAL3]]*(RESUMO!$F$32/RESUMO!$F$24),0) -> 0 | AU37: 16 | AV37: Analista de Sistemas de Automação I
B38: 15 | C38: Sistemas | D38: Serviço | E38: 0 | F38: =LOOKUP('SERVICOS MONTAGEM'!$E$24:$E$63,BASE!A$4:A$125,BASE!B$4:B$125) -> 0 | I38: 8.8 | J38: NORMAL | K38: =_xlfn.IFS('SERVICOS MONTAGEM'!$J$24:$J$63="EXTRA 150%",((1)*2.5),'SERVICOS MONTAGEM'!$J$24:$J$63="EXTRA 100%",((1)*2),'SERVICOS MONTAGEM'!$J$24:$J$63="EXTRA 75%",((1)*1.75),'SERVICOS MONTAGEM'!$J$24:$J$63="EXTRA 50%",((1)*1.5),'SERVICOS MONTAGEM'!$J$24:$J$63="NORMAL",((1))) -> 1 | L38: =ServInt10[[#This Row],[DIAS]]*ServInt10[[#This Row],[PESSOAS]]*ServInt10[[#This Row],[HORAS DIA]] -> 0 | M38: =(IF(ServInt10[[#This Row],[CÓDIGO]]="","",LOOKUP(ServInt10[[#This Row],[CÓDIGO]],BASE!A$4:A$125,BASE!G$4:G$125)))*ServInt10[[#This Row],[HE CALC]] -> 0 | N38: =ServInt10[[#This Row],[TOTAL HORAS]]*ServInt10[[#This Row],[R$ / HORA]] -> 0 | O38: =BASE!$W$54 -> 0.79709864 | P38: =ServInt10[[#This Row],[R$ / HORA]]/ServInt10[[#This Row],[MARK-UP]] -> 0 | Q38: =ServInt10[[#This Row],[TOTAL]]/ServInt10[[#This Row],[MARK-UP]] -> 0 | S38: =(IF(E38="","",LOOKUP(E38,BASE!A$4:A$125,BASE!E$4:E$125)))*ServInt10[[#This Row],[TOTAL HORAS]] -> 0 | T38: =IFERROR(ServInt10[[#This Row],[TOTAL3]]*(RESUMO!$F$32/RESUMO!$F$24),0) -> 0 | W38: 15 | X38: Sistemas | Z38: 0 | AA38: =LOOKUP(Z38,BASE!A$4:A$125,BASE!B$4:B$125) -> 0 | AD38: 8.8 | AE38: NORMAL | AF38: =_xlfn.IFS(ServExt8[[#This Row],[TIPO H]]="EXTRA 150%",((1)*2.5),ServExt8[[#This Row],[TIPO H]]="EXTRA 100%",((1)*2),ServExt8[[#This Row],[TIPO H]]="EXTRA 75%",((1)*1.75),ServExt8[[#This Row],[TIPO H]]="EXTRA 50%",((1)*1.5),ServExt8[[#This Row],[TIPO H]]="NORMAL",((1))) -> 1 | AG38: =AC38*AB38*AD38 -> 0 | AH38: =(IF(Z38="","",LOOKUP(Z38,BASE!A$4:A$125,BASE!H$4:H$125)))*ServExt8[[#This Row],[HE CALC]] -> 0 | AI38: =ServExt8[[#This Row],[TOTAL HORAS]]*ServExt8[[#This Row],[R$ / HORA]] -> 0 | AJ38: =BASE!$W$54 -> 0.79709864 | AK38: =AH38/AJ38 -> 0 | AL38: =AI38/AJ38 -> 0 | AM38: =IF(OR(ServExt8[[#This Row],[TIPO H]]="NORMAL",ServExt8[[#This Row],[HORAS DIA]]>=8),ServExt8[[#This Row],[PESSOAS]]*ServExt8[[#This Row],[DIAS]]*2,0) -> 0 | AN38: =(IF(Z38="","",LOOKUP(Z38,BASE!A$4:A$125,BASE!E$4:E$125)))*ServExt8[[#This Row],[TOTAL HORAS]] -> 0 | AO38: =IF(ServExt8[[#This Row],[TIPO H]]="NORMAL",ServExt8[[#This Row],[PESSOAS]],0) -> 0 | AP38: =IFERROR(ServExt8[[#This Row],[TOTAL3]]*(RESUMO!$F$32/RESUMO!$F$24),0) -> 0 | AU38: 17 | AV38: Analista de Sistemas de Automação II
B39: 16 | C39: Sistemas | D39: Serviço | E39: 0 | F39: =LOOKUP('SERVICOS MONTAGEM'!$E$24:$E$63,BASE!A$4:A$125,BASE!B$4:B$125) -> 0 | I39: 8.8 | J39: NORMAL | K39: =_xlfn.IFS('SERVICOS MONTAGEM'!$J$24:$J$63="EXTRA 150%",((1)*2.5),'SERVICOS MONTAGEM'!$J$24:$J$63="EXTRA 100%",((1)*2),'SERVICOS MONTAGEM'!$J$24:$J$63="EXTRA 75%",((1)*1.75),'SERVICOS MONTAGEM'!$J$24:$J$63="EXTRA 50%",((1)*1.5),'SERVICOS MONTAGEM'!$J$24:$J$63="NORMAL",((1))) -> 1 | L39: =ServInt10[[#This Row],[DIAS]]*ServInt10[[#This Row],[PESSOAS]]*ServInt10[[#This Row],[HORAS DIA]] -> 0 | M39: =(IF(ServInt10[[#This Row],[CÓDIGO]]="","",LOOKUP(ServInt10[[#This Row],[CÓDIGO]],BASE!A$4:A$125,BASE!G$4:G$125)))*ServInt10[[#This Row],[HE CALC]] -> 0 | N39: =ServInt10[[#This Row],[TOTAL HORAS]]*ServInt10[[#This Row],[R$ / HORA]] -> 0 | O39: =BASE!$W$54 -> 0.79709864 | P39: =ServInt10[[#This Row],[R$ / HORA]]/ServInt10[[#This Row],[MARK-UP]] -> 0 | Q39: =ServInt10[[#This Row],[TOTAL]]/ServInt10[[#This Row],[MARK-UP]] -> 0 | S39: =(IF(E39="","",LOOKUP(E39,BASE!A$4:A$125,BASE!E$4:E$125)))*ServInt10[[#This Row],[TOTAL HORAS]] -> 0 | T39: =IFERROR(ServInt10[[#This Row],[TOTAL3]]*(RESUMO!$F$32/RESUMO!$F$24),0) -> 0 | W39: 16 | X39: Sistemas | Z39: 0 | AA39: =LOOKUP(Z39,BASE!A$4:A$125,BASE!B$4:B$125) -> 0 | AD39: 8.8 | AE39: NORMAL | AF39: =_xlfn.IFS(ServExt8[[#This Row],[TIPO H]]="EXTRA 150%",((1)*2.5),ServExt8[[#This Row],[TIPO H]]="EXTRA 100%",((1)*2),ServExt8[[#This Row],[TIPO H]]="EXTRA 75%",((1)*1.75),ServExt8[[#This Row],[TIPO H]]="EXTRA 50%",((1)*1.5),ServExt8[[#This Row],[TIPO H]]="NORMAL",((1))) -> 1 | AG39: =AC39*AB39*AD39 -> 0 | AH39: =(IF(Z39="","",LOOKUP(Z39,BASE!A$4:A$125,BASE!H$4:H$125)))*ServExt8[[#This Row],[HE CALC]] -> 0 | AI39: =ServExt8[[#This Row],[TOTAL HORAS]]*ServExt8[[#This Row],[R$ / HORA]] -> 0 | AJ39: =BASE!$W$54 -> 0.79709864 | AK39: =AH39/AJ39 -> 0 | AL39: =AI39/AJ39 -> 0 | AM39: =IF(OR(ServExt8[[#This Row],[TIPO H]]="NORMAL",ServExt8[[#This Row],[HORAS DIA]]>=8),ServExt8[[#This Row],[PESSOAS]]*ServExt8[[#This Row],[DIAS]]*2,0) -> 0 | AN39: =(IF(Z39="","",LOOKUP(Z39,BASE!A$4:A$125,BASE!E$4:E$125)))*ServExt8[[#This Row],[TOTAL HORAS]] -> 0 | AO39: =IF(ServExt8[[#This Row],[TIPO H]]="NORMAL",ServExt8[[#This Row],[PESSOAS]],0) -> 0 | AP39: =IFERROR(ServExt8[[#This Row],[TOTAL3]]*(RESUMO!$F$32/RESUMO!$F$24),0) -> 0 | AU39: 18 | AV39: Analista de Sistemas de Automação III
B40: 17 | C40: Sistemas | D40: Serviço | E40: 0 | F40: =LOOKUP('SERVICOS MONTAGEM'!$E$24:$E$63,BASE!A$4:A$125,BASE!B$4:B$125) -> 0 | I40: 8.8 | J40: NORMAL | K40: =_xlfn.IFS('SERVICOS MONTAGEM'!$J$24:$J$63="EXTRA 150%",((1)*2.5),'SERVICOS MONTAGEM'!$J$24:$J$63="EXTRA 100%",((1)*2),'SERVICOS MONTAGEM'!$J$24:$J$63="EXTRA 75%",((1)*1.75),'SERVICOS MONTAGEM'!$J$24:$J$63="EXTRA 50%",((1)*1.5),'SERVICOS MONTAGEM'!$J$24:$J$63="NORMAL",((1))) -> 1 | L40: =ServInt10[[#This Row],[DIAS]]*ServInt10[[#This Row],[PESSOAS]]*ServInt10[[#This Row],[HORAS DIA]] -> 0 | M40: =(IF(ServInt10[[#This Row],[CÓDIGO]]="","",LOOKUP(ServInt10[[#This Row],[CÓDIGO]],BASE!A$4:A$125,BASE!G$4:G$125)))*ServInt10[[#This Row],[HE CALC]] -> 0 | N40: =ServInt10[[#This Row],[TOTAL HORAS]]*ServInt10[[#This Row],[R$ / HORA]] -> 0 | O40: =BASE!$W$54 -> 0.79709864 | P40: =ServInt10[[#This Row],[R$ / HORA]]/ServInt10[[#This Row],[MARK-UP]] -> 0 | Q40: =ServInt10[[#This Row],[TOTAL]]/ServInt10[[#This Row],[MARK-UP]] -> 0 | S40: =(IF(E40="","",LOOKUP(E40,BASE!A$4:A$125,BASE!E$4:E$125)))*ServInt10[[#This Row],[TOTAL HORAS]] -> 0 | T40: =IFERROR(ServInt10[[#This Row],[TOTAL3]]*(RESUMO!$F$32/RESUMO!$F$24),0) -> 0 | W40: 17 | X40: Sistemas | Z40: 0 | AA40: =LOOKUP(Z40,BASE!A$4:A$125,BASE!B$4:B$125) -> 0 | AD40: 8.8 | AE40: NORMAL | AF40: =_xlfn.IFS(ServExt8[[#This Row],[TIPO H]]="EXTRA 150%",((1)*2.5),ServExt8[[#This Row],[TIPO H]]="EXTRA 100%",((1)*2),ServExt8[[#This Row],[TIPO H]]="EXTRA 75%",((1)*1.75),ServExt8[[#This Row],[TIPO H]]="EXTRA 50%",((1)*1.5),ServExt8[[#This Row],[TIPO H]]="NORMAL",((1))) -> 1 | AG40: =AC40*AB40*AD40 -> 0 | AH40: =(IF(Z40="","",LOOKUP(Z40,BASE!A$4:A$125,BASE!H$4:H$125)))*ServExt8[[#This Row],[HE CALC]] -> 0 | AI40: =ServExt8[[#This Row],[TOTAL HORAS]]*ServExt8[[#This Row],[R$ / HORA]] -> 0 | AJ40: =BASE!$W$54 -> 0.79709864 | AK40: =AH40/AJ40 -> 0 | AL40: =AI40/AJ40 -> 0 | AM40: =IF(OR(ServExt8[[#This Row],[TIPO H]]="NORMAL",ServExt8[[#This Row],[HORAS DIA]]>=8),ServExt8[[#This Row],[PESSOAS]]*ServExt8[[#This Row],[DIAS]]*2,0) -> 0 | AN40: =(IF(Z40="","",LOOKUP(Z40,BASE!A$4:A$125,BASE!E$4:E$125)))*ServExt8[[#This Row],[TOTAL HORAS]] -> 0 | AO40: =IF(ServExt8[[#This Row],[TIPO H]]="NORMAL",ServExt8[[#This Row],[PESSOAS]],0) -> 0 | AP40: =IFERROR(ServExt8[[#This Row],[TOTAL3]]*(RESUMO!$F$32/RESUMO!$F$24),0) -> 0 | AU40: 19 | AV40: Analista de Sistemas de Automação IV
B41: 18 | C41: Sistemas | D41: Serviço | E41: 0 | F41: =LOOKUP('SERVICOS MONTAGEM'!$E$24:$E$63,BASE!A$4:A$125,BASE!B$4:B$125) -> 0 | I41: 8.8 | J41: NORMAL | K41: =_xlfn.IFS('SERVICOS MONTAGEM'!$J$24:$J$63="EXTRA 150%",((1)*2.5),'SERVICOS MONTAGEM'!$J$24:$J$63="EXTRA 100%",((1)*2),'SERVICOS MONTAGEM'!$J$24:$J$63="EXTRA 75%",((1)*1.75),'SERVICOS MONTAGEM'!$J$24:$J$63="EXTRA 50%",((1)*1.5),'SERVICOS MONTAGEM'!$J$24:$J$63="NORMAL",((1))) -> 1 | L41: =ServInt10[[#This Row],[DIAS]]*ServInt10[[#This Row],[PESSOAS]]*ServInt10[[#This Row],[HORAS DIA]] -> 0 | M41: =(IF(ServInt10[[#This Row],[CÓDIGO]]="","",LOOKUP(ServInt10[[#This Row],[CÓDIGO]],BASE!A$4:A$125,BASE!G$4:G$125)))*ServInt10[[#This Row],[HE CALC]] -> 0 | N41: =ServInt10[[#This Row],[TOTAL HORAS]]*ServInt10[[#This Row],[R$ / HORA]] -> 0 | O41: =BASE!$W$54 -> 0.79709864 | P41: =ServInt10[[#This Row],[R$ / HORA]]/ServInt10[[#This Row],[MARK-UP]] -> 0 | Q41: =ServInt10[[#This Row],[TOTAL]]/ServInt10[[#This Row],[MARK-UP]] -> 0 | S41: =(IF(E41="","",LOOKUP(E41,BASE!A$4:A$125,BASE!E$4:E$125)))*ServInt10[[#This Row],[TOTAL HORAS]] -> 0 | T41: =IFERROR(ServInt10[[#This Row],[TOTAL3]]*(RESUMO!$F$32/RESUMO!$F$24),0) -> 0 | W41: 18 | X41: Sistemas | Z41: 0 | AA41: =LOOKUP(Z41,BASE!A$4:A$125,BASE!B$4:B$125) -> 0 | AD41: 8.8 | AE41: NORMAL | AF41: =_xlfn.IFS(ServExt8[[#This Row],[TIPO H]]="EXTRA 150%",((1)*2.5),ServExt8[[#This Row],[TIPO H]]="EXTRA 100%",((1)*2),ServExt8[[#This Row],[TIPO H]]="EXTRA 75%",((1)*1.75),ServExt8[[#This Row],[TIPO H]]="EXTRA 50%",((1)*1.5),ServExt8[[#This Row],[TIPO H]]="NORMAL",((1))) -> 1 | AG41: =AC41*AB41*AD41 -> 0 | AH41: =(IF(Z41="","",LOOKUP(Z41,BASE!A$4:A$125,BASE!H$4:H$125)))*ServExt8[[#This Row],[HE CALC]] -> 0 | AI41: =ServExt8[[#This Row],[TOTAL HORAS]]*ServExt8[[#This Row],[R$ / HORA]] -> 0 | AJ41: =BASE!$W$54 -> 0.79709864 | AK41: =AH41/AJ41 -> 0 | AL41: =AI41/AJ41 -> 0 | AM41: =IF(OR(ServExt8[[#This Row],[TIPO H]]="NORMAL",ServExt8[[#This Row],[HORAS DIA]]>=8),ServExt8[[#This Row],[PESSOAS]]*ServExt8[[#This Row],[DIAS]]*2,0) -> 0 | AN41: =(IF(Z41="","",LOOKUP(Z41,BASE!A$4:A$125,BASE!E$4:E$125)))*ServExt8[[#This Row],[TOTAL HORAS]] -> 0 | AO41: =IF(ServExt8[[#This Row],[TIPO H]]="NORMAL",ServExt8[[#This Row],[PESSOAS]],0) -> 0 | AP41: =IFERROR(ServExt8[[#This Row],[TOTAL3]]*(RESUMO!$F$32/RESUMO!$F$24),0) -> 0 | AU41: 20 | AV41: Analista de Sistemas de Automação V
... B45: 22 | C45: Sistemas | D45: Serviço | E45: 0 | F45: =LOOKUP('SERVICOS MONTAGEM'!$E$24:$E$63,BASE!A$4:A$125,BASE!B$4:B$125) -> 0 | I45: 8.8 | J45: NORMAL | K45: =_xlfn.IFS('SERVICOS MONTAGEM'!$J$24:$J$63="EXTRA 150%",((1)*2.5),'SERVICOS MONTAGEM'!$J$24:$J$63="EXTRA 100%",((1)*2),'SERVICOS MONTAGEM'!$J$24:$J$63="EXTRA 75%",((1)*1.75),'SERVICOS MONTAGEM'!$J$24:$J$63="EXTRA 50%",((1)*1.5),'SERVICOS MONTAGEM'!$J$24:$J$63="NORMAL",((1))) -> 1 | L45: =ServInt10[[#This Row],[DIAS]]*ServInt10[[#This Row],[PESSOAS]]*ServInt10[[#This Row],[HORAS DIA]] -> 0 | M45: =(IF(ServInt10[[#This Row],[CÓDIGO]]="","",LOOKUP(ServInt10[[#This Row],[CÓDIGO]],BASE!A$4:A$125,BASE!G$4:G$125)))*ServInt10[[#This Row],[HE CALC]] -> 0 | N45: =ServInt10[[#This Row],[TOTAL HORAS]]*ServInt10[[#This Row],[R$ / HORA]] -> 0 | O45: =BASE!$W$54 -> 0.79709864 | P45: =ServInt10[[#This Row],[R$ / HORA]]/ServInt10[[#This Row],[MARK-UP]] -> 0 | Q45: =ServInt10[[#This Row],[TOTAL]]/ServInt10[[#This Row],[MARK-UP]] -> 0 | S45: =(IF(E45="","",LOOKUP(E45,BASE!A$4:A$125,BASE!E$4:E$125)))*ServInt10[[#This Row],[TOTAL HORAS]] -> 0 | T45: =IFERROR(ServInt10[[#This Row],[TOTAL3]]*(RESUMO!$F$32/RESUMO!$F$24),0) -> 0 | W45: 22 | X45: Sistemas | Z45: 0 | AA45: =LOOKUP(Z45,BASE!A$4:A$125,BASE!B$4:B$125) -> 0 | AD45: 8.8 | AE45: NORMAL | AF45: =_xlfn.IFS(ServExt8[[#This Row],[TIPO H]]="EXTRA 150%",((1)*2.5),ServExt8[[#This Row],[TIPO H]]="EXTRA 100%",((1)*2),ServExt8[[#This Row],[TIPO H]]="EXTRA 75%",((1)*1.75),ServExt8[[#This Row],[TIPO H]]="EXTRA 50%",((1)*1.5),ServExt8[[#This Row],[TIPO H]]="NORMAL",((1))) -> 1 | AG45: =AC45*AB45*AD45 -> 0 | AH45: =(IF(Z45="","",LOOKUP(Z45,BASE!A$4:A$125,BASE!H$4:H$125)))*ServExt8[[#This Row],[HE CALC]] -> 0 | AI45: =ServExt8[[#This Row],[TOTAL HORAS]]*ServExt8[[#This Row],[R$ / HORA]] -> 0 | AJ45: =BASE!$W$54 -> 0.79709864 | AK45: =AH45/AJ45 -> 0 | AL45: =AI45/AJ45 -> 0 | AM45: =IF(OR(ServExt8[[#This Row],[TIPO H]]="NORMAL",ServExt8[[#This Row],[HORAS DIA]]>=8),ServExt8[[#This Row],[PESSOAS]]*ServExt8[[#This Row],[DIAS]]*2,0) -> 0 | AN45: =(IF(Z45="","",LOOKUP(Z45,BASE!A$4:A$125,BASE!E$4:E$125)))*ServExt8[[#This Row],[TOTAL HORAS]] -> 0 | AO45: =IF(ServExt8[[#This Row],[TIPO H]]="NORMAL",ServExt8[[#This Row],[PESSOAS]],0) -> 0 | AP45: =IFERROR(ServExt8[[#This Row],[TOTAL3]]*(RESUMO!$F$32/RESUMO!$F$24),0) -> 0 | AU45: 24 | AV45: Desenhista Projetista IV
B46: 23 | C46: Sistemas | D46: Serviço | E46: 0 | F46: =LOOKUP('SERVICOS MONTAGEM'!$E$24:$E$63,BASE!A$4:A$125,BASE!B$4:B$125) -> 0 | I46: 8.8 | J46: NORMAL | K46: =_xlfn.IFS('SERVICOS MONTAGEM'!$J$24:$J$58="EXTRA 150%",((1)*2.5),'SERVICOS MONTAGEM'!$J$24:$J$58="EXTRA 100%",((1)*2),'SERVICOS MONTAGEM'!$J$24:$J$58="EXTRA 75%",((1)*1.75),'SERVICOS MONTAGEM'!$J$24:$J$58="EXTRA 50%",((1)*1.5),'SERVICOS MONTAGEM'!$J$24:$J$58="NORMAL",((1))) -> 1 | L46: =ServInt10[[#This Row],[DIAS]]*ServInt10[[#This Row],[PESSOAS]]*ServInt10[[#This Row],[HORAS DIA]] -> 0 | M46: =(IF(ServInt10[[#This Row],[CÓDIGO]]="","",LOOKUP(ServInt10[[#This Row],[CÓDIGO]],BASE!A$4:A$125,BASE!G$4:G$125)))*ServInt10[[#This Row],[HE CALC]] -> 0 | N46: =ServInt10[[#This Row],[TOTAL HORAS]]*ServInt10[[#This Row],[R$ / HORA]] -> 0 | O46: =BASE!$W$54 -> 0.79709864 | P46: =ServInt10[[#This Row],[R$ / HORA]]/ServInt10[[#This Row],[MARK-UP]] -> 0 | Q46: =ServInt10[[#This Row],[TOTAL]]/ServInt10[[#This Row],[MARK-UP]] -> 0 | S46: =(IF(E46="","",LOOKUP(E46,BASE!A$4:A$125,BASE!E$4:E$125)))*ServInt10[[#This Row],[TOTAL HORAS]] -> 0 | T46: =IFERROR(ServInt10[[#This Row],[TOTAL3]]*(RESUMO!$F$32/RESUMO!$F$24),0) -> 0 | W46: 23 | X46: Sistemas | Z46: 0 | AA46: =LOOKUP(Z46,BASE!A$4:A$125,BASE!B$4:B$125) -> 0 | AD46: 8.8 | AE46: NORMAL | AF46: =_xlfn.IFS(ServExt8[[#This Row],[TIPO H]]="EXTRA 150%",((1)*2.5),ServExt8[[#This Row],[TIPO H]]="EXTRA 100%",((1)*2),ServExt8[[#This Row],[TIPO H]]="EXTRA 75%",((1)*1.75),ServExt8[[#This Row],[TIPO H]]="EXTRA 50%",((1)*1.5),ServExt8[[#This Row],[TIPO H]]="NORMAL",((1))) -> 1 | AG46: =AC46*AB46*AD46 -> 0 | AH46: =(IF(Z46="","",LOOKUP(Z46,BASE!A$4:A$125,BASE!H$4:H$125)))*ServExt8[[#This Row],[HE CALC]] -> 0 | AI46: =ServExt8[[#This Row],[TOTAL HORAS]]*ServExt8[[#This Row],[R$ / HORA]] -> 0 | AJ46: =BASE!$W$54 -> 0.79709864 | AK46: =AH46/AJ46 -> 0 | AL46: =AI46/AJ46 -> 0 | AM46: =IF(OR(ServExt8[[#This Row],[TIPO H]]="NORMAL",ServExt8[[#This Row],[HORAS DIA]]>=8),ServExt8[[#This Row],[PESSOAS]]*ServExt8[[#This Row],[DIAS]]*2,0) -> 0 | AN46: =(IF(Z46="","",LOOKUP(Z46,BASE!A$4:A$125,BASE!E$4:E$125)))*ServExt8[[#This Row],[TOTAL HORAS]] -> 0 | AO46: =IF(ServExt8[[#This Row],[TIPO H]]="NORMAL",ServExt8[[#This Row],[PESSOAS]],0) -> 0 | AP46: =IFERROR(ServExt8[[#This Row],[TOTAL3]]*(RESUMO!$F$32/RESUMO!$F$24),0) -> 0 | AU46: 25 | AV46: Desenhista Projetista V
B47: 24 | C47: Sistemas | D47: Serviço | E47: 0 | F47: =LOOKUP('SERVICOS MONTAGEM'!$E$24:$E$63,BASE!A$4:A$125,BASE!B$4:B$125) -> 0 | I47: 8.8 | J47: NORMAL | K47: =_xlfn.IFS('SERVICOS MONTAGEM'!$J$24:$J$58="EXTRA 150%",((1)*2.5),'SERVICOS MONTAGEM'!$J$24:$J$58="EXTRA 100%",((1)*2),'SERVICOS MONTAGEM'!$J$24:$J$58="EXTRA 75%",((1)*1.75),'SERVICOS MONTAGEM'!$J$24:$J$58="EXTRA 50%",((1)*1.5),'SERVICOS MONTAGEM'!$J$24:$J$58="NORMAL",((1))) -> 1 | L47: =ServInt10[[#This Row],[DIAS]]*ServInt10[[#This Row],[PESSOAS]]*ServInt10[[#This Row],[HORAS DIA]] -> 0 | M47: =(IF(ServInt10[[#This Row],[CÓDIGO]]="","",LOOKUP(ServInt10[[#This Row],[CÓDIGO]],BASE!A$4:A$125,BASE!G$4:G$125)))*ServInt10[[#This Row],[HE CALC]] -> 0 | N47: =ServInt10[[#This Row],[TOTAL HORAS]]*ServInt10[[#This Row],[R$ / HORA]] -> 0 | O47: =BASE!$W$54 -> 0.79709864 | P47: =ServInt10[[#This Row],[R$ / HORA]]/ServInt10[[#This Row],[MARK-UP]] -> 0 | Q47: =ServInt10[[#This Row],[TOTAL]]/ServInt10[[#This Row],[MARK-UP]] -> 0 | S47: =(IF(E47="","",LOOKUP(E47,BASE!A$4:A$125,BASE!E$4:E$125)))*ServInt10[[#This Row],[TOTAL HORAS]] -> 0 | T47: =IFERROR(ServInt10[[#This Row],[TOTAL3]]*(RESUMO!$F$32/RESUMO!$F$24),0) -> 0 | W47: 24 | X47: Sistemas | Z47: 0 | AA47: =LOOKUP(Z47,BASE!A$4:A$125,BASE!B$4:B$125) -> 0 | AD47: 8.8 | AE47: NORMAL | AF47: =_xlfn.IFS(ServExt8[[#This Row],[TIPO H]]="EXTRA 150%",((1)*2.5),ServExt8[[#This Row],[TIPO H]]="EXTRA 100%",((1)*2),ServExt8[[#This Row],[TIPO H]]="EXTRA 75%",((1)*1.75),ServExt8[[#This Row],[TIPO H]]="EXTRA 50%",((1)*1.5),ServExt8[[#This Row],[TIPO H]]="NORMAL",((1))) -> 1 | AG47: =AC47*AB47*AD47 -> 0 | AH47: =(IF(Z47="","",LOOKUP(Z47,BASE!A$4:A$125,BASE!H$4:H$125)))*ServExt8[[#This Row],[HE CALC]] -> 0 | AI47: =ServExt8[[#This Row],[TOTAL HORAS]]*ServExt8[[#This Row],[R$ / HORA]] -> 0 | AJ47: =BASE!$W$54 -> 0.79709864 | AK47: =AH47/AJ47 -> 0 | AL47: =AI47/AJ47 -> 0 | AM47: =IF(OR(ServExt8[[#This Row],[TIPO H]]="NORMAL",ServExt8[[#This Row],[HORAS DIA]]>=8),ServExt8[[#This Row],[PESSOAS]]*ServExt8[[#This Row],[DIAS]]*2,0) -> 0 | AN47: =(IF(Z47="","",LOOKUP(Z47,BASE!A$4:A$125,BASE!E$4:E$125)))*ServExt8[[#This Row],[TOTAL HORAS]] -> 0 | AO47: =IF(ServExt8[[#This Row],[TIPO H]]="NORMAL",ServExt8[[#This Row],[PESSOAS]],0) -> 0 | AP47: =IFERROR(ServExt8[[#This Row],[TOTAL3]]*(RESUMO!$F$32/RESUMO!$F$24),0) -> 0 | AU47: 26 | AV47: Projetista Elétrico I
B48: 25 | C48: Sistemas | D48: Serviço | E48: 0 | F48: =LOOKUP('SERVICOS MONTAGEM'!$E$24:$E$63,BASE!A$4:A$125,BASE!B$4:B$125) -> 0 | I48: 8.8 | J48: NORMAL | K48: =_xlfn.IFS('SERVICOS MONTAGEM'!$J$24:$J$58="EXTRA 150%",((1)*2.5),'SERVICOS MONTAGEM'!$J$24:$J$58="EXTRA 100%",((1)*2),'SERVICOS MONTAGEM'!$J$24:$J$58="EXTRA 75%",((1)*1.75),'SERVICOS MONTAGEM'!$J$24:$J$58="EXTRA 50%",((1)*1.5),'SERVICOS MONTAGEM'!$J$24:$J$58="NORMAL",((1))) -> 1 | L48: =ServInt10[[#This Row],[DIAS]]*ServInt10[[#This Row],[PESSOAS]]*ServInt10[[#This Row],[HORAS DIA]] -> 0 | M48: =(IF(ServInt10[[#This Row],[CÓDIGO]]="","",LOOKUP(ServInt10[[#This Row],[CÓDIGO]],BASE!A$4:A$125,BASE!G$4:G$125)))*ServInt10[[#This Row],[HE CALC]] -> 0 | N48: =ServInt10[[#This Row],[TOTAL HORAS]]*ServInt10[[#This Row],[R$ / HORA]] -> 0 | O48: =BASE!$W$54 -> 0.79709864 | P48: =ServInt10[[#This Row],[R$ / HORA]]/ServInt10[[#This Row],[MARK-UP]] -> 0 | Q48: =ServInt10[[#This Row],[TOTAL]]/ServInt10[[#This Row],[MARK-UP]] -> 0 | S48: =(IF(E48="","",LOOKUP(E48,BASE!A$4:A$125,BASE!E$4:E$125)))*ServInt10[[#This Row],[TOTAL HORAS]] -> 0 | T48: =IFERROR(ServInt10[[#This Row],[TOTAL3]]*(RESUMO!$F$32/RESUMO!$F$24),0) -> 0 | W48: 25 | X48: Sistemas | Z48: 0 | AA48: =LOOKUP(Z48,BASE!A$4:A$125,BASE!B$4:B$125) -> 0 | AD48: 8.8 | AE48: NORMAL | AF48: =_xlfn.IFS(ServExt8[[#This Row],[TIPO H]]="EXTRA 150%",((1)*2.5),ServExt8[[#This Row],[TIPO H]]="EXTRA 100%",((1)*2),ServExt8[[#This Row],[TIPO H]]="EXTRA 75%",((1)*1.75),ServExt8[[#This Row],[TIPO H]]="EXTRA 50%",((1)*1.5),ServExt8[[#This Row],[TIPO H]]="NORMAL",((1))) -> 1 | AG48: =AC48*AB48*AD48 -> 0 | AH48: =(IF(Z48="","",LOOKUP(Z48,BASE!A$4:A$125,BASE!H$4:H$125)))*ServExt8[[#This Row],[HE CALC]] -> 0 | AI48: =ServExt8[[#This Row],[TOTAL HORAS]]*ServExt8[[#This Row],[R$ / HORA]] -> 0 | AJ48: =BASE!$W$54 -> 0.79709864 | AK48: =AH48/AJ48 -> 0 | AL48: =AI48/AJ48 -> 0 | AM48: =IF(OR(ServExt8[[#This Row],[TIPO H]]="NORMAL",ServExt8[[#This Row],[HORAS DIA]]>=8),ServExt8[[#This Row],[PESSOAS]]*ServExt8[[#This Row],[DIAS]]*2,0) -> 0 | AN48: =(IF(Z48="","",LOOKUP(Z48,BASE!A$4:A$125,BASE!E$4:E$125)))*ServExt8[[#This Row],[TOTAL HORAS]] -> 0 | AO48: =IF(ServExt8[[#This Row],[TIPO H]]="NORMAL",ServExt8[[#This Row],[PESSOAS]],0) -> 0 | AP48: =IFERROR(ServExt8[[#This Row],[TOTAL3]]*(RESUMO!$F$32/RESUMO!$F$24),0) -> 0 | AU48: 27 | AV48: Projetista Elétrico II
B49: 26 | C49: Sistemas | D49: Serviço | E49: 0 | F49: =LOOKUP('SERVICOS MONTAGEM'!$E$24:$E$63,BASE!A$4:A$125,BASE!B$4:B$125) -> 0 | I49: 8.8 | J49: NORMAL | K49: =_xlfn.IFS('SERVICOS MONTAGEM'!$J$24:$J$58="EXTRA 150%",((1)*2.5),'SERVICOS MONTAGEM'!$J$24:$J$58="EXTRA 100%",((1)*2),'SERVICOS MONTAGEM'!$J$24:$J$58="EXTRA 75%",((1)*1.75),'SERVICOS MONTAGEM'!$J$24:$J$58="EXTRA 50%",((1)*1.5),'SERVICOS MONTAGEM'!$J$24:$J$58="NORMAL",((1))) -> 1 | L49: =ServInt10[[#This Row],[DIAS]]*ServInt10[[#This Row],[PESSOAS]]*ServInt10[[#This Row],[HORAS DIA]] -> 0 | M49: =(IF(ServInt10[[#This Row],[CÓDIGO]]="","",LOOKUP(ServInt10[[#This Row],[CÓDIGO]],BASE!A$4:A$125,BASE!G$4:G$125)))*ServInt10[[#This Row],[HE CALC]] -> 0 | N49: =ServInt10[[#This Row],[TOTAL HORAS]]*ServInt10[[#This Row],[R$ / HORA]] -> 0 | O49: =BASE!$W$54 -> 0.79709864 | P49: =ServInt10[[#This Row],[R$ / HORA]]/ServInt10[[#This Row],[MARK-UP]] -> 0 | Q49: =ServInt10[[#This Row],[TOTAL]]/ServInt10[[#This Row],[MARK-UP]] -> 0 | S49: =(IF(E49="","",LOOKUP(E49,BASE!A$4:A$125,BASE!E$4:E$125)))*ServInt10[[#This Row],[TOTAL HORAS]] -> 0 | T49: =IFERROR(ServInt10[[#This Row],[TOTAL3]]*(RESUMO!$F$32/RESUMO!$F$24),0) -> 0 | W49: 26 | X49: Sistemas | Z49: 0 | AA49: =LOOKUP(Z49,BASE!A$4:A$125,BASE!B$4:B$125) -> 0 | AD49: 8.8 | AE49: NORMAL | AF49: =_xlfn.IFS(ServExt8[[#This Row],[TIPO H]]="EXTRA 150%",((1)*2.5),ServExt8[[#This Row],[TIPO H]]="EXTRA 100%",((1)*2),ServExt8[[#This Row],[TIPO H]]="EXTRA 75%",((1)*1.75),ServExt8[[#This Row],[TIPO H]]="EXTRA 50%",((1)*1.5),ServExt8[[#This Row],[TIPO H]]="NORMAL",((1))) -> 1 | AG49: =AC49*AB49*AD49 -> 0 | AH49: =(IF(Z49="","",LOOKUP(Z49,BASE!A$4:A$125,BASE!H$4:H$125)))*ServExt8[[#This Row],[HE CALC]] -> 0 | AI49: =ServExt8[[#This Row],[TOTAL HORAS]]*ServExt8[[#This Row],[R$ / HORA]] -> 0 | AJ49: =BASE!$W$54 -> 0.79709864 | AK49: =AH49/AJ49 -> 0 | AL49: =AI49/AJ49 -> 0 | AM49: =IF(OR(ServExt8[[#This Row],[TIPO H]]="NORMAL",ServExt8[[#This Row],[HORAS DIA]]>=8),ServExt8[[#This Row],[PESSOAS]]*ServExt8[[#This Row],[DIAS]]*2,0) -> 0 | AN49: =(IF(Z49="","",LOOKUP(Z49,BASE!A$4:A$125,BASE!E$4:E$125)))*ServExt8[[#This Row],[TOTAL HORAS]] -> 0 | AO49: =IF(ServExt8[[#This Row],[TIPO H]]="NORMAL",ServExt8[[#This Row],[PESSOAS]],0) -> 0 | AP49: =IFERROR(ServExt8[[#This Row],[TOTAL3]]*(RESUMO!$F$32/RESUMO!$F$24),0) -> 0 | AU49: 28 | AV49: Projetista Elétrico III
B50: 27 | C50: Sistemas | D50: Serviço | E50: 0 | F50: =LOOKUP('SERVICOS MONTAGEM'!$E$24:$E$63,BASE!A$4:A$125,BASE!B$4:B$125) -> 0 | I50: 8.8 | J50: NORMAL | K50: =_xlfn.IFS('SERVICOS MONTAGEM'!$J$24:$J$58="EXTRA 150%",((1)*2.5),'SERVICOS MONTAGEM'!$J$24:$J$58="EXTRA 100%",((1)*2),'SERVICOS MONTAGEM'!$J$24:$J$58="EXTRA 75%",((1)*1.75),'SERVICOS MONTAGEM'!$J$24:$J$58="EXTRA 50%",((1)*1.5),'SERVICOS MONTAGEM'!$J$24:$J$58="NORMAL",((1))) -> 1 | L50: =ServInt10[[#This Row],[DIAS]]*ServInt10[[#This Row],[PESSOAS]]*ServInt10[[#This Row],[HORAS DIA]] -> 0 | M50: =(IF(ServInt10[[#This Row],[CÓDIGO]]="","",LOOKUP(ServInt10[[#This Row],[CÓDIGO]],BASE!A$4:A$125,BASE!G$4:G$125)))*ServInt10[[#This Row],[HE CALC]] -> 0 | N50: =ServInt10[[#This Row],[TOTAL HORAS]]*ServInt10[[#This Row],[R$ / HORA]] -> 0 | O50: =BASE!$W$54 -> 0.79709864 | P50: =ServInt10[[#This Row],[R$ / HORA]]/ServInt10[[#This Row],[MARK-UP]] -> 0 | Q50: =ServInt10[[#This Row],[TOTAL]]/ServInt10[[#This Row],[MARK-UP]] -> 0 | S50: =(IF(E50="","",LOOKUP(E50,BASE!A$4:A$125,BASE!E$4:E$125)))*ServInt10[[#This Row],[TOTAL HORAS]] -> 0 | T50: =IFERROR(ServInt10[[#This Row],[TOTAL3]]*(RESUMO!$F$32/RESUMO!$F$24),0) -> 0 | W50: 27 | X50: Sistemas | Z50: 0 | AA50: =LOOKUP(Z50,BASE!A$4:A$125,BASE!B$4:B$125) -> 0 | AD50: 8.8 | AE50: NORMAL | AF50: =_xlfn.IFS(ServExt8[[#This Row],[TIPO H]]="EXTRA 150%",((1)*2.5),ServExt8[[#This Row],[TIPO H]]="EXTRA 100%",((1)*2),ServExt8[[#This Row],[TIPO H]]="EXTRA 75%",((1)*1.75),ServExt8[[#This Row],[TIPO H]]="EXTRA 50%",((1)*1.5),ServExt8[[#This Row],[TIPO H]]="NORMAL",((1))) -> 1 | AG50: =AC50*AB50*AD50 -> 0 | AH50: =(IF(Z50="","",LOOKUP(Z50,BASE!A$4:A$125,BASE!H$4:H$125)))*ServExt8[[#This Row],[HE CALC]] -> 0 | AI50: =ServExt8[[#This Row],[TOTAL HORAS]]*ServExt8[[#This Row],[R$ / HORA]] -> 0 | AJ50: =BASE!$W$54 -> 0.79709864 | AK50: =AH50/AJ50 -> 0 | AL50: =AI50/AJ50 -> 0 | AM50: =IF(OR(ServExt8[[#This Row],[TIPO H]]="NORMAL",ServExt8[[#This Row],[HORAS DIA]]>=8),ServExt8[[#This Row],[PESSOAS]]*ServExt8[[#This Row],[DIAS]]*2,0) -> 0 | AN50: =(IF(Z50="","",LOOKUP(Z50,BASE!A$4:A$125,BASE!E$4:E$125)))*ServExt8[[#This Row],[TOTAL HORAS]] -> 0 | AO50: =IF(ServExt8[[#This Row],[TIPO H]]="NORMAL",ServExt8[[#This Row],[PESSOAS]],0) -> 0 | AP50: =IFERROR(ServExt8[[#This Row],[TOTAL3]]*(RESUMO!$F$32/RESUMO!$F$24),0) -> 0 | AU50: 29 | AV50: Projetista Elétrico IV
B51: 28 | C51: Sistemas | D51: Serviço | E51: 0 | F51: =LOOKUP('SERVICOS MONTAGEM'!$E$24:$E$63,BASE!A$4:A$125,BASE!B$4:B$125) -> 0 | I51: 8.8 | J51: NORMAL | K51: =_xlfn.IFS('SERVICOS MONTAGEM'!$J$24:$J$58="EXTRA 150%",((1)*2.5),'SERVICOS MONTAGEM'!$J$24:$J$58="EXTRA 100%",((1)*2),'SERVICOS MONTAGEM'!$J$24:$J$58="EXTRA 75%",((1)*1.75),'SERVICOS MONTAGEM'!$J$24:$J$58="EXTRA 50%",((1)*1.5),'SERVICOS MONTAGEM'!$J$24:$J$58="NORMAL",((1))) -> 1 | L51: =ServInt10[[#This Row],[DIAS]]*ServInt10[[#This Row],[PESSOAS]]*ServInt10[[#This Row],[HORAS DIA]] -> 0 | M51: =(IF(ServInt10[[#This Row],[CÓDIGO]]="","",LOOKUP(ServInt10[[#This Row],[CÓDIGO]],BASE!A$4:A$125,BASE!G$4:G$125)))*ServInt10[[#This Row],[HE CALC]] -> 0 | N51: =ServInt10[[#This Row],[TOTAL HORAS]]*ServInt10[[#This Row],[R$ / HORA]] -> 0 | O51: =BASE!$W$54 -> 0.79709864 | P51: =ServInt10[[#This Row],[R$ / HORA]]/ServInt10[[#This Row],[MARK-UP]] -> 0 | Q51: =ServInt10[[#This Row],[TOTAL]]/ServInt10[[#This Row],[MARK-UP]] -> 0 | S51: =(IF(E51="","",LOOKUP(E51,BASE!A$4:A$125,BASE!E$4:E$125)))*ServInt10[[#This Row],[TOTAL HORAS]] -> 0 | T51: =IFERROR(ServInt10[[#This Row],[TOTAL3]]*(RESUMO!$F$32/RESUMO!$F$24),0) -> 0 | W51: 28 | X51: Sistemas | Z51: 0 | AA51: =LOOKUP(Z51,BASE!A$4:A$125,BASE!B$4:B$125) -> 0 | AD51: 8.8 | AE51: NORMAL | AF51: =_xlfn.IFS(ServExt8[[#This Row],[TIPO H]]="EXTRA 150%",((1)*2.5),ServExt8[[#This Row],[TIPO H]]="EXTRA 100%",((1)*2),ServExt8[[#This Row],[TIPO H]]="EXTRA 75%",((1)*1.75),ServExt8[[#This Row],[TIPO H]]="EXTRA 50%",((1)*1.5),ServExt8[[#This Row],[TIPO H]]="NORMAL",((1))) -> 1 | AG51: =AC51*AB51*AD51 -> 0 | AH51: =(IF(Z51="","",LOOKUP(Z51,BASE!A$4:A$125,BASE!H$4:H$125)))*ServExt8[[#This Row],[HE CALC]] -> 0 | AI51: =ServExt8[[#This Row],[TOTAL HORAS]]*ServExt8[[#This Row],[R$ / HORA]] -> 0 | AJ51: =BASE!$W$54 -> 0.79709864 | AK51: =AH51/AJ51 -> 0 | AL51: =AI51/AJ51 -> 0 | AM51: =IF(OR(ServExt8[[#This Row],[TIPO H]]="NORMAL",ServExt8[[#This Row],[HORAS DIA]]>=8),ServExt8[[#This Row],[PESSOAS]]*ServExt8[[#This Row],[DIAS]]*2,0) -> 0 | AN51: =(IF(Z51="","",LOOKUP(Z51,BASE!A$4:A$125,BASE!E$4:E$125)))*ServExt8[[#This Row],[TOTAL HORAS]] -> 0 | AO51: =IF(ServExt8[[#This Row],[TIPO H]]="NORMAL",ServExt8[[#This Row],[PESSOAS]],0) -> 0 | AP51: =IFERROR(ServExt8[[#This Row],[TOTAL3]]*(RESUMO!$F$32/RESUMO!$F$24),0) -> 0 | AU51: 30 | AV51: Projetista Elétrico V
B52: 29 | C52: Sistemas | D52: Serviço | E52: 0 | F52: =LOOKUP('SERVICOS MONTAGEM'!$E$24:$E$63,BASE!A$4:A$125,BASE!B$4:B$125) -> 0 | I52: 8.8 | J52: NORMAL | K52: =_xlfn.IFS('SERVICOS MONTAGEM'!$J$24:$J$58="EXTRA 150%",((1)*2.5),'SERVICOS MONTAGEM'!$J$24:$J$58="EXTRA 100%",((1)*2),'SERVICOS MONTAGEM'!$J$24:$J$58="EXTRA 75%",((1)*1.75),'SERVICOS MONTAGEM'!$J$24:$J$58="EXTRA 50%",((1)*1.5),'SERVICOS MONTAGEM'!$J$24:$J$58="NORMAL",((1))) -> 1 | L52: =ServInt10[[#This Row],[DIAS]]*ServInt10[[#This Row],[PESSOAS]]*ServInt10[[#This Row],[HORAS DIA]] -> 0 | M52: =(IF(ServInt10[[#This Row],[CÓDIGO]]="","",LOOKUP(ServInt10[[#This Row],[CÓDIGO]],BASE!A$4:A$125,BASE!G$4:G$125)))*ServInt10[[#This Row],[HE CALC]] -> 0 | N52: =ServInt10[[#This Row],[TOTAL HORAS]]*ServInt10[[#This Row],[R$ / HORA]] -> 0 | O52: =BASE!$W$54 -> 0.79709864 | P52: =ServInt10[[#This Row],[R$ / HORA]]/ServInt10[[#This Row],[MARK-UP]] -> 0 | Q52: =ServInt10[[#This Row],[TOTAL]]/ServInt10[[#This Row],[MARK-UP]] -> 0 | S52: =(IF(E52="","",LOOKUP(E52,BASE!A$4:A$125,BASE!E$4:E$125)))*ServInt10[[#This Row],[TOTAL HORAS]] -> 0 | T52: =IFERROR(ServInt10[[#This Row],[TOTAL3]]*(RESUMO!$F$32/RESUMO!$F$24),0) -> 0 | W52: 29 | X52: Sistemas | Z52: 0 | AA52: =LOOKUP(Z52,BASE!A$4:A$125,BASE!B$4:B$125) -> 0 | AD52: 8.8 | AE52: NORMAL | AF52: =_xlfn.IFS(ServExt8[[#This Row],[TIPO H]]="EXTRA 150%",((1)*2.5),ServExt8[[#This Row],[TIPO H]]="EXTRA 100%",((1)*2),ServExt8[[#This Row],[TIPO H]]="EXTRA 75%",((1)*1.75),ServExt8[[#This Row],[TIPO H]]="EXTRA 50%",((1)*1.5),ServExt8[[#This Row],[TIPO H]]="NORMAL",((1))) -> 1 | AG52: =AC52*AB52*AD52 -> 0 | AH52: =(IF(Z52="","",LOOKUP(Z52,BASE!A$4:A$125,BASE!H$4:H$125)))*ServExt8[[#This Row],[HE CALC]] -> 0 | AI52: =ServExt8[[#This Row],[TOTAL HORAS]]*ServExt8[[#This Row],[R$ / HORA]] -> 0 | AJ52: =BASE!$W$54 -> 0.79709864 | AK52: =AH52/AJ52 -> 0 | AL52: =AI52/AJ52 -> 0 | AM52: =IF(OR(ServExt8[[#This Row],[TIPO H]]="NORMAL",ServExt8[[#This Row],[HORAS DIA]]>=8),ServExt8[[#This Row],[PESSOAS]]*ServExt8[[#This Row],[DIAS]]*2,0) -> 0 | AN52: =(IF(Z52="","",LOOKUP(Z52,BASE!A$4:A$125,BASE!E$4:E$125)))*ServExt8[[#This Row],[TOTAL HORAS]] -> 0 | AO52: =IF(ServExt8[[#This Row],[TIPO H]]="NORMAL",ServExt8[[#This Row],[PESSOAS]],0) -> 0 | AP52: =IFERROR(ServExt8[[#This Row],[TOTAL3]]*(RESUMO!$F$32/RESUMO!$F$24),0) -> 0 | AU52: 31 | AV52: Técnico Automação I
B53: 30 | C53: Sistemas | D53: Serviço | E53: 0 | F53: =LOOKUP('SERVICOS MONTAGEM'!$E$24:$E$63,BASE!A$4:A$125,BASE!B$4:B$125) -> 0 | I53: 8.8 | J53: NORMAL | K53: =_xlfn.IFS('SERVICOS MONTAGEM'!$J$24:$J$58="EXTRA 150%",((1)*2.5),'SERVICOS MONTAGEM'!$J$24:$J$58="EXTRA 100%",((1)*2),'SERVICOS MONTAGEM'!$J$24:$J$58="EXTRA 75%",((1)*1.75),'SERVICOS MONTAGEM'!$J$24:$J$58="EXTRA 50%",((1)*1.5),'SERVICOS MONTAGEM'!$J$24:$J$58="NORMAL",((1))) -> 1 | L53: =ServInt10[[#This Row],[DIAS]]*ServInt10[[#This Row],[PESSOAS]]*ServInt10[[#This Row],[HORAS DIA]] -> 0 | M53: =(IF(ServInt10[[#This Row],[CÓDIGO]]="","",LOOKUP(ServInt10[[#This Row],[CÓDIGO]],BASE!A$4:A$125,BASE!G$4:G$125)))*ServInt10[[#This Row],[HE CALC]] -> 0 | N53: =ServInt10[[#This Row],[TOTAL HORAS]]*ServInt10[[#This Row],[R$ / HORA]] -> 0 | O53: =BASE!$W$54 -> 0.79709864 | P53: =ServInt10[[#This Row],[R$ / HORA]]/ServInt10[[#This Row],[MARK-UP]] -> 0 | Q53: =ServInt10[[#This Row],[TOTAL]]/ServInt10[[#This Row],[MARK-UP]] -> 0 | S53: =(IF(E53="","",LOOKUP(E53,BASE!A$4:A$125,BASE!E$4:E$125)))*ServInt10[[#This Row],[TOTAL HORAS]] -> 0 | T53: =IFERROR(ServInt10[[#This Row],[TOTAL3]]*(RESUMO!$F$32/RESUMO!$F$24),0) -> 0 | W53: 30 | X53: Sistemas | Z53: 0 | AA53: =LOOKUP(Z53,BASE!A$4:A$125,BASE!B$4:B$125) -> 0 | AD53: 8.8 | AE53: NORMAL | AF53: =_xlfn.IFS(ServExt8[[#This Row],[TIPO H]]="EXTRA 150%",((1)*2.5),ServExt8[[#This Row],[TIPO H]]="EXTRA 100%",((1)*2),ServExt8[[#This Row],[TIPO H]]="EXTRA 75%",((1)*1.75),ServExt8[[#This Row],[TIPO H]]="EXTRA 50%",((1)*1.5),ServExt8[[#This Row],[TIPO H]]="NORMAL",((1))) -> 1 | AG53: =AC53*AB53*AD53 -> 0 | AH53: =(IF(Z53="","",LOOKUP(Z53,BASE!A$4:A$125,BASE!H$4:H$125)))*ServExt8[[#This Row],[HE CALC]] -> 0 | AI53: =ServExt8[[#This Row],[TOTAL HORAS]]*ServExt8[[#This Row],[R$ / HORA]] -> 0 | AJ53: =BASE!$W$54 -> 0.79709864 | AK53: =AH53/AJ53 -> 0 | AL53: =AI53/AJ53 -> 0 | AM53: =IF(OR(ServExt8[[#This Row],[TIPO H]]="NORMAL",ServExt8[[#This Row],[HORAS DIA]]>=8),ServExt8[[#This Row],[PESSOAS]]*ServExt8[[#This Row],[DIAS]]*2,0) -> 0 | AN53: =(IF(Z53="","",LOOKUP(Z53,BASE!A$4:A$125,BASE!E$4:E$125)))*ServExt8[[#This Row],[TOTAL HORAS]] -> 0 | AO53: =IF(ServExt8[[#This Row],[TIPO H]]="NORMAL",ServExt8[[#This Row],[PESSOAS]],0) -> 0 | AP53: =IFERROR(ServExt8[[#This Row],[TOTAL3]]*(RESUMO!$F$32/RESUMO!$F$24),0) -> 0 | AU53: 32 | AV53: Técnico Automação II
B54: 31 | C54: Sistemas | D54: Serviço | E54: 0 | F54: =LOOKUP('SERVICOS MONTAGEM'!$E$24:$E$63,BASE!A$4:A$125,BASE!B$4:B$125) -> 0 | I54: 8.8 | J54: NORMAL | K54: =_xlfn.IFS('SERVICOS MONTAGEM'!$J$24:$J$58="EXTRA 150%",((1)*2.5),'SERVICOS MONTAGEM'!$J$24:$J$58="EXTRA 100%",((1)*2),'SERVICOS MONTAGEM'!$J$24:$J$58="EXTRA 75%",((1)*1.75),'SERVICOS MONTAGEM'!$J$24:$J$58="EXTRA 50%",((1)*1.5),'SERVICOS MONTAGEM'!$J$24:$J$58="NORMAL",((1))) -> 1 | L54: =ServInt10[[#This Row],[DIAS]]*ServInt10[[#This Row],[PESSOAS]]*ServInt10[[#This Row],[HORAS DIA]] -> 0 | M54: =(IF(ServInt10[[#This Row],[CÓDIGO]]="","",LOOKUP(ServInt10[[#This Row],[CÓDIGO]],BASE!A$4:A$125,BASE!G$4:G$125)))*ServInt10[[#This Row],[HE CALC]] -> 0 | N54: =ServInt10[[#This Row],[TOTAL HORAS]]*ServInt10[[#This Row],[R$ / HORA]] -> 0 | O54: =BASE!$W$54 -> 0.79709864 | P54: =ServInt10[[#This Row],[R$ / HORA]]/ServInt10[[#This Row],[MARK-UP]] -> 0 | Q54: =ServInt10[[#This Row],[TOTAL]]/ServInt10[[#This Row],[MARK-UP]] -> 0 | S54: =(IF(E54="","",LOOKUP(E54,BASE!A$4:A$125,BASE!E$4:E$125)))*ServInt10[[#This Row],[TOTAL HORAS]] -> 0 | T54: =IFERROR(ServInt10[[#This Row],[TOTAL3]]*(RESUMO!$F$32/RESUMO!$F$24),0) -> 0 | W54: 31 | X54: Sistemas | Z54: 0 | AA54: =LOOKUP(Z54,BASE!A$4:A$125,BASE!B$4:B$125) -> 0 | AD54: 8.8 | AE54: NORMAL | AF54: =_xlfn.IFS(ServExt8[[#This Row],[TIPO H]]="EXTRA 150%",((1)*2.5),ServExt8[[#This Row],[TIPO H]]="EXTRA 100%",((1)*2),ServExt8[[#This Row],[TIPO H]]="EXTRA 75%",((1)*1.75),ServExt8[[#This Row],[TIPO H]]="EXTRA 50%",((1)*1.5),ServExt8[[#This Row],[TIPO H]]="NORMAL",((1))) -> 1 | AG54: =AC54*AB54*AD54 -> 0 | AH54: =(IF(Z54="","",LOOKUP(Z54,BASE!A$4:A$125,BASE!H$4:H$125)))*ServExt8[[#This Row],[HE CALC]] -> 0 | AI54: =ServExt8[[#This Row],[TOTAL HORAS]]*ServExt8[[#This Row],[R$ / HORA]] -> 0 | AJ54: =BASE!$W$54 -> 0.79709864 | AK54: =AH54/AJ54 -> 0 | AL54: =AI54/AJ54 -> 0 | AM54: =IF(OR(ServExt8[[#This Row],[TIPO H]]="NORMAL",ServExt8[[#This Row],[HORAS DIA]]>=8),ServExt8[[#This Row],[PESSOAS]]*ServExt8[[#This Row],[DIAS]]*2,0) -> 0 | AN54: =(IF(Z54="","",LOOKUP(Z54,BASE!A$4:A$125,BASE!E$4:E$125)))*ServExt8[[#This Row],[TOTAL HORAS]] -> 0 | AO54: =IF(ServExt8[[#This Row],[TIPO H]]="NORMAL",ServExt8[[#This Row],[PESSOAS]],0) -> 0 | AP54: =IFERROR(ServExt8[[#This Row],[TOTAL3]]*(RESUMO!$F$32/RESUMO!$F$24),0) -> 0 | AU54: 33 | AV54: Técnico Automação III
B55: 32 | C55: Sistemas | D55: Serviço | E55: 0 | F55: =LOOKUP('SERVICOS MONTAGEM'!$E$24:$E$63,BASE!A$4:A$125,BASE!B$4:B$125) -> 0 | I55: 8.8 | J55: NORMAL | K55: =_xlfn.IFS('SERVICOS MONTAGEM'!$J$24:$J$58="EXTRA 150%",((1)*2.5),'SERVICOS MONTAGEM'!$J$24:$J$58="EXTRA 100%",((1)*2),'SERVICOS MONTAGEM'!$J$24:$J$58="EXTRA 75%",((1)*1.75),'SERVICOS MONTAGEM'!$J$24:$J$58="EXTRA 50%",((1)*1.5),'SERVICOS MONTAGEM'!$J$24:$J$58="NORMAL",((1))) -> 1 | L55: =ServInt10[[#This Row],[DIAS]]*ServInt10[[#This Row],[PESSOAS]]*ServInt10[[#This Row],[HORAS DIA]] -> 0 | M55: =(IF(ServInt10[[#This Row],[CÓDIGO]]="","",LOOKUP(ServInt10[[#This Row],[CÓDIGO]],BASE!A$4:A$125,BASE!G$4:G$125)))*ServInt10[[#This Row],[HE CALC]] -> 0 | N55: =ServInt10[[#This Row],[TOTAL HORAS]]*ServInt10[[#This Row],[R$ / HORA]] -> 0 | O55: =BASE!$W$54 -> 0.79709864 | P55: =ServInt10[[#This Row],[R$ / HORA]]/ServInt10[[#This Row],[MARK-UP]] -> 0 | Q55: =ServInt10[[#This Row],[TOTAL]]/ServInt10[[#This Row],[MARK-UP]] -> 0 | S55: =(IF(E55="","",LOOKUP(E55,BASE!A$4:A$125,BASE!E$4:E$125)))*ServInt10[[#This Row],[TOTAL HORAS]] -> 0 | T55: =IFERROR(ServInt10[[#This Row],[TOTAL3]]*(RESUMO!$F$32/RESUMO!$F$24),0) -> 0 | W55: 32 | X55: Sistemas | Z55: 0 | AA55: =LOOKUP(Z55,BASE!A$4:A$125,BASE!B$4:B$125) -> 0 | AD55: 8.8 | AE55: NORMAL | AF55: =_xlfn.IFS(ServExt8[[#This Row],[TIPO H]]="EXTRA 150%",((1)*2.5),ServExt8[[#This Row],[TIPO H]]="EXTRA 100%",((1)*2),ServExt8[[#This Row],[TIPO H]]="EXTRA 75%",((1)*1.75),ServExt8[[#This Row],[TIPO H]]="EXTRA 50%",((1)*1.5),ServExt8[[#This Row],[TIPO H]]="NORMAL",((1))) -> 1 | AG55: =AC55*AB55*AD55 -> 0 | AH55: =(IF(Z55="","",LOOKUP(Z55,BASE!A$4:A$125,BASE!H$4:H$125)))*ServExt8[[#This Row],[HE CALC]] -> 0 | AI55: =ServExt8[[#This Row],[TOTAL HORAS]]*ServExt8[[#This Row],[R$ / HORA]] -> 0 | AJ55: =BASE!$W$54 -> 0.79709864 | AK55: =AH55/AJ55 -> 0 | AL55: =AI55/AJ55 -> 0 | AM55: =IF(OR(ServExt8[[#This Row],[TIPO H]]="NORMAL",ServExt8[[#This Row],[HORAS DIA]]>=8),ServExt8[[#This Row],[PESSOAS]]*ServExt8[[#This Row],[DIAS]]*2,0) -> 0 | AN55: =(IF(Z55="","",LOOKUP(Z55,BASE!A$4:A$125,BASE!E$4:E$125)))*ServExt8[[#This Row],[TOTAL HORAS]] -> 0 | AO55: =IF(ServExt8[[#This Row],[TIPO H]]="NORMAL",ServExt8[[#This Row],[PESSOAS]],0) -> 0 | AP55: =IFERROR(ServExt8[[#This Row],[TOTAL3]]*(RESUMO!$F$32/RESUMO!$F$24),0) -> 0 | AU55: 34 | AV55: Técnico Automação IV
B56: 33 | C56: Sistemas | D56: Serviço | E56: 0 | F56: =LOOKUP('SERVICOS MONTAGEM'!$E$24:$E$63,BASE!A$4:A$125,BASE!B$4:B$125) -> 0 | I56: 8.8 | J56: NORMAL | K56: =_xlfn.IFS('SERVICOS MONTAGEM'!$J$24:$J$58="EXTRA 150%",((1)*2.5),'SERVICOS MONTAGEM'!$J$24:$J$58="EXTRA 100%",((1)*2),'SERVICOS MONTAGEM'!$J$24:$J$58="EXTRA 75%",((1)*1.75),'SERVICOS MONTAGEM'!$J$24:$J$58="EXTRA 50%",((1)*1.5),'SERVICOS MONTAGEM'!$J$24:$J$58="NORMAL",((1))) -> 1 | L56: =ServInt10[[#This Row],[DIAS]]*ServInt10[[#This Row],[PESSOAS]]*ServInt10[[#This Row],[HORAS DIA]] -> 0 | M56: =(IF(ServInt10[[#This Row],[CÓDIGO]]="","",LOOKUP(ServInt10[[#This Row],[CÓDIGO]],BASE!A$4:A$125,BASE!G$4:G$125)))*ServInt10[[#This Row],[HE CALC]] -> 0 | N56: =ServInt10[[#This Row],[TOTAL HORAS]]*ServInt10[[#This Row],[R$ / HORA]] -> 0 | O56: =BASE!$W$54 -> 0.79709864 | P56: =ServInt10[[#This Row],[R$ / HORA]]/ServInt10[[#This Row],[MARK-UP]] -> 0 | Q56: =ServInt10[[#This Row],[TOTAL]]/ServInt10[[#This Row],[MARK-UP]] -> 0 | S56: =(IF(E56="","",LOOKUP(E56,BASE!A$4:A$125,BASE!E$4:E$125)))*ServInt10[[#This Row],[TOTAL HORAS]] -> 0 | T56: =IFERROR(ServInt10[[#This Row],[TOTAL3]]*(RESUMO!$F$32/RESUMO!$F$24),0) -> 0 | W56: 33 | X56: Sistemas | Z56: 0 | AA56: =LOOKUP(Z56,BASE!A$4:A$125,BASE!B$4:B$125) -> 0 | AD56: 8.8 | AE56: NORMAL | AF56: =_xlfn.IFS(ServExt8[[#This Row],[TIPO H]]="EXTRA 150%",((1)*2.5),ServExt8[[#This Row],[TIPO H]]="EXTRA 100%",((1)*2),ServExt8[[#This Row],[TIPO H]]="EXTRA 75%",((1)*1.75),ServExt8[[#This Row],[TIPO H]]="EXTRA 50%",((1)*1.5),ServExt8[[#This Row],[TIPO H]]="NORMAL",((1))) -> 1 | AG56: =AC56*AB56*AD56 -> 0 | AH56: =(IF(Z56="","",LOOKUP(Z56,BASE!A$4:A$125,BASE!H$4:H$125)))*ServExt8[[#This Row],[HE CALC]] -> 0 | AI56: =ServExt8[[#This Row],[TOTAL HORAS]]*ServExt8[[#This Row],[R$ / HORA]] -> 0 | AJ56: =BASE!$W$54 -> 0.79709864 | AK56: =AH56/AJ56 -> 0 | AL56: =AI56/AJ56 -> 0 | AM56: =IF(OR(ServExt8[[#This Row],[TIPO H]]="NORMAL",ServExt8[[#This Row],[HORAS DIA]]>=8),ServExt8[[#This Row],[PESSOAS]]*ServExt8[[#This Row],[DIAS]]*2,0) -> 0 | AN56: =(IF(Z56="","",LOOKUP(Z56,BASE!A$4:A$125,BASE!E$4:E$125)))*ServExt8[[#This Row],[TOTAL HORAS]] -> 0 | AO56: =IF(ServExt8[[#This Row],[TIPO H]]="NORMAL",ServExt8[[#This Row],[PESSOAS]],0) -> 0 | AP56: =IFERROR(ServExt8[[#This Row],[TOTAL3]]*(RESUMO!$F$32/RESUMO!$F$24),0) -> 0 | AU56: 35 | AV56: Técnico Automação V
B57: 34 | C57: Sistemas | D57: Serviço | E57: 0 | F57: =LOOKUP('SERVICOS MONTAGEM'!$E$24:$E$63,BASE!A$4:A$125,BASE!B$4:B$125) -> 0 | I57: 8.8 | J57: NORMAL | K57: =_xlfn.IFS('SERVICOS MONTAGEM'!$J$24:$J$58="EXTRA 150%",((1)*2.5),'SERVICOS MONTAGEM'!$J$24:$J$58="EXTRA 100%",((1)*2),'SERVICOS MONTAGEM'!$J$24:$J$58="EXTRA 75%",((1)*1.75),'SERVICOS MONTAGEM'!$J$24:$J$58="EXTRA 50%",((1)*1.5),'SERVICOS MONTAGEM'!$J$24:$J$58="NORMAL",((1))) -> 1 | L57: =ServInt10[[#This Row],[DIAS]]*ServInt10[[#This Row],[PESSOAS]]*ServInt10[[#This Row],[HORAS DIA]] -> 0 | M57: =(IF(ServInt10[[#This Row],[CÓDIGO]]="","",LOOKUP(ServInt10[[#This Row],[CÓDIGO]],BASE!A$4:A$125,BASE!G$4:G$125)))*ServInt10[[#This Row],[HE CALC]] -> 0 | N57: =ServInt10[[#This Row],[TOTAL HORAS]]*ServInt10[[#This Row],[R$ / HORA]] -> 0 | O57: =BASE!$W$54 -> 0.79709864 | P57: =ServInt10[[#This Row],[R$ / HORA]]/ServInt10[[#This Row],[MARK-UP]] -> 0 | Q57: =ServInt10[[#This Row],[TOTAL]]/ServInt10[[#This Row],[MARK-UP]] -> 0 | S57: =(IF(E57="","",LOOKUP(E57,BASE!A$4:A$125,BASE!E$4:E$125)))*ServInt10[[#This Row],[TOTAL HORAS]] -> 0 | T57: =IFERROR(ServInt10[[#This Row],[TOTAL3]]*(RESUMO!$F$32/RESUMO!$F$24),0) -> 0 | W57: 34 | X57: Sistemas | Z57: 0 | AA57: =LOOKUP(Z57,BASE!A$4:A$125,BASE!B$4:B$125) -> 0 | AD57: 8.8 | AE57: NORMAL | AF57: =_xlfn.IFS(ServExt8[[#This Row],[TIPO H]]="EXTRA 150%",((1)*2.5),ServExt8[[#This Row],[TIPO H]]="EXTRA 100%",((1)*2),ServExt8[[#This Row],[TIPO H]]="EXTRA 75%",((1)*1.75),ServExt8[[#This Row],[TIPO H]]="EXTRA 50%",((1)*1.5),ServExt8[[#This Row],[TIPO H]]="NORMAL",((1))) -> 1 | AG57: =AC57*AB57*AD57 -> 0 | AH57: =(IF(Z57="","",LOOKUP(Z57,BASE!A$4:A$125,BASE!H$4:H$125)))*ServExt8[[#This Row],[HE CALC]] -> 0 | AI57: =ServExt8[[#This Row],[TOTAL HORAS]]*ServExt8[[#This Row],[R$ / HORA]] -> 0 | AJ57: =BASE!$W$54 -> 0.79709864 | AK57: =AH57/AJ57 -> 0 | AL57: =AI57/AJ57 -> 0 | AM57: =IF(OR(ServExt8[[#This Row],[TIPO H]]="NORMAL",ServExt8[[#This Row],[HORAS DIA]]>=8),ServExt8[[#This Row],[PESSOAS]]*ServExt8[[#This Row],[DIAS]]*2,0) -> 0 | AN57: =(IF(Z57="","",LOOKUP(Z57,BASE!A$4:A$125,BASE!E$4:E$125)))*ServExt8[[#This Row],[TOTAL HORAS]] -> 0 | AO57: =IF(ServExt8[[#This Row],[TIPO H]]="NORMAL",ServExt8[[#This Row],[PESSOAS]],0) -> 0 | AP57: =IFERROR(ServExt8[[#This Row],[TOTAL3]]*(RESUMO!$F$32/RESUMO!$F$24),0) -> 0 | AU57: 36 | AV57: Técnico Mecatrônica I
B58: 35 | C58: Sistemas | D58: Serviço | E58: 0 | F58: =LOOKUP('SERVICOS MONTAGEM'!$E$24:$E$63,BASE!A$4:A$125,BASE!B$4:B$125) -> 0 | I58: 8.8 | J58: NORMAL | K58: =_xlfn.IFS('SERVICOS MONTAGEM'!$J$24:$J$58="EXTRA 150%",((1)*2.5),'SERVICOS MONTAGEM'!$J$24:$J$58="EXTRA 100%",((1)*2),'SERVICOS MONTAGEM'!$J$24:$J$58="EXTRA 75%",((1)*1.75),'SERVICOS MONTAGEM'!$J$24:$J$58="EXTRA 50%",((1)*1.5),'SERVICOS MONTAGEM'!$J$24:$J$58="NORMAL",((1))) -> 1 | L58: =ServInt10[[#This Row],[DIAS]]*ServInt10[[#This Row],[PESSOAS]]*ServInt10[[#This Row],[HORAS DIA]] -> 0 | M58: =(IF(ServInt10[[#This Row],[CÓDIGO]]="","",LOOKUP(ServInt10[[#This Row],[CÓDIGO]],BASE!A$4:A$125,BASE!G$4:G$125)))*ServInt10[[#This Row],[HE CALC]] -> 0 | N58: =ServInt10[[#This Row],[TOTAL HORAS]]*ServInt10[[#This Row],[R$ / HORA]] -> 0 | O58: =BASE!$W$54 -> 0.79709864 | P58: =ServInt10[[#This Row],[R$ / HORA]]/ServInt10[[#This Row],[MARK-UP]] -> 0 | Q58: =ServInt10[[#This Row],[TOTAL]]/ServInt10[[#This Row],[MARK-UP]] -> 0 | S58: =(IF(E58="","",LOOKUP(E58,BASE!A$4:A$125,BASE!E$4:E$125)))*ServInt10[[#This Row],[TOTAL HORAS]] -> 0 | T58: =IFERROR(ServInt10[[#This Row],[TOTAL3]]*(RESUMO!$F$32/RESUMO!$F$24),0) -> 0 | W58: 35 | X58: Sistemas | Z58: 0 | AA58: =LOOKUP(Z58,BASE!A$4:A$125,BASE!B$4:B$125) -> 0 | AD58: 8.8 | AE58: NORMAL | AF58: =_xlfn.IFS(ServExt8[[#This Row],[TIPO H]]="EXTRA 150%",((1)*2.5),ServExt8[[#This Row],[TIPO H]]="EXTRA 100%",((1)*2),ServExt8[[#This Row],[TIPO H]]="EXTRA 75%",((1)*1.75),ServExt8[[#This Row],[TIPO H]]="EXTRA 50%",((1)*1.5),ServExt8[[#This Row],[TIPO H]]="NORMAL",((1))) -> 1 | AG58: =AC58*AB58*AD58 -> 0 | AH58: =(IF(Z58="","",LOOKUP(Z58,BASE!A$4:A$125,BASE!H$4:H$125)))*ServExt8[[#This Row],[HE CALC]] -> 0 | AI58: =ServExt8[[#This Row],[TOTAL HORAS]]*ServExt8[[#This Row],[R$ / HORA]] -> 0 | AJ58: =BASE!$W$54 -> 0.79709864 | AK58: =AH58/AJ58 -> 0 | AL58: =AI58/AJ58 -> 0 | AM58: =IF(OR(ServExt8[[#This Row],[TIPO H]]="NORMAL",ServExt8[[#This Row],[HORAS DIA]]>=8),ServExt8[[#This Row],[PESSOAS]]*ServExt8[[#This Row],[DIAS]]*2,0) -> 0 | AN58: =(IF(Z58="","",LOOKUP(Z58,BASE!A$4:A$125,BASE!E$4:E$125)))*ServExt8[[#This Row],[TOTAL HORAS]] -> 0 | AO58: =IF(ServExt8[[#This Row],[TIPO H]]="NORMAL",ServExt8[[#This Row],[PESSOAS]],0) -> 0 | AP58: =IFERROR(ServExt8[[#This Row],[TOTAL3]]*(RESUMO!$F$32/RESUMO!$F$24),0) -> 0 | AU58: 37 | AV58: Técnico Mecatrônica II
B59: 36 | C59: Sistemas | D59: Serviço | E59: 0 | F59: =LOOKUP('SERVICOS MONTAGEM'!$E$24:$E$63,BASE!A$4:A$125,BASE!B$4:B$125) -> 0 | I59: 8.8 | J59: NORMAL | K59: =_xlfn.IFS('SERVICOS MONTAGEM'!$J$24:$J$63="EXTRA 150%",((1)*2.5),'SERVICOS MONTAGEM'!$J$24:$J$63="EXTRA 100%",((1)*2),'SERVICOS MONTAGEM'!$J$24:$J$63="EXTRA 75%",((1)*1.75),'SERVICOS MONTAGEM'!$J$24:$J$63="EXTRA 50%",((1)*1.5),'SERVICOS MONTAGEM'!$J$24:$J$63="NORMAL",((1))) -> 1 | L59: =ServInt10[[#This Row],[DIAS]]*ServInt10[[#This Row],[PESSOAS]]*ServInt10[[#This Row],[HORAS DIA]] -> 0 | M59: =(IF(ServInt10[[#This Row],[CÓDIGO]]="","",LOOKUP(ServInt10[[#This Row],[CÓDIGO]],BASE!A$4:A$125,BASE!G$4:G$125)))*ServInt10[[#This Row],[HE CALC]] -> 0 | N59: =ServInt10[[#This Row],[TOTAL HORAS]]*ServInt10[[#This Row],[R$ / HORA]] -> 0 | O59: =BASE!$W$54 -> 0.79709864 | P59: =ServInt10[[#This Row],[R$ / HORA]]/ServInt10[[#This Row],[MARK-UP]] -> 0 | Q59: =ServInt10[[#This Row],[TOTAL]]/ServInt10[[#This Row],[MARK-UP]] -> 0 | S59: =(IF(E59="","",LOOKUP(E59,BASE!A$4:A$125,BASE!E$4:E$125)))*ServInt10[[#This Row],[TOTAL HORAS]] -> 0 | T59: =IFERROR(ServInt10[[#This Row],[TOTAL3]]*(RESUMO!$F$32/RESUMO!$F$24),0) -> 0 | W59: 36 | X59: Sistemas | Z59: 0 | AA59: =LOOKUP(Z59,BASE!A$4:A$125,BASE!B$4:B$125) -> 0 | AD59: 8.8 | AE59: NORMAL | AF59: =_xlfn.IFS(ServExt8[[#This Row],[TIPO H]]="EXTRA 150%",((1)*2.5),ServExt8[[#This Row],[TIPO H]]="EXTRA 100%",((1)*2),ServExt8[[#This Row],[TIPO H]]="EXTRA 75%",((1)*1.75),ServExt8[[#This Row],[TIPO H]]="EXTRA 50%",((1)*1.5),ServExt8[[#This Row],[TIPO H]]="NORMAL",((1))) -> 1 | AG59: =AC59*AB59*AD59 -> 0 | AH59: =(IF(Z59="","",LOOKUP(Z59,BASE!A$4:A$125,BASE!H$4:H$125)))*ServExt8[[#This Row],[HE CALC]] -> 0 | AI59: =ServExt8[[#This Row],[TOTAL HORAS]]*ServExt8[[#This Row],[R$ / HORA]] -> 0 | AJ59: =BASE!$W$54 -> 0.79709864 | AK59: =AH59/AJ59 -> 0 | AL59: =AI59/AJ59 -> 0 | AM59: =IF(OR(ServExt8[[#This Row],[TIPO H]]="NORMAL",ServExt8[[#This Row],[HORAS DIA]]>=8),ServExt8[[#This Row],[PESSOAS]]*ServExt8[[#This Row],[DIAS]]*2,0) -> 0 | AN59: =(IF(Z59="","",LOOKUP(Z59,BASE!A$4:A$125,BASE!E$4:E$125)))*ServExt8[[#This Row],[TOTAL HORAS]] -> 0 | AO59: =IF(ServExt8[[#This Row],[TIPO H]]="NORMAL",ServExt8[[#This Row],[PESSOAS]],0) -> 0 | AP59: =IFERROR(ServExt8[[#This Row],[TOTAL3]]*(RESUMO!$F$32/RESUMO!$F$24),0) -> 0 | AU59: 38 | AV59: Técnico Mecatrônica III
B60: 37 | C60: Sistemas | D60: Serviço | E60: 0 | F60: =LOOKUP('SERVICOS MONTAGEM'!$E$24:$E$63,BASE!A$4:A$125,BASE!B$4:B$125) -> 0 | I60: 8.8 | J60: NORMAL | K60: =_xlfn.IFS('SERVICOS MONTAGEM'!$J$24:$J$63="EXTRA 150%",((1)*2.5),'SERVICOS MONTAGEM'!$J$24:$J$63="EXTRA 100%",((1)*2),'SERVICOS MONTAGEM'!$J$24:$J$63="EXTRA 75%",((1)*1.75),'SERVICOS MONTAGEM'!$J$24:$J$63="EXTRA 50%",((1)*1.5),'SERVICOS MONTAGEM'!$J$24:$J$63="NORMAL",((1))) -> 1 | L60: =ServInt10[[#This Row],[DIAS]]*ServInt10[[#This Row],[PESSOAS]]*ServInt10[[#This Row],[HORAS DIA]] -> 0 | M60: =(IF(ServInt10[[#This Row],[CÓDIGO]]="","",LOOKUP(ServInt10[[#This Row],[CÓDIGO]],BASE!A$4:A$125,BASE!G$4:G$125)))*ServInt10[[#This Row],[HE CALC]] -> 0 | N60: =ServInt10[[#This Row],[TOTAL HORAS]]*ServInt10[[#This Row],[R$ / HORA]] -> 0 | O60: =BASE!$W$54 -> 0.79709864 | P60: =ServInt10[[#This Row],[R$ / HORA]]/ServInt10[[#This Row],[MARK-UP]] -> 0 | Q60: =ServInt10[[#This Row],[TOTAL]]/ServInt10[[#This Row],[MARK-UP]] -> 0 | S60: =(IF(E60="","",LOOKUP(E60,BASE!A$4:A$125,BASE!E$4:E$125)))*ServInt10[[#This Row],[TOTAL HORAS]] -> 0 | T60: =IFERROR(ServInt10[[#This Row],[TOTAL3]]*(RESUMO!$F$32/RESUMO!$F$24),0) -> 0 | W60: 37 | X60: Sistemas | Z60: 0 | AA60: =LOOKUP(Z60,BASE!A$4:A$125,BASE!B$4:B$125) -> 0 | AD60: 8.8 | AE60: NORMAL | AF60: =_xlfn.IFS(ServExt8[[#This Row],[TIPO H]]="EXTRA 150%",((1)*2.5),ServExt8[[#This Row],[TIPO H]]="EXTRA 100%",((1)*2),ServExt8[[#This Row],[TIPO H]]="EXTRA 75%",((1)*1.75),ServExt8[[#This Row],[TIPO H]]="EXTRA 50%",((1)*1.5),ServExt8[[#This Row],[TIPO H]]="NORMAL",((1))) -> 1 | AG60: =AC60*AB60*AD60 -> 0 | AH60: =(IF(Z60="","",LOOKUP(Z60,BASE!A$4:A$125,BASE!H$4:H$125)))*ServExt8[[#This Row],[HE CALC]] -> 0 | AI60: =ServExt8[[#This Row],[TOTAL HORAS]]*ServExt8[[#This Row],[R$ / HORA]] -> 0 | AJ60: =BASE!$W$54 -> 0.79709864 | AK60: =AH60/AJ60 -> 0 | AL60: =AI60/AJ60 -> 0 | AM60: =IF(OR(ServExt8[[#This Row],[TIPO H]]="NORMAL",ServExt8[[#This Row],[HORAS DIA]]>=8),ServExt8[[#This Row],[PESSOAS]]*ServExt8[[#This Row],[DIAS]]*2,0) -> 0 | AN60: =(IF(Z60="","",LOOKUP(Z60,BASE!A$4:A$125,BASE!E$4:E$125)))*ServExt8[[#This Row],[TOTAL HORAS]] -> 0 | AO60: =IF(ServExt8[[#This Row],[TIPO H]]="NORMAL",ServExt8[[#This Row],[PESSOAS]],0) -> 0 | AP60: =IFERROR(ServExt8[[#This Row],[TOTAL3]]*(RESUMO!$F$32/RESUMO!$F$24),0) -> 0 | AU60: 39 | AV60: Técnico Mecatrônica IV
B61: 38 | C61: Sistemas | D61: Serviço | E61: 0 | F61: =LOOKUP('SERVICOS MONTAGEM'!$E$24:$E$63,BASE!A$4:A$125,BASE!B$4:B$125) -> 0 | I61: 8.8 | J61: NORMAL | K61: =_xlfn.IFS('SERVICOS MONTAGEM'!$J$24:$J$63="EXTRA 150%",((1)*2.5),'SERVICOS MONTAGEM'!$J$24:$J$63="EXTRA 100%",((1)*2),'SERVICOS MONTAGEM'!$J$24:$J$63="EXTRA 75%",((1)*1.75),'SERVICOS MONTAGEM'!$J$24:$J$63="EXTRA 50%",((1)*1.5),'SERVICOS MONTAGEM'!$J$24:$J$63="NORMAL",((1))) -> 1 | L61: =ServInt10[[#This Row],[DIAS]]*ServInt10[[#This Row],[PESSOAS]]*ServInt10[[#This Row],[HORAS DIA]] -> 0 | M61: =(IF(ServInt10[[#This Row],[CÓDIGO]]="","",LOOKUP(ServInt10[[#This Row],[CÓDIGO]],BASE!A$4:A$125,BASE!G$4:G$125)))*ServInt10[[#This Row],[HE CALC]] -> 0 | N61: =ServInt10[[#This Row],[TOTAL HORAS]]*ServInt10[[#This Row],[R$ / HORA]] -> 0 | O61: =BASE!$W$54 -> 0.79709864 | P61: =ServInt10[[#This Row],[R$ / HORA]]/ServInt10[[#This Row],[MARK-UP]] -> 0 | Q61: =ServInt10[[#This Row],[TOTAL]]/ServInt10[[#This Row],[MARK-UP]] -> 0 | S61: =(IF(E61="","",LOOKUP(E61,BASE!A$4:A$125,BASE!E$4:E$125)))*ServInt10[[#This Row],[TOTAL HORAS]] -> 0 | T61: =IFERROR(ServInt10[[#This Row],[TOTAL3]]*(RESUMO!$F$32/RESUMO!$F$24),0) -> 0 | W61: 38 | X61: Sistemas | Z61: 0 | AA61: =LOOKUP(Z61,BASE!A$4:A$125,BASE!B$4:B$125) -> 0 | AD61: 8.8 | AE61: NORMAL | AF61: =_xlfn.IFS(ServExt8[[#This Row],[TIPO H]]="EXTRA 150%",((1)*2.5),ServExt8[[#This Row],[TIPO H]]="EXTRA 100%",((1)*2),ServExt8[[#This Row],[TIPO H]]="EXTRA 75%",((1)*1.75),ServExt8[[#This Row],[TIPO H]]="EXTRA 50%",((1)*1.5),ServExt8[[#This Row],[TIPO H]]="NORMAL",((1))) -> 1 | AG61: =AC61*AB61*AD61 -> 0 | AH61: =(IF(Z61="","",LOOKUP(Z61,BASE!A$4:A$125,BASE!H$4:H$125)))*ServExt8[[#This Row],[HE CALC]] -> 0 | AI61: =ServExt8[[#This Row],[TOTAL HORAS]]*ServExt8[[#This Row],[R$ / HORA]] -> 0 | AJ61: =BASE!$W$54 -> 0.79709864 | AK61: =AH61/AJ61 -> 0 | AL61: =AI61/AJ61 -> 0 | AM61: =IF(OR(ServExt8[[#This Row],[TIPO H]]="NORMAL",ServExt8[[#This Row],[HORAS DIA]]>=8),ServExt8[[#This Row],[PESSOAS]]*ServExt8[[#This Row],[DIAS]]*2,0) -> 0 | AN61: =(IF(Z61="","",LOOKUP(Z61,BASE!A$4:A$125,BASE!E$4:E$125)))*ServExt8[[#This Row],[TOTAL HORAS]] -> 0 | AO61: =IF(ServExt8[[#This Row],[TIPO H]]="NORMAL",ServExt8[[#This Row],[PESSOAS]],0) -> 0 | AP61: =IFERROR(ServExt8[[#This Row],[TOTAL3]]*(RESUMO!$F$32/RESUMO!$F$24),0) -> 0 | AU61: 40 | AV61: Técnico Mecatrônica V
B62: 39 | C62: Sistemas | D62: Serviço | E62: 0 | F62: =LOOKUP('SERVICOS MONTAGEM'!$E$24:$E$63,BASE!A$4:A$125,BASE!B$4:B$125) -> 0 | I62: 8.8 | J62: NORMAL | K62: =_xlfn.IFS('SERVICOS MONTAGEM'!$J$24:$J$63="EXTRA 150%",((1)*2.5),'SERVICOS MONTAGEM'!$J$24:$J$63="EXTRA 100%",((1)*2),'SERVICOS MONTAGEM'!$J$24:$J$63="EXTRA 75%",((1)*1.75),'SERVICOS MONTAGEM'!$J$24:$J$63="EXTRA 50%",((1)*1.5),'SERVICOS MONTAGEM'!$J$24:$J$63="NORMAL",((1))) -> 1 | L62: =ServInt10[[#This Row],[DIAS]]*ServInt10[[#This Row],[PESSOAS]]*ServInt10[[#This Row],[HORAS DIA]] -> 0 | M62: =(IF(ServInt10[[#This Row],[CÓDIGO]]="","",LOOKUP(ServInt10[[#This Row],[CÓDIGO]],BASE!A$4:A$125,BASE!G$4:G$125)))*ServInt10[[#This Row],[HE CALC]] -> 0 | N62: =ServInt10[[#This Row],[TOTAL HORAS]]*ServInt10[[#This Row],[R$ / HORA]] -> 0 | O62: =BASE!$W$54 -> 0.79709864 | P62: =ServInt10[[#This Row],[R$ / HORA]]/ServInt10[[#This Row],[MARK-UP]] -> 0 | Q62: =ServInt10[[#This Row],[TOTAL]]/ServInt10[[#This Row],[MARK-UP]] -> 0 | S62: =(IF(E62="","",LOOKUP(E62,BASE!A$4:A$125,BASE!E$4:E$125)))*ServInt10[[#This Row],[TOTAL HORAS]] -> 0 | T62: =IFERROR(ServInt10[[#This Row],[TOTAL3]]*(RESUMO!$F$32/RESUMO!$F$24),0) -> 0 | W62: 39 | X62: Sistemas | Z62: 0 | AA62: =LOOKUP(Z62,BASE!A$4:A$125,BASE!B$4:B$125) -> 0 | AD62: 8.8 | AE62: NORMAL | AF62: =_xlfn.IFS(ServExt8[[#This Row],[TIPO H]]="EXTRA 150%",((1)*2.5),ServExt8[[#This Row],[TIPO H]]="EXTRA 100%",((1)*2),ServExt8[[#This Row],[TIPO H]]="EXTRA 75%",((1)*1.75),ServExt8[[#This Row],[TIPO H]]="EXTRA 50%",((1)*1.5),ServExt8[[#This Row],[TIPO H]]="NORMAL",((1))) -> 1 | AG62: =AC62*AB62*AD62 -> 0 | AH62: =(IF(Z62="","",LOOKUP(Z62,BASE!A$4:A$125,BASE!H$4:H$125)))*ServExt8[[#This Row],[HE CALC]] -> 0 | AI62: =ServExt8[[#This Row],[TOTAL HORAS]]*ServExt8[[#This Row],[R$ / HORA]] -> 0 | AJ62: =BASE!$W$54 -> 0.79709864 | AK62: =AH62/AJ62 -> 0 | AL62: =AI62/AJ62 -> 0 | AM62: =IF(OR(ServExt8[[#This Row],[TIPO H]]="NORMAL",ServExt8[[#This Row],[HORAS DIA]]>=8),ServExt8[[#This Row],[PESSOAS]]*ServExt8[[#This Row],[DIAS]]*2,0) -> 0 | AN62: =(IF(Z62="","",LOOKUP(Z62,BASE!A$4:A$125,BASE!E$4:E$125)))*ServExt8[[#This Row],[TOTAL HORAS]] -> 0 | AO62: =IF(ServExt8[[#This Row],[TIPO H]]="NORMAL",ServExt8[[#This Row],[PESSOAS]],0) -> 0 | AP62: =IFERROR(ServExt8[[#This Row],[TOTAL3]]*(RESUMO!$F$32/RESUMO!$F$24),0) -> 0 | AU62: 41 | AV62: Eletricista Instalador I
B63: 40 | C63: Sistemas | D63: Serviço | E63: 0 | F63: =LOOKUP('SERVICOS MONTAGEM'!$E$24:$E$63,BASE!A$4:A$125,BASE!B$4:B$125) -> 0 | I63: 8.8 | J63: NORMAL | K63: =_xlfn.IFS('SERVICOS MONTAGEM'!$J$24:$J$63="EXTRA 150%",((1)*2.5),'SERVICOS MONTAGEM'!$J$24:$J$63="EXTRA 100%",((1)*2),'SERVICOS MONTAGEM'!$J$24:$J$63="EXTRA 75%",((1)*1.75),'SERVICOS MONTAGEM'!$J$24:$J$63="EXTRA 50%",((1)*1.5),'SERVICOS MONTAGEM'!$J$24:$J$63="NORMAL",((1))) -> 1 | L63: =ServInt10[[#This Row],[DIAS]]*ServInt10[[#This Row],[PESSOAS]]*ServInt10[[#This Row],[HORAS DIA]] -> 0 | M63: =(IF(ServInt10[[#This Row],[CÓDIGO]]="","",LOOKUP(ServInt10[[#This Row],[CÓDIGO]],BASE!A$4:A$125,BASE!G$4:G$125)))*ServInt10[[#This Row],[HE CALC]] -> 0 | N63: =ServInt10[[#This Row],[TOTAL HORAS]]*ServInt10[[#This Row],[R$ / HORA]] -> 0 | O63: =BASE!$W$54 -> 0.79709864 | P63: =ServInt10[[#This Row],[R$ / HORA]]/ServInt10[[#This Row],[MARK-UP]] -> 0 | Q63: =ServInt10[[#This Row],[TOTAL]]/ServInt10[[#This Row],[MARK-UP]] -> 0 | S63: =(IF(E63="","",LOOKUP(E63,BASE!A$4:A$125,BASE!E$4:E$125)))*ServInt10[[#This Row],[TOTAL HORAS]] -> 0 | T63: =IFERROR(ServInt10[[#This Row],[TOTAL3]]*(RESUMO!$F$32/RESUMO!$F$24),0) -> 0 | W63: 40 | X63: Sistemas | Z63: 0 | AA63: =LOOKUP(Z63,BASE!A$4:A$125,BASE!B$4:B$125) -> 0 | AD63: 8.8 | AE63: NORMAL | AF63: =_xlfn.IFS(ServExt8[[#This Row],[TIPO H]]="EXTRA 150%",((1)*2.5),ServExt8[[#This Row],[TIPO H]]="EXTRA 100%",((1)*2),ServExt8[[#This Row],[TIPO H]]="EXTRA 75%",((1)*1.75),ServExt8[[#This Row],[TIPO H]]="EXTRA 50%",((1)*1.5),ServExt8[[#This Row],[TIPO H]]="NORMAL",((1))) -> 1 | AG63: =AC63*AB63*AD63 -> 0 | AH63: =(IF(Z63="","",LOOKUP(Z63,BASE!A$4:A$125,BASE!H$4:H$125)))*ServExt8[[#This Row],[HE CALC]] -> 0 | AI63: =ServExt8[[#This Row],[TOTAL HORAS]]*ServExt8[[#This Row],[R$ / HORA]] -> 0 | AJ63: =BASE!$W$54 -> 0.79709864 | AK63: =AH63/AJ63 -> 0 | AL63: =AI63/AJ63 -> 0 | AM63: =IF(OR(ServExt8[[#This Row],[TIPO H]]="NORMAL",ServExt8[[#This Row],[HORAS DIA]]>=8),ServExt8[[#This Row],[PESSOAS]]*ServExt8[[#This Row],[DIAS]]*2,0) -> 0 | AN63: =(IF(Z63="","",LOOKUP(Z63,BASE!A$4:A$125,BASE!E$4:E$125)))*ServExt8[[#This Row],[TOTAL HORAS]] -> 0 | AO63: =IF(ServExt8[[#This Row],[TIPO H]]="NORMAL",ServExt8[[#This Row],[PESSOAS]],0) -> 0 | AP63: =IFERROR(ServExt8[[#This Row],[TOTAL3]]*(RESUMO!$F$32/RESUMO!$F$24),0) -> 0 | AU63: 42 | AV63: Eletricista Instalador II
B64: 8 | G64: =SUBTOTAL(109,ServInt10[DIAS]) -> 0 | N64: =SUBTOTAL(109,ServInt10[TOTAL]) -> 0 | Q64: =SUBTOTAL(109,ServInt10[TOTAL3]) -> 0 | R64: =SUBTOTAL(103,ServInt10[TOTAL4]) -> 0 | S64: =SUBTOTAL(109,ServInt10[MULTA]) -> 0 | T64: =SUBTOTAL(109,ServInt10[VENDA COM IMPOSTOS]) -> 0 | W64: 41 | X64: Sistemas | Z64: 0 | AA64: =LOOKUP(Z64,BASE!A$4:A$125,BASE!B$4:B$125) -> 0 | AD64: 8.8 | AE64: NORMAL | AF64: =_xlfn.IFS(ServExt8[[#This Row],[TIPO H]]="EXTRA 150%",((1)*2.5),ServExt8[[#This Row],[TIPO H]]="EXTRA 100%",((1)*2),ServExt8[[#This Row],[TIPO H]]="EXTRA 75%",((1)*1.75),ServExt8[[#This Row],[TIPO H]]="EXTRA 50%",((1)*1.5),ServExt8[[#This Row],[TIPO H]]="NORMAL",((1))) -> 1 | AG64: =AC64*AB64*AD64 -> 0 | AH64: =(IF(Z64="","",LOOKUP(Z64,BASE!A$4:A$125,BASE!H$4:H$125)))*ServExt8[[#This Row],[HE CALC]] -> 0 | AI64: =ServExt8[[#This Row],[TOTAL HORAS]]*ServExt8[[#This Row],[R$ / HORA]] -> 0 | AJ64: =BASE!$W$54 -> 0.79709864 | AK64: =AH64/AJ64 -> 0 | AL64: =AI64/AJ64 -> 0 | AM64: =IF(OR(ServExt8[[#This Row],[TIPO H]]="NORMAL",ServExt8[[#This Row],[HORAS DIA]]>=8),ServExt8[[#This Row],[PESSOAS]]*ServExt8[[#This Row],[DIAS]]*2,0) -> 0 | AN64: =(IF(Z64="","",LOOKUP(Z64,BASE!A$4:A$125,BASE!E$4:E$125)))*ServExt8[[#This Row],[TOTAL HORAS]] -> 0 | AO64: =IF(ServExt8[[#This Row],[TIPO H]]="NORMAL",ServExt8[[#This Row],[PESSOAS]],0) -> 0 | AP64: =IFERROR(ServExt8[[#This Row],[TOTAL3]]*(RESUMO!$F$32/RESUMO!$F$24),0) -> 0 | AU64: 43 | AV64: Eletricista Instalador III
B65: 0 | W65: 42 | X65: Sistemas | Z65: 0 | AA65: =LOOKUP(Z65,BASE!A$4:A$125,BASE!B$4:B$125) -> 0 | AD65: 8.8 | AE65: NORMAL | AF65: =_xlfn.IFS(ServExt8[[#This Row],[TIPO H]]="EXTRA 150%",((1)*2.5),ServExt8[[#This Row],[TIPO H]]="EXTRA 100%",((1)*2),ServExt8[[#This Row],[TIPO H]]="EXTRA 75%",((1)*1.75),ServExt8[[#This Row],[TIPO H]]="EXTRA 50%",((1)*1.5),ServExt8[[#This Row],[TIPO H]]="NORMAL",((1))) -> 1 | AG65: =AC65*AB65*AD65 -> 0 | AH65: =(IF(Z65="","",LOOKUP(Z65,BASE!A$4:A$125,BASE!H$4:H$125)))*ServExt8[[#This Row],[HE CALC]] -> 0 | AI65: =ServExt8[[#This Row],[TOTAL HORAS]]*ServExt8[[#This Row],[R$ / HORA]] -> 0 | AJ65: =BASE!$W$54 -> 0.79709864 | AK65: =AH65/AJ65 -> 0 | AL65: =AI65/AJ65 -> 0 | AM65: =IF(OR(ServExt8[[#This Row],[TIPO H]]="NORMAL",ServExt8[[#This Row],[HORAS DIA]]>=8),ServExt8[[#This Row],[PESSOAS]]*ServExt8[[#This Row],[DIAS]]*2,0) -> 0 | AN65: =(IF(Z65="","",LOOKUP(Z65,BASE!A$4:A$125,BASE!E$4:E$125)))*ServExt8[[#This Row],[TOTAL HORAS]] -> 0 | AO65: =IF(ServExt8[[#This Row],[TIPO H]]="NORMAL",ServExt8[[#This Row],[PESSOAS]],0) -> 0 | AP65: =IFERROR(ServExt8[[#This Row],[TOTAL3]]*(RESUMO!$F$32/RESUMO!$F$24),0) -> 0 | AU65: 44 | AV65: Eletricista Instalador IV
B66: 0 | W66: 43 | X66: Sistemas | Z66: 0 | AA66: =LOOKUP(Z66,BASE!A$4:A$125,BASE!B$4:B$125) -> 0 | AD66: 8.8 | AE66: NORMAL | AF66: =_xlfn.IFS(ServExt8[[#This Row],[TIPO H]]="EXTRA 150%",((1)*2.5),ServExt8[[#This Row],[TIPO H]]="EXTRA 100%",((1)*2),ServExt8[[#This Row],[TIPO H]]="EXTRA 75%",((1)*1.75),ServExt8[[#This Row],[TIPO H]]="EXTRA 50%",((1)*1.5),ServExt8[[#This Row],[TIPO H]]="NORMAL",((1))) -> 1 | AG66: =AC66*AB66*AD66 -> 0 | AH66: =(IF(Z66="","",LOOKUP(Z66,BASE!A$4:A$125,BASE!H$4:H$125)))*ServExt8[[#This Row],[HE CALC]] -> 0 | AI66: =ServExt8[[#This Row],[TOTAL HORAS]]*ServExt8[[#This Row],[R$ / HORA]] -> 0 | AJ66: =BASE!$W$54 -> 0.79709864 | AK66: =AH66/AJ66 -> 0 | AL66: =AI66/AJ66 -> 0 | AM66: =IF(OR(ServExt8[[#This Row],[TIPO H]]="NORMAL",ServExt8[[#This Row],[HORAS DIA]]>=8),ServExt8[[#This Row],[PESSOAS]]*ServExt8[[#This Row],[DIAS]]*2,0) -> 0 | AN66: =(IF(Z66="","",LOOKUP(Z66,BASE!A$4:A$125,BASE!E$4:E$125)))*ServExt8[[#This Row],[TOTAL HORAS]] -> 0 | AO66: =IF(ServExt8[[#This Row],[TIPO H]]="NORMAL",ServExt8[[#This Row],[PESSOAS]],0) -> 0 | AP66: =IFERROR(ServExt8[[#This Row],[TOTAL3]]*(RESUMO!$F$32/RESUMO!$F$24),0) -> 0 | AU66: 45 | AV66: Eletricista Instalador V
W67: 44 | X67: Sistemas | Z67: 0 | AA67: =LOOKUP(Z67,BASE!A$4:A$125,BASE!B$4:B$125) -> 0 | AD67: 8.8 | AE67: NORMAL | AF67: =_xlfn.IFS(ServExt8[[#This Row],[TIPO H]]="EXTRA 150%",((1)*2.5),ServExt8[[#This Row],[TIPO H]]="EXTRA 100%",((1)*2),ServExt8[[#This Row],[TIPO H]]="EXTRA 75%",((1)*1.75),ServExt8[[#This Row],[TIPO H]]="EXTRA 50%",((1)*1.5),ServExt8[[#This Row],[TIPO H]]="NORMAL",((1))) -> 1 | AG67: =AC67*AB67*AD67 -> 0 | AH67: =(IF(Z67="","",LOOKUP(Z67,BASE!A$4:A$125,BASE!H$4:H$125)))*ServExt8[[#This Row],[HE CALC]] -> 0 | AI67: =ServExt8[[#This Row],[TOTAL HORAS]]*ServExt8[[#This Row],[R$ / HORA]] -> 0 | AJ67: =BASE!$W$54 -> 0.79709864 | AK67: =AH67/AJ67 -> 0 | AL67: =AI67/AJ67 -> 0 | AM67: =IF(OR(ServExt8[[#This Row],[TIPO H]]="NORMAL",ServExt8[[#This Row],[HORAS DIA]]>=8),ServExt8[[#This Row],[PESSOAS]]*ServExt8[[#This Row],[DIAS]]*2,0) -> 0 | AN67: =(IF(Z67="","",LOOKUP(Z67,BASE!A$4:A$125,BASE!E$4:E$125)))*ServExt8[[#This Row],[TOTAL HORAS]] -> 0 | AO67: =IF(ServExt8[[#This Row],[TIPO H]]="NORMAL",ServExt8[[#This Row],[PESSOAS]],0) -> 0 | AP67: =IFERROR(ServExt8[[#This Row],[TOTAL3]]*(RESUMO!$F$32/RESUMO!$F$24),0) -> 0 | AU67: 46 | AV67: Eletricista Força e Comando I
